Workbook

Sheet README
A1: Shea Resilience NPV Model: Tema factory and Tamale shea supply
A3: Purpose | B3: Compares climate-adaptation investments for a Tema (Free Zone) factory that buys crude shea butter from women processors around Tamale, refines it and makes cosmetics. Values are in constant 2026 USD; cedi-sourced figures were converted at GH₵11.55/USD.
A4: Case basis | B4: Case scenario built on market benchmarks, not company records: 200 t crude butter a year, bare baseline (no backup power, no insurance), 85% exports.
A5: How to use | B5: 1) Change blue cells on Inputs (Low/Base/High columns) or pick the case in column H. 2) Set the hazard scenario with G09. 3) Change the export share with G05. 4) Switch options on in Portfolio. 5) Read Results and Value chain.
A6: Colour code | B6: Blue text = input you can change · Black = formula · Green = link to another sheet · Yellow fill = key result or switch.
A7: Confidence tags | B7: Local field evidence = Ghana or primary market source · Transferable evidence = other countries or global data · Analyst assumption = reasoned estimate or design choice, editable. Every input carries its sources, the quoted figure, a rationale and a verdict (Confirmed / Adjusted / Unsupported / New).
A8: Key switches | B8: G09 hazard scenario (1 Benign, 2 Base, 3 Stress) · G05 export share · C11 margin basis (1 bulk benchmark, 2 value chain blend) · C12 share of butter sold as retail jars · G08 carbon revenue (0 in base) · N05 building insurance in baseline (0, bare) · P02 grant co-funding.
A9: Sheets | B9: Inputs · Hazards (damage curves, scenario values) · Value chain (where the jar price goes, share staying in Ghana) · Calc (derived quantities) · Supply (butter supply and loss by option) · Engine (cash flows by option) · Portfolio (combined package) · Results · Sensitivity (snapshot) · Checks · Gates · Source audit · Sources.
A10: Tax | B10: Free Zone: 0% corporate tax for G04a years, then 15% on exports and 25% on domestic income, blended by G05. Tax is applied to positive operating flow; capital allowances are ignored (small, conservative). Whether the 2.5% Growth & Sustainability Levy applies to Free Zone firms is not verified.
A11: Simplifications | B11: Backup power protects critical loads; production continues only in proportion to the load the battery (E06a) or genset (E25) covers. Option 8 models mango only; coconut rows are information for a later procurement option. Programme spend for supplier options is expensed. Portfolio uses a 20-year horizon for all options, so regeneration (which needs 30) is understated there. Supplier income is modelled for irrigation, apiaries and stoves only. Carbon is excluded unless G08 = 1.
A12: Limits to know | B12: Inputs that rest on reasoned estimates rather than sources include the Amazon FBA fee (check Amazon's Revenue Calculator), ocean freight (get a forwarder quote), the current US tariff on Ghana after 24 Jul 2026, retail price, flood depth at your site, and the programme effect sizes for fire, stoves and loyalty. Filter Inputs by 'Analyst assumption' to see them.
A13: Sensitivity sheet | B13: A snapshot computed by recalculating this workbook with each input at Low and High. It does not update live; recompute after major changes.

Sheet Inputs
A1: Input register: every number with its source, quoted figure, rationale and verdict
A2: Edit blue cells only. Column H picks the case (L = Low, B = Base, H = High) per input; hazard rows follow the scenario switch G09. Column I is the value the model uses.
A4: ID | B4: Group | C4: Input | D4: Unit | E4: Low | F4: Base | G4: High | H4: Case | I4: Active value | J4: Confidence tag | K4: Verdict | L4: Rationale | M4: Correction to earlier source | N4: Source 1 | O4: URL 1 | P4: Quoted figure 1 | Q4: Source 2 | R4: URL 2 | S4: Quoted figure 2 | T4: Source 3 | U4: URL 3 | V4: Quoted figure 3
A5: G01 | B5: Global | C5: Discount rate, real USD | D5: % | E5: 0.09 | F5: 0.13 | G5: 0.17 | H5: B | I5: =IF(H5="L",E5,IF(H5="H",G5,F5)) -> 0.13 | J5: Transferable evidence | K5: Adjusted | L5: Cost of equity = 5.24% US 10-yr + 4.23% mature-market premium + 9.71% Ghana country premium = 19.2% nominal, 16.4% real (10-yr breakeven inflation 2.36%). With 40% local debt at ~7.5% real, WACC ≈ 12.8%. Low case: concessional debt and a rating upgrade; high case: all-equity SME premium. | M5: Previous 8/12/16 used an older risk-free rate. Fitch upgraded Ghana to B in May 2026, so the country premium may fall. | N5: Damodaran, Jan 2026 | O5: https://pages.stern.nyu.edu/~adamodar/New_Home_Page/datafile/ctryprem.html | P5: Ghana | Caa1 | 6.37% | 9.71% | 13.94% | Q5: FRED DGS10, 1 Oct 2026 | R5: https://fred.stlouisfed.org/series/DGS10 | S5: 2026-10-01: 5.24 | T5: Graphic, 8 May 2026 | U5: https://www.graphic.com.gh/business/business-news/fitch-upgrades-ghanas-sovereign-rating-as-debt-burden-eases.html | V5: upgraded … from 'B-' to 'B'
A6: G02a | B6: Global | C6: Horizon, plant options | D6: years | E6: 20 | F6: 20 | G6: 20 | H6: B | I6: =IF(H6="L",E6,IF(H6="H",G6,F6)) -> 20 | J6: Transferable evidence | K6: Confirmed | L6: 20 years matches standard appraisal practice for plant. Tree measures need 30+ years because benefits start late; 40 years is a sensitivity. | N6: ADB project appraisal guidance | O6: https://development.asia/summary/guidelines-economic-analysis-projects | P6: normally spans over 20–30 years | Q6: ICRAF species profile | R6: https://apps.worldagroforestry.org/treedb2/speciesprofile.php?Spid=394 | S6: trees do not start to bear fruit until they are 15-20 years old
A7: G02b | B7: Global | C7: Horizon, tree options | D7: years | E7: 30 | F7: 30 | G7: 30 | H7: B | I7: =IF(H7="L",E7,IF(H7="H",G7,F7)) -> 30 | J7: Transferable evidence | K7: Confirmed | L7: 20 years matches standard appraisal practice for plant. Tree measures need 30+ years because benefits start late; 40 years is a sensitivity. | N7: ADB project appraisal guidance | O7: https://development.asia/summary/guidelines-economic-analysis-projects | P7: normally spans over 20–30 years | Q7: ICRAF species profile | R7: https://apps.worldagroforestry.org/treedb2/speciesprofile.php?Spid=394 | S7: trees do not start to bear fruit until they are 15-20 years old
A8: G03 | B8: Global | C8: Exchange rate (info only) | D8: GH₵/USD | E8: 10.5 | F8: 11.6 | G8: 14.5 | H8: B | I8: =IF(H8="L",E8,IF(H8="H",G8,F8)) -> 11.6 | J8: Local field evidence | K8: Adjusted | L8: Model runs in USD; FX converts cedi-priced inputs. The cedi moved from ~16 to ~10 within 2025, so the high case is widened to 14.5. | N8: MyJoyOnline/BoG, Sep 2026 | O8: https://www.myjoyonline.com/cedi-depreciates-by-9-5-in-nine-months-of-2026-bog/ | P8: GH¢11.55 interbank | Q8: Databank, 16 Sep 2026 | R8: https://www.myjoyonline.com/cedi-to-end-year-at-gh%C2%A212-20-to-a-us-dollar-databank-research/ | S8: GH¢12.20 at end-2026 | T8: Barclays via Reuters, Jul 2025 | U8: https://www.marketscreener.com/quote/stock/BARCLAYS-PLC-9583556/news/Ghana-s-cedi-set-to-weaken-sharply-as-gold-exports-plateau-and-spending-rises-Barclays-warns-50499015/ | V8: 14.5 per dollar by end-2026
A9: G04a | B9: Global | C9: Free Zone tax holiday | D9: years | E9: 10 | F9: 10 | G9: 10 | H9: B | I9: =IF(H9="L",E9,IF(H9="H",G9,F9)) -> 10 | J9: Local field evidence | K9: Adjusted | L9: Your factory is a Free Zone enterprise: 0% for years 1–10, then 15% on export income and 25% on domestic sales. Spot-checked against PwC. Whether the 2.5% Growth & Sustainability Levy applies to Free Zone firms is unresolved. | M9: Previous model used a flat 25%. The ordinary agro-processing regime (5% for 5 years, then 20% in Tema) is kept as an alternative scenario. | N9: PwC Tax Summaries, Mar 2026 | O9: https://taxsummaries.pwc.com/Ghana/Corporate/Tax-credits-and-incentives | P9: do not pay CIT for the first ten years … 15% … export … 25% | Q9: PwC Tax Summaries | R9: https://taxsummaries.pwc.com/ghana/corporate/taxes-on-corporate-income | S9: The general corporate income tax (CIT) rate is 25%.
A10: G04b | B10: Global | C10: CIT on export income after holiday | D10: % | E10: 0.15 | F10: 0.15 | G10: 0.15 | H10: B | I10: =IF(H10="L",E10,IF(H10="H",G10,F10)) -> 0.15 | J10: Local field evidence | K10: Adjusted | L10: Your factory is a Free Zone enterprise: 0% for years 1–10, then 15% on export income and 25% on domestic sales. Spot-checked against PwC. Whether the 2.5% Growth & Sustainability Levy applies to Free Zone firms is unresolved. | M10: Previous model used a flat 25%. The ordinary agro-processing regime (5% for 5 years, then 20% in Tema) is kept as an alternative scenario. | N10: PwC Tax Summaries, Mar 2026 | O10: https://taxsummaries.pwc.com/Ghana/Corporate/Tax-credits-and-incentives | P10: do not pay CIT for the first ten years … 15% … export … 25% | Q10: PwC Tax Summaries | R10: https://taxsummaries.pwc.com/ghana/corporate/taxes-on-corporate-income | S10: The general corporate income tax (CIT) rate is 25%.
A11: G04c | B11: Global | C11: CIT on domestic income after holiday | D11: % | E11: 0.25 | F11: 0.25 | G11: 0.25 | H11: B | I11: =IF(H11="L",E11,IF(H11="H",G11,F11)) -> 0.25 | J11: Local field evidence | K11: Adjusted | L11: Your factory is a Free Zone enterprise: 0% for years 1–10, then 15% on export income and 25% on domestic sales. Spot-checked against PwC. Whether the 2.5% Growth & Sustainability Levy applies to Free Zone firms is unresolved. | M11: Previous model used a flat 25%. The ordinary agro-processing regime (5% for 5 years, then 20% in Tema) is kept as an alternative scenario. | N11: PwC Tax Summaries, Mar 2026 | O11: https://taxsummaries.pwc.com/Ghana/Corporate/Tax-credits-and-incentives | P11: do not pay CIT for the first ten years … 15% … export … 25% | Q11: PwC Tax Summaries | R11: https://taxsummaries.pwc.com/ghana/corporate/taxes-on-corporate-income | S11: The general corporate income tax (CIT) rate is 25%.
A12: G05 | B12: Global | C12: Export share of sales | D12: % | E12: 0.7 | F12: 0.85 | G12: 1 | H12: B | I12: =IF(H12="L",E12,IF(H12="H",G12,F12)) -> 0.85 | J12: Analyst assumption | K12: New | L12: Sets the blended tax rate after year 10. Free Zone firms are export-oriented; the minimum export share was not verified on a GFZA page, so confirm with GFZA. | N12: PwC Tax Summaries | O12: https://taxsummaries.pwc.com/Ghana/Corporate/Tax-credits-and-incentives | P12: 15% … export … 25%
A13: G06 | B13: Global | C13: Capital allowance, plant (info only) | D13: % RB | E13: 0.3 | F13: 0.3 | G13: 0.3 | H13: B | I13: =IF(H13="L",E13,IF(H13="H",G13,F13)) -> 0.3 | J13: Local field evidence | K13: Confirmed | L13: Only affects years 11+ because the first 10 years are tax-free. The engine taxes positive operating benefit after year 10 and ignores allowances, a small conservative simplification. | N13: PwC Deductions | O13: https://taxsummaries.pwc.com/ghana/corporate/deductions | P13: plant and machinery used in manufacturing … 30% reducing balance
A14: G07 | B14: Global | C14: Supply-shock correlation, shea vs mango/coconut | D14: ρ | E14: 0 | F14: 0.3 | G14: 0.8 | H14: B | I14: =IF(H14="L",E14,IF(H14="H",G14,F14)) -> 0.3 | J14: Analyst assumption | K14: Adjusted | L14: No yield-correlation study exists. Opposite rainfall trends argue for low correlation; a shared El Niño/La Niña driver argues for a fat upper tail. No rainfall or yield series could be downloaded this session (NASA POWER blocked to automated access), so the range is a reasoned estimate. | M14: Previous base of 0.5 had no source; the KNUST study reports trends, not correlations. | N14: Atiah et al. 2019, KNUST | O14: https://ir.knust.edu.gh/items/55b8fbe9-58e6-4ed9-aedf-281400004a58/full | P14: decreasing trends of consecutive wet days … over the Savannah … increasing trends dominate the Forest zone | Q14: Baidu 2016, KNUST | R14: https://ir.knust.edu.gh/items/3dfcb635-4563-4fad-9e72-aba3d0115d5c/full | S14: effects of strong El Niño and La Niña episodes on the region
A15: C01 | B15: Company | C15: Crude shea butter purchased | D15: t/yr | E15: 100 | F15: 200 | G15: 500 | H15: B | I15: =IF(H15="L",E15,IF(H15="H",G15,F15)) -> 200 | J15: Analyst assumption | K15: New | L15: Case benchmark for a small/medium refiner-formulator. 200 t butter ≈ 540 t kernel at 37% yield ≈ 0.4% of national nut output. Savannah Fruits, a larger exporter, ships 10–12 containers a month. | N15: GNA, Sep 2026 | O15: https://gna.org.gh/2026/09/vice-president-opoku-agyemang-opens-world-shea-expo-2026-in-tamale/ | P15: 130,000 to 150,000 metric tonnes | Q15: Ajala et al. 2019 | R15: https://doaj.org/article/73e0ffab0b6a4dd882aaedcc6ee0e28b | S15: The optimum 37% (w/w) yield | T15: How We Made It In Africa | U15: https://www.howwemadeitinafrica.com/ghana-company-sells-homegrown-shea-butter-to-unilever-and-loccitane/139951/ | V15: 10 to 12 containers every month
A16: C02 | B16: Company | C16: Crude butter purchase price | D16: USD/kg | E16: 2 | F16: 2.8 | G16: 4.7 | H16: B | I16: =IF(H16="L",E16,IF(H16="H",G16,F16)) -> 2.8 | J16: Local field evidence | K16: New | L16: Kernel at the TCDA minimum (~USD 780/t) ÷ 0.37 yield ≈ USD 2.1/kg in kernel cost alone; add processing and margin for ~2.8. Tridge has only 5 Ghana transactions (1.75–4.69). | M16: TCDA price dates from the 2025 season; no 2026/27 price found. | N16: Graphic, TCDA, Jul 2025 | O16: https://www.graphic.com.gh/business/business-news/tcda-sets-gh-9-01-kg-as-minimum-producer-price-for-shea-nuts-from-july-1.html | P16: GH₵9.01 per kilogram | Q16: Ajala et al. 2019 | R16: https://doaj.org/article/73e0ffab0b6a4dd882aaedcc6ee0e28b | S16: 37% (w/w) yield | T16: Tridge Ghana export samples, 2026 | U16: https://www.tridge.com/intelligences/shea-butter/GH/price | V16: 1.75 … 3.26 … 4.69 USD/kg
A17: C03 | B17: Company | C17: Contribution margin per t crude butter | D17: USD/t | E17: 800 | F17: 1500 | G17: 3000 | H17: B | I17: =IF(H17="L",E17,IF(H17="H",G17,F17)) -> 1500 | J17: Transferable evidence | K17: New | L17: Refined bulk butter sells for ~USD 4.7–6.0/kg against ~2.8 crude, leaving ~1.0–2.5/kg before refining cost. Cosmetic finished goods earn more, but no cosmetic price source was opened, so the high case is an assumption. | N17: Tridge refined shea butter, Apr 2026 | O17: https://www.tridge.com/market-overview/refined-shea-butter | P17: India 5.99, Netherlands 5.76, France 4.70 USD/kg | Q17: Tridge Ghana crude samples | R17: https://www.tridge.com/intelligences/shea-butter/GH/price | S17: 1.75–4.69 USD/kg
A18: C04 | B18: Company | C18: Replacement premium in a short year | D18: USD/t butter | E18: 400 | F18: 675 | G18: 1100 | H18: B | I18: =IF(H18="L",E18,IF(H18="H",G18,F18)) -> 675 | J18: Transferable evidence | K18: Derived | L18: Per-kernel premium of USD 150/250/400 (a 27–40% shortage-year price rise plus extra haulage) × 2.7 t kernel per t butter. | N18: Gulf Times/AFP, Dec 2025 | O18: https://www.gulf-times.com/article/717500/international/africa/sellers-under-strain-in-ivory-coasts-struggling-shea-industry | P18: 250 CFA francs to 350 CFA per kilogram | Q18: IFDC Tema port fact sheet, 2019 | R18: https://ifdc.org/wp-content/uploads/2020/09/EnGRAIS_Port-Fact-Sheet-Tema_EN.pdf | S18: Road transit (Tema→Bobo-Dioulasso) 60 USD/t
A19: C05 | B19: Company | C19: Unreplaceable share of a shortfall | D19: % | E19: 0.15 | F19: 0.3 | G19: 0.6 | H19: B | I19: =IF(H19="L",E19,IF(H19="H",G19,F19)) -> 0.3 | J19: Analyst assumption | K19: Unsupported | L19: No literature measures this. The Côte d'Ivoire 2025 anecdote (a buyer ~85% short) justifies a fat high case. | N19: Gulf Times/AFP, Dec 2025 | O19: https://www.gulf-times.com/article/717500/international/africa/sellers-under-strain-in-ivory-coasts-struggling-shea-industry | P19: normally … 3,500 and 4,000 tons … haven't even managed 500 tons
A20: C06 | B20: Company | C20: Catchment supply ÷ requirement | D20: ratio | E20: 1 | F20: 1.25 | G20: 2 | H20: B | I20: =IF(H20="L",E20,IF(H20="H",G20,F20)) -> 1.25 | J20: Analyst assumption | K20: Adjusted | L20: Only ~40% of available nuts are collected nationally, so suppliers can usually find more; the ratio sets when structural decline turns into a deficit. | N20: Citi Newsroom, Jul 2025 | O20: https://www.citinewsroom.com/2025/07/ghana-targets-640m-annual-revenue-from-shea-under-24-hour-economy-push/ | P20: 40% of the available shea nut resource is recovered
A21: C07 | B21: Company | C21: Assets + inventory at Tema | D21: USD | E21: 1000000 | F21: 1800000 | G21: 3000000 | H21: B | I21: =IF(H21="L",E21,IF(H21="H",G21,F21)) -> 1800000 | J21: Analyst assumption | K21: Confirmed | L21: No direct benchmark for a refiner-formulator; the range sits between community centres and industrial plants. Replace with your asset register. | N21: Graphic, 2019 | O21: https://www.graphic.com.gh/news/general-news/ghana-news-shea-butter-processing-facility-inaugurated-at-kpugi.html | P21: US$75,000 community centre | Q21: Ecofin, Jul 2025 | R21: https://www.ecofinagency.com/news/2307-47810-ghana-to-revive-shea-processing-plant-with-4-million-injection | S21: €4M rehabilitation of Buipe | T21: AllAfrica, Feb 2026 | U21: https://allafrica.com/stories/202602110580.html | V21: US$90 million AAK factory
A22: C08 | B22: Company | C22: Electricity use | D22: MWh/yr | E22: 75 | F22: 250 | G22: 600 | H22: B | I22: =IF(H22="L",E22,IF(H22="H",G22,F22)) -> 250 | J22: Transferable evidence | K22: Adjusted | L22: Heat dominates shea processing and is usually biomass or steam; electricity covers motors, vacuum, refining pumps, cold store and HVAC. | M22: Previous 350 MWh implied electric heating. | N22: Nounagnon et al. 2024 | O22: https://ideas.repec.org/a/spr/envsyd/v44y2024i1d10.1007_s10669-023-09925-y.html | P22: 8–10 kWh of heat per kg of produced crude shea butter | Q22: Carré & Quinsac 2011 | R22: https://www.gcirc.org/fileadmin/documents/Proceedings/IRCPrague2011vol2/Oilmill_Refining_Process/1101-1104.pdf | S22: 28.4 kWh of electric power … per ton of seeds
A23: C09 | B23: Company | C23: Operating hours per day | D23: h | E23: 8 | F23: 16 | G23: 24 | H23: B | I23: =IF(H23="L",E23,IF(H23="H",G23,F23)) -> 16 | J23: Analyst assumption | K23: New | L23: Sets how many outage hours hit production. Two shifts is the base for a small refiner.
A24: C10 | B24: Company | C24: Lost output not recovered later | D24: % | E24: 0.3 | F24: 0.5 | G24: 0.8 | H24: B | I24: =IF(H24="L",E24,IF(H24="H",G24,F24)) -> 0.5 | J24: Transferable evidence | K24: New | L24: Part of the output lost in an outage or flood is caught up later; the rest is lost margin. Cross-check: total outage loss should land within the 0–10% of sales band firms report. | N24: World Bank Enterprise Survey Ghana 2023 | O24: https://microdata.worldbank.org/catalog/6444 | P24: losses as % of annual sales: 28.6% report 0, 12.6% report 5%, 11.3% report 10%
A25: H01 | B25: Hazards | C25: Probability of a poor shea year | D25: /yr | E25: 0.15 | F25: 0.3 | G25: 0.5 | H25: =CHOOSE(in_G09,"L","B","H") -> B | I25: =IF(H25="L",E25,IF(H25="H",G25,F25)) -> 0.3 | J25: Transferable evidence | K25: Adjusted | L25: 'Every 2–3 years' describes one tree. Trees fruit under 50% in sync, so a supply-wide bad year is rarer. Drier conditions raise variability, which supports a 0.5 high case. | N25: FAO, Boffa 1999 | O25: https://www.fao.org/4/X3940E/X3940E09.htm | P25: varied by a factor of five in two consecutive years | Q25: Bondé et al. 2019, Burkina | R25: https://agris.fao.org/search/fr/records/65df45000f3e94b9e5d6cd8e | S25: interannual variation … higher in drier climatic conditions | T25: GMet State of the Climate 2025 | U25: https://www.meteo.gov.gh/documents/12579/State_of_the_climate_Report_2025.pdf | V25: Tamale recorded the longest dry spell with a maximum of 13 consecutive dry days
A26: H02 | B26: Hazards | C26: Shortfall in a poor year | D26: % | E26: 0.2 | F26: 0.3 | G26: 0.5 | H26: =CHOOSE(in_G09,"L","B","H") -> B | I26: =IF(H26="L",E26,IF(H26="H",G26,F26)) -> 0.3 | J26: Analyst assumption | K26: Confirmed | L26: Stand-level swings are large but average out across a catchment. No usable national series exists (FAOSTAT Ghana looks imputed). | N26: FAO, Boffa 1999 | O26: https://www.fao.org/4/X3940E/X3940E09.htm | P26: varied by a factor of five | Q26: Ecofin, Jul 2025 | R26: https://www.ecofinagency.com/news-agriculture/1607-47708-shea-sector-west-africa-market-struggles-as-export-bans-expand | S26: two years of reduced harvests
A27: H03 | B27: Hazards | C27: Fire share of the poor-year shortfall | D27: % | E27: 0.1 | F27: 0.3 | G27: 0.5 | H27: B | I27: =IF(H27="L",E27,IF(H27="H",G27,F27)) -> 0.3 | J27: Analyst assumption | K27: Adjusted | L27: Late fires hit flowering, but early fires can raise yield, and pollination and drought compete as causes. No study quantifies the fire share. | M27: Previous citation 'Husseini et al.' was wrong (first author Dahan), and its 825 km²/yr, 19,811 km² and 60% figures are internally inconsistent and unusable. | N27: Lamien et al. 2004 | O27: https://revues.cirad.fr/index.php/fruits/article/download/35862/34641/37906 | P27: late fires … coincide with shea flowering peaks and could harm resulting fruit production | Q27: FAO, Boffa 1999 | R27: https://www.fao.org/4/X3940E/X3940E09.htm | S27: a light, early fire … lead to higher fruit production | T27: Dahan, Kasei & Husseini 2023 | U27: https://link.springer.com/10.1186/s42408-023-00198-z | V27: Fire activity started in October and peaked in December
A28: H04 | B28: Hazards | C28: Structural tree-loss decline | D28: %/yr | E28: 0.005 | F28: 0.015 | G28: 0.025 | H28: =CHOOSE(in_G09,"L","B","H") -> B | I28: =IF(H28="L",E28,IF(H28="H",G28,F28)) -> 0.015 | J28: Transferable evidence | K28: Adjusted | L28: 8M ÷ 500M = 1.6%/yr. The 5,000 ha figure implies only 0.06%/yr across Ghana's shea zone. The 8M figure is an advocacy estimate with no published method. | M28: '9.4 million trees in Ghana' is wrong (it also claims they yield 100 t of nuts). UN-REDD '77% loss' is forest cover, not shea. | N28: GSA via MyJoyOnline, Jul 2026 | O28: https://www.myjoyonline.com/west-africa-losing-8-million-shea-trees-annually-global-shea-alliance-warns/ | P28: 8 million trees annually | Q28: Bup et al. 2014, OCL | R28: https://www.ocl-journal.org/articles/ocl/pdf/2014/02/ocl130026.pdf | S28: About 500 million shea trees grow in Africa | T28: AllAfrica, Jun 2025 | U28: https://allafrica.com/stories/202506110147.html | V28: 5,000 hectares of shea trees annually
A29: H05 | B29: Hazards | C29: Probability the Tema site floods | D29: /yr | E29: 0.05 | F29: 0.1 | G29: 0.25 | H29: =CHOOSE(in_G09,"L","B","H") -> B | I29: =IF(H29="L",E29,IF(H29="H",G29,F29)) -> 0.1 | J29: Local field evidence | K29: Adjusted | L29: Parts of Tema flooded in 2010, 2017, May 2025 and twice in June 2026, including the VALCO/Sentuo industrial zone. Site-level probability depends on elevation, so the high case is raised. | N29: MyJoyOnline, Jun 2010 | O29: https://www.myjoyonline.com/?p=10047971 | P29: bodies of 11 people who drowned in Tema | Q29: Ghana Armed Forces, Jun 2026 | R29: https://www.gafonline.mil.gh/blog-details/eastern-naval-command-conducts-flood-rescues-in-tema | S29: Waterland, VALCO/Sentuo, Tema New Town, Afienya and Alajo | T29: StarrFM/NADMO, May 2025 | U29: https://starrfm.com.gh/may-18-floods-most-severe-in-5-years-in-parts-of-ghana-nadmo | V29: Tema among affected areas
A30: H06 | B30: Hazards | C30: Flood depth without measures | D30: m | E30: 0.3 | F30: 0.5 | G30: 1 | H30: =CHOOSE(in_G09,"L","B","H") -> B | I30: =IF(H30="L",E30,IF(H30="H",G30,F30)) -> 0.5 | J30: Analyst assumption | K30: Adjusted | L30: No public depth exists for any Tema flood. 0.5 m (knee to thigh height) is a reasoned base for an industrial site flooded by overland flow; 1.0 m covers a low-lying parcel. Replace with a site survey: on the JRC curve damage rises from ~4% at 0.3 m to ~25% at 1.0 m. | N30: JRC depth-damage report | O30: https://publications.jrc.ec.europa.eu/repository/handle/JRC105688 | P30: no Tema depth data
A31: H07 | B31: Hazards | C31: Downtime per flood | D31: days | E31: 2 | F31: 5 | G31: 10 | H31: B | I31: =IF(H31="L",E31,IF(H31="H",G31,F31)) -> 5 | J31: Local field evidence | K31: Confirmed | L31: Tema Shipyard reopened ~9 days after the 29 Jun 2026 flood, with partial operation in between. | N31: Citi Newsroom, Jul 2026 | O31: https://www.citinewsroom.com/?p=1369423 | P31: We shall be back to business on Wednesday | Q31: Amegayie 2022, Tema survey | R31: https://www.etd.ceu.edu/2022/amegayie_amos.pdf | S31: 52.4% … hours, 33.6% … days, 9.2% … weeks
A32: H08 | B32: Hazards | C32: Grid outage hours | D32: h/yr | E32: 50 | F32: 250 | G32: 1100 | H32: =CHOOSE(in_G09,"L","B","H") -> B | I32: =IF(H32="L",E32,IF(H32="H",G32,F32)) -> 250 | J32: Local field evidence | K32: Adjusted | L32: Normal years ~50–70 h (WBES); 2016 dumsor ~720 h; 2024 survey implies up to ~1,100 h. Base blends normal years with a crisis roughly one year in four. | M32: Previous high of 1,500 h exceeded every observed crisis year. | N32: World Bank Enterprise Survey 2023 | O32: https://microdata.worldbank.org/catalog/6444 | P32: modal 2 outages per month | Q32: GNA / IEA Ghana, Jun 2024 | R32: https://gna.org.gh/2024/06/accra-residents-experience-outages-four-times-a-week-iea-survey/ | S32: 75.4 per cent … at least thrice a week | T32: Energy for Growth Hub | U32: https://energyforgrowth.org/article/how-can-small-and-medium-enterprises-cope-with-power-outages | V32: about 10 outages in a month … about 6 hours
A33: H09 | B33: Hazards | C33: Depth-damage curve (1 = Africa, 2 = Global) | D33: switch | E33: 1 | F33: 1 | G33: 2 | H33: B | I33: =IF(H33="L",E33,IF(H33="H",G33,F33)) -> 1 | J33: Transferable evidence | K33: Confirmed | L33: Values spot-checked. The Africa curve rests on one South African function, so the global curve (29.7% at 0.5 m) is the high case. | N33: JRC data via os-climate | O33: https://raw.githubusercontent.com/os-climate/physrisk/main/docs/user_guide/vulnerability/vulnerability_functions/inundation_jrc/raw.csv | P33: Africa_Mean 0.5 m 0.0627; 1.0 m 0.2472 | Q33: Huizinga et al. 2017, JRC | R33: https://publications.jrc.ec.europa.eu/repository/handle/JRC105688 | S33: only one function for the class 'Industry' … originating from South Africa
A34: I01 | B34: 1 Irrigation | C34: Solar borehole system, turnkey | D34: USD | E34: 10000 | F34: 27700 | G34: 35000 | H34: B | I34: =IF(H34="L",E34,IF(H34="H",G34,F34)) -> 27700 | J34: Local field evidence | K34: Adjusted | L34: GH¢8M ÷ 25 = GH¢320k ≈ USD 27.7k each, including storage and delivery. A plot-scale kit (borehole + 1-acre pump + tank) can cost ~USD 5–10k. | M34: Agrilinks USD figures used an older exchange rate; at GH¢11.55 the pump is USD 2.2–2.6k. | N34: ISD Ghana, GROW2 | O34: https://www.isd.gov.gh/government-builds-25-solar-boreholes-to-boost-vegetable-production-in-northern-ghana/ | P34: 25 modern solar powered boreholes … about GH¢8 million | Q34: Agrilinks/IWMI | R34: https://agrilinks.org/post/cocoa-farmers-ghana-show-strong-interest-solar-based-irrigation-pump-costs-are-often-too-high | S34: GHS 25,000 … and GHS 30,000 … at least one acre
A35: I02 | B35: 1 Irrigation | C35: Borehole success rate | D35: % | E35: 0.3 | F35: 0.45 | G35: 0.65 | H35: B | I35: =IF(H35="L",E35,IF(H35="H",G35,F35)) -> 0.45 | J35: Local field evidence | K35: Adjusted | L35: BGS defines success at hand-pump yield; irrigation needs more water, so rates are shifted down. | N35: BGS/UNICEF, Northern Region | O35: https://core.ac.uk/display/385054 | P35: typically between 40 and 60%, but range from 20% … to around 70%
A36: I03 | B36: 1 Irrigation | C36: Systems installed | D36: count | E36: 2 | F36: 4 | G36: 8 | H36: B | I36: =IF(H36="L",E36,IF(H36="H",G36,F36)) -> 4 | J36: Analyst assumption | K36: Confirmed | L36: Programme design choice; budget ~2.2 drilling attempts per working system.
A37: I04 | B37: 1 Irrigation | C37: Garden net income per system | D37: USD/yr | E37: 1000 | F37: 2500 | G37: 5000 | H37: B | I37: =IF(H37="L",E37,IF(H37="H",G37,F37)) -> 2500 | J37: Local field evidence | K37: Adjusted | L37: About 1 ha per system. 2026 gross margins (~USD 1.2k/ha) are well below 2017 USD figures. Accrues to the farmer account. | M37: Area per GROW2 system is contradictory (50 acres each vs 50 acres in total). | N37: FSRP Ghana, Aug 2026 | O37: https://fsrp.org.gh/blog/From-Dry-Fields-To-Full-Baskets-%28How-Ghana%27s-Tomato-Farmers-Are-Re-writting-The-Dry-Season%29 | P37: GHS 14,150 per hectare | Q37: IWMI/ILSSI 2017 | R37: https://borlaug.tamu.edu/wp-content/uploads/sites/3/2019/11/ilssi-technical-report-economic-analayis-ghana.pdf | S37: GHS 19,249/ha (USD 4,466/ha)
A38: I05 | B38: 1 Irrigation | C38: Loyalty: cut in poor-year loss among served suppliers | D38: pts | E38: 0 | F38: 0.05 | G38: 0.15 | H38: B | I38: =IF(H38="L",E38,IF(H38="H",G38,F38)) -> 0.05 | J38: Analyst assumption | K38: Unsupported | L38: Qualitative evidence only. AAK's obligation-free pre-finance to 275,000 women competes for the same supply, so the low case is zero. | N38: GSA finance pilot | O38: https://globalshea.com/gsamain/storage/img/news/docs/Finance%20Reimagined_%20A%20Replicable%20Model%20For%20Financing%20The%20Shea%20Industry%20(1).pdf | P38: reduced and in most cases, eliminated side-selling | Q38: Graphic, AAK 2026 | R38: https://www.graphic.com.gh/news/general-news/ghanan-news-disbursement-for-shea-collectors-begins-in-bimbilla-275-000-women-to-receive-eur13m-for-2026-season.html | S38: obligation-free … not obligated to sell
A39: I06 | B39: 1 Irrigation | C39: Seedling survival gain with watering | D39: pts | E39: 0.1 | F39: 0.2 | G39: 0.3 | H39: B | I39: =IF(H39="L",E39,IF(H39="H",G39,F39)) -> 0.2 | J39: Transferable evidence | K39: Confirmed | L39: Applies only when irrigation is paired with Option 3 nurseries. | N39: Noulekoun et al., Benin | O39: https://www.tropentag.de/2016/abstracts/pdf/1029.pdf | P39: reduced by ten-folds the mortality rate of … Parkia biglobosa
A40: I07 | B40: 1 Irrigation | C40: O&M | D40: % capex/yr | E40: 0.01 | F40: 0.02 | G40: 0.03 | H40: B | I40: =IF(H40="L",E40,IF(H40="H",G40,F40)) -> 0.02 | J40: Analyst assumption | K40: Unsupported | L40: Typical for solar pumping; no Ghana source found.
A41: A01 | B41: 2 Apiaries | C41: Hive, kit and training | D41: USD/hive | E41: 65 | F41: 100 | G41: 150 | H41: B | I41: =IF(H41="L",E41,IF(H41="H",G41,F41)) -> 100 | J41: Transferable evidence | K41: Confirmed | L41: Local top-bar box USD 20–40, shared protective kit and training. The 2017 GH¢750 converted at 2017 rates is ~USD 170, so the low case is optimistic. | N41: Bee Culture, Feb 2017 | O41: https://www.beeculture.com/catch-buzz-ghana-wants-piece-global-honey-export-business-intends-fund-growth/ | P41: cost of one beehive, other inputs and training at GH¢750 | Q41: Rufford, Bia, 2015 | R41: https://media.rufford.org/media/project_reports/12807-1%20Final%20Report.pdf | S41: £13.50 per hive
A42: A02 | B42: 2 Apiaries | C42: Honey per occupied colony | D42: kg/yr | E42: 6 | F42: 10 | G42: 16 | H42: B | I42: =IF(H42="L",E42,IF(H42="H",G42,F42)) -> 10 | J42: Transferable evidence | K42: Adjusted | L42: Frame hives in West Africa give 15–19 kg; top-bar hives run by new beekeepers in drier savanna will yield less. | N42: Jakpa 2015, Volta Region | O42: https://ir.knust.edu.gh/handle/123456789/8463 | P42: 18.70kg per beehive per season (Langstroth) | Q42: USAID Côte d'Ivoire 2017 | R42: https://pdf.usaid.gov/pdf_docs/PA00T98B.pdf | S42: A mean of 15.7 kg honey
A43: A03 | B43: 2 Apiaries | C43: Wax as share of honey (top-bar) | D43: % | E43: 0.05 | F43: 0.08 | G43: 0.1 | H43: B | I43: =IF(H43="L",E43,IF(H43="H",G43,F43)) -> 0.08 | J43: Transferable evidence | K43: Confirmed | L43: Top-bar hives harvest whole comb, so wax is ~8–10% of honey; frame hives give ~2%. | N43: LRRD 2013 | O43: https://lrrd.org/lrrd25/5/haft25086.htm | P43: About 8 percent beeswax per kilogram of honey | Q43: FAO | R43: https://www.fao.org/4/y5110e/y5110e07.htm | S43: about 10:1
A44: A04 | B44: 2 Apiaries | C44: Colony occupancy | D44: % | E44: 0.35 | F44: 0.65 | G44: 0.85 | H44: B | I44: =IF(H44="L",E44,IF(H44="H",G44,F44)) -> 0.65 | J44: Local field evidence | K44: Adjusted | L44: Savanna sites colonise more slowly than forest-edge sites. | N44: Rufford, Bia, Ghana | O44: https://media.rufford.org/media/project_reports/12807-1%20Final%20Report.pdf | P44: 75% of the supplied beehives had been colonised | Q44: Ja'afar-Furo 2017, NE Nigeria | R44: https://ijsses.tiu.edu.iq/index.php/ijsses/article/view/468 | S44: 22.5% in year 1 … 62.5% in year 2
A45: A05 | B45: 2 Apiaries | C45: Raw beeswax price, farm-gate | D45: USD/kg | E45: 5 | F45: 6.9 | G45: 8.1 | H45: B | I45: =IF(H45="L",E45,IF(H45="H",G45,F45)) -> 6.9 | J45: Local field evidence | K45: Adjusted | L45: GH₵80 ÷ 11.55 = USD 6.9. Spot-checked. | M45: Previous source (Selina Wamucii) states no method. | N45: Bees for Babar, Tamale, 2026 | O45: https://beesforbabar.org/photos_update_20260705.htm | P45: Beeswax … 80 cedis/kg
A46: A06 | B46: 2 Apiaries | C46: Mature shea fruit gain near apiaries | D46: % | E46: 0 | F46: 0 | G46: 0.05 | H46: B | I46: =IF(H46="L",E46,IF(H46="H",G46,F46)) -> 0 | J46: Local field evidence | K46: Confirmed | L46: Stout compares pollination with none; it does not test adding hives. The direct apiary test found no mature-fruit effect. | N46: Nasare et al. 2024, N. Ghana | O46: https://doaj.org/article/5092b417b85c425388272fd8bdc264e2 | P46: related to number of immature fruit set but not number of mature fruits | Q46: Stout et al. 2018 | R46: https://pollinationecology.org/index.php/jpe/article/download/473/158/1782 | S46: 1.86 ± 0.18 … 0.78 ± 0.09 (open vs bagged)
A47: A07 | B47: 2 Apiaries | C47: Burned-area cut near apiaries | D47: % | E47: 0 | F47: 0.05 | G47: 0.25 | H47: B | I47: =IF(H47="L",E47,IF(H47="H",G47,F47)) -> 0.05 | J47: Analyst assumption | K47: Unsupported | L47: Mechanism plausible (beekeepers guard and clear around hives) but unmeasured. | M47: The Darwin project is in Eastern Region, not the north, and reports no burned-area comparison. | N47: Darwin Initiative, Afram Plains | O47: https://www.darwininitiative.org.uk/documents/DAR30001/27704/30-001%20AR2%20-%20edited.pdf | P47: cumulatively protected over 500 hectares
A48: A08 | B48: 2 Apiaries | C48: Hives installed | D48: count | E48: 100 | F48: 200 | G48: 400 | H48: B | I48: =IF(H48="L",E48,IF(H48="H",G48,F48)) -> 200 | J48: Analyst assumption | K48: New | L48: Programme design choice.
A49: A09 | B49: 2 Apiaries | C49: Delivered price of comparable cosmetic beeswax | D49: USD/kg | E49: 4.5 | F49: 6.5 | G49: 9 | H49: B | I49: =IF(H49="L",E49,IF(H49="H",G49,F49)) -> 6.5 | J49: Transferable evidence | K49: Adjusted | L49: Cosmetic-grade beeswax from India is ₹320–610/kg = USD 3.3–6.4/kg ex-works; freight and small lots add 20–40%. Local farm-gate wax (USD 6.9) is about the same price, so the factory saves little by buying locally. | N49: IndiaMART beeswax, Oct 2026 | O49: https://m.indiamart.com/impcat/beeswax.html | P49: ₹325–₹450/kg (cosmetic grade, most common) | Q49: FRED DEXINUS, 25 Sep 2026 | R49: https://fred.stlouisfed.org/series/DEXINUS | S49: 95.8100 Indian Rupees to One U.S. Dollar
A50: R01 | B50: 3 Regeneration | C50: Grafted shea seedling, delivered | D50: USD | E50: 1 | F50: 2 | G50: 4 | H50: B | I50: =IF(H50="L",E50,IF(H50="H",G50,F50)) -> 2 | J50: Analyst assumption | K50: Unsupported | L50: Ordinary seedlings cost ~USD 0.85 delivered; grafting adds scions, skilled labour and nursery time. Ask CRIG Bole or GSA nurseries for quotes. | N50: Auditor-General, Green Ghana audit, May 2026 | O50: https://audit.gov.gh/files/audit_reports/Performance_Audit_Report_Of_The_Auditor-General_On_Management_Of_The_Green_Ghana_Project_By_Ministry_Of_Lands_And_Natural_Resources.pdf | P50: GH¢9 to GH¢10 per seedling (delivered)
A51: R02 | B51: 3 Regeneration | C51: Planting + 3 years aftercare | D51: USD/ha | E51: 150 | F51: 350 | G51: 600 | H51: B | I51: =IF(H51="L",E51,IF(H51="H",G51,F51)) -> 350 | J51: Transferable evidence | K51: Confirmed | L51: Enrichment planting of 50–100 grafted trees/ha plus protection and weeding. Natural regeneration alone costs ~USD 60/ha. | N51: CRS / Regreening Africa | O51: https://www.crs.org/sites/default/files/2025-04/ReGreening%20Africa%20Case%20Study_final%20%281%29.pdf | P51: Cost to adopt land restoration practices was $58 per hectare (Ghana)
A52: R03 | B52: 3 Regeneration | C52: Survival at year 5 | D52: % | E52: 0.2 | F52: 0.4 | G52: 0.65 | H52: B | I52: =IF(H52="L",E52,IF(H52="H",G52,F52)) -> 0.4 | J52: Local field evidence | K52: Adjusted | L52: The independent audit and the Forestry Commission's own figure bracket the outcome; year-5 survival is below year-1. | M52: The UNDP 70% was a target, not a result. The Darwin 39% was mixed species in Eastern Region after under a year. | N52: Auditor-General, May 2026 | O52: https://audit.gov.gh/files/audit_reports/Performance_Audit_Report_Of_The_Auditor-General_On_Management_Of_The_Green_Ghana_Project_By_Ministry_Of_Lands_And_Natural_Resources.pdf | P52: 2,863 (17.3%) survived | Q52: Graphic editorial, Jun 2026 | R52: https://www.graphic.com.gh/daily-graphic-editorials/ghana-news-tree-planting-is-easy-nurturing-is-the-test.html | S52: 78 per cent in the Northern Savannah Zone (self-reported)
A53: R04a | B53: 3 Regeneration | C53: Grafted trees: years to first fruit | D53: years | E53: 4 | F53: 6 | G53: 9 | H53: B | I53: =IF(H53="L",E53,IF(H53="H",G53,F53)) -> 6 | J53: Local field evidence | K53: Adjusted | L53: First-fruit years are supported; no source gives a full-production year, so 14 and 18 are assumptions. Seed-grown trees take 15–20 years. | N53: Graphic, CRIG Bole 2021 | O53: https://www.graphic.com.gh/features/features/bole-crig-develops-short-gestation-shea.html | P53: from about 20 years to five or less | Q53: UNDP 2023 | R53: https://www.undp.org/node/416886 | S53: from 15-20 years in the wild to 5-7 years | T53: Sanou et al. 2004 | U53: https://agritrop.cirad.fr/548895 | V53: Two grafts produced fruits two years after grafting
A54: R04b | B54: 3 Regeneration | C54: Grafted trees: years to full yield | D54: years | E54: 10 | F54: 14 | G54: 18 | H54: B | I54: =IF(H54="L",E54,IF(H54="H",G54,F54)) -> 14 | J54: Local field evidence | K54: Adjusted | L54: First-fruit years are supported; no source gives a full-production year, so 14 and 18 are assumptions. Seed-grown trees take 15–20 years. | N54: Graphic, CRIG Bole 2021 | O54: https://www.graphic.com.gh/features/features/bole-crig-develops-short-gestation-shea.html | P54: from about 20 years to five or less | Q54: UNDP 2023 | R54: https://www.undp.org/node/416886 | S54: from 15-20 years in the wild to 5-7 years | T54: Sanou et al. 2004 | U54: https://agritrop.cirad.fr/548895 | V54: Two grafts produced fruits two years after grafting
A55: R05 | B55: 3 Regeneration | C55: Mature yield | D55: kg dry kernel/tree/yr | E55: 2 | F55: 4 | G55: 6 | H55: B | I55: =IF(H55="L",E55,IF(H55="H",G55,F55)) -> 4 | J55: Transferable evidence | K55: Adjusted | L55: Measured parkland mean ~4 kg; natural stands ~1.5 kg. Spot-checked. | M55: The OCL '5 kg' was an assumption used to scale up a regional total. | N55: Lamien et al. 2004, Burkina | O55: https://fruits.edpsciences.org/articles/fruits/abs/2004/06/i4039/i4039.html | P55: around 4 kg·tree–1 (parklands) | Q55: Practical Action | R55: https://kolibri.teacherinabox.org.au/modules/en-practical_action/Crop%20processing/Nut%20Processing%20and%20Oil%20Extraction/KnO-100293_Shea%20nut%20processing.pdf | S55: 15 to 20 kg of fresh fruit … 3 to 4 kg of dry kernels
A56: R06 | B56: 3 Regeneration | C56: Share of new nuts you capture | D56: % | E56: 0.2 | F56: 0.4 | G56: 0.7 | H56: B | I56: =IF(H56="L",E56,IF(H56="H",G56,F56)) -> 0.4 | J56: Analyst assumption | K56: Unsupported | L56: No Ghana estimate exists. Competing buyers pre-finance without obligation, so high capture needs exclusive aggregation. | N56: Mahama et al. 2025, Tamale | O56: https://ageconsearch.umn.edu/record/368218/files/Mahama4332025AJAEES131074.pdf | P56: 84% … ready market access | Q56: Graphic, AAK 2026 | R56: https://www.graphic.com.gh/news/general-news/ghanan-news-disbursement-for-shea-collectors-begins-in-bimbilla-275-000-women-to-receive-eur13m-for-2026-season.html | S56: obligation-free
A57: R07 | B57: 3 Regeneration | C57: Seedlings planted | D57: count | E57: 5000 | F57: 10000 | G57: 20000 | H57: B | I57: =IF(H57="L",E57,IF(H57="H",G57,F57)) -> 10000 | J57: Analyst assumption | K57: New | L57: Programme design choice; ~100 per ha.
A58: R08a | B58: 3 Regeneration | C58: Parkland carbon uptake | D58: t CO₂/ha/yr | E58: 1 | F58: 1.5 | G58: 2 | H58: B | I58: =IF(H58="L",E58,IF(H58="H",G58,F58)) -> 1.5 | J58: Transferable evidence | K58: Confirmed | L58: 0.4 tC = 1.47 tCO₂. Revenue is 0 in the base case. | N58: Luedeling & Neufeldt 2012 | O58: https://www.gov.uk/research-for-development-outputs/carbon-sequestration-potential-of-parkland-agroforestry-in-the-sahel | P58: 0.4 Mg C ha−1 a−1 | Q58: Sylvera Q3 2025 | R58: https://sylvera.com/blog/q3-2025-carbon-data-snapshot | S58: $24/tCO₂e (BBB+ ARR)
A59: R08b | B59: 3 Regeneration | C59: ARR credit price | D59: USD/t CO₂ | E59: 10 | F59: 22 | G59: 35 | H59: B | I59: =IF(H59="L",E59,IF(H59="H",G59,F59)) -> 22 | J59: Transferable evidence | K59: Confirmed | L59: 0.4 tC = 1.47 tCO₂. Revenue is 0 in the base case. | N59: Luedeling & Neufeldt 2012 | O59: https://www.gov.uk/research-for-development-outputs/carbon-sequestration-potential-of-parkland-agroforestry-in-the-sahel | P59: 0.4 Mg C ha−1 a−1 | Q59: Sylvera Q3 2025 | R59: https://sylvera.com/blog/q3-2025-carbon-data-snapshot | S59: $24/tCO₂e (BBB+ ARR)
A60: B01 | B60: 4 Biochar | C60: Shea cake from supplier processing (dry) | D60: t/yr | E60: 150 | F60: 240 | G60: 320 | H60: B | I60: =IF(H60="L",E60,IF(H60="H",G60,F60)) -> 240 | J60: Transferable evidence | K60: Adjusted | L60: Your suppliers make the butter, so the cake sits at village processing centres, not in Tema. 200 t butter needs ~540–670 t kernel, leaving ~1.7–2.3 t wet cake per t butter, about 1.0–1.4 t dry. | M60: Previous version placed 275 t of cake at the factory; that no longer applies to a crude-butter buyer. | N60: Ajala et al. 2019 | O60: https://doaj.org/article/73e0ffab0b6a4dd882aaedcc6ee0e28b | P60: 37% (w/w) yield | Q60: Adamon 2021 | R60: https://independent.academia.edu/DavidADAMON | S60: 0.43 tonnes [cake] per tonne of processed dry shea nuts | T60: USAID/BDL roasting study | U60: https://pdf.usaid.gov/pdf_docs/PA00TGBJ.pdf | V60: [cake moisture] around 40%
A61: B02 | B61: 4 Biochar | C61: Char yield | D61: % of dry feedstock | E61: 0.2 | F61: 0.25 | G61: 0.32 | H61: B | I61: =IF(H61="L",E61,IF(H61="H",G61,F61)) -> 0.25 | J61: Transferable evidence | K61: Confirmed | L61: No shea-cake yield exists; oily cake may need pelletising. Test a batch. | M61: Cogent Engineering 2024 covers shea shells, not cake, and gives no yield. | N61: Anderson 2022 | O61: https://woodgas.com/wp-content/uploads/2022/08/Small-and-medium-pyrolysis-20-minutes-2022-08-30.pdf | P61: Small to Midi scales: 15 – 25% | Q61: Biochar Today 2025 | R61: https://biochartoday.com/news/a-comparison-of-biochar-kilns-for-low-to-middle-income-countries/ | S61: retort kilns up to 46%
A62: B03 | B62: 4 Biochar | C62: Kiln or retort | D62: USD | E62: 5000 | F62: 25000 | G62: 80000 | H62: B | I62: =IF(H62="L",E62,IF(H62="H",G62,F62)) -> 25000 | J62: Transferable evidence | K62: Confirmed | L62: ~1 t/day of cake suits several flame-curtain kilns (low) or a small retort (base/high). Add USD 10–20k if pelletising is needed. | N62: Anderson 2022 | O62: https://woodgas.com/wp-content/uploads/2022/08/Small-and-medium-pyrolysis-20-minutes-2022-08-30.pdf | P62: RoCC kiln: medium $2K – 10K … large $20K – 80K
A63: B04 | B63: 4 Biochar | C63: Production cost | D63: USD/t char | E63: 40 | F63: 120 | G63: 300 | H63: B | I63: =IF(H63="L",E63,IF(H63="H",G63,F63)) -> 120 | J63: Transferable evidence | K63: Adjusted | L63: Free residue feedstock puts costs below the African median; pelletising, labour and testing put them above earth kilns. | N63: Kern et al. 2025 | O63: https://repository.tudelft.nl/file/File_b7e9c73e-a192-46b1-a108-a7af523df54a?preview=1 | P63: Sub-Saharan Africa: median 197.82 €/ton (Kontiki kiln) | Q63: Biochar Today, Amazonia | R63: https://biochartoday.com/news/traditional-kilns-boost-farmer-net-revenue-by-94-with-biochar/ | S63: $0.03-$0.08 per kilogram (earth kiln)
A64: B05 | B64: 4 Biochar | C64: Fuel value lost (cake now burned) | D64: USD/t | E64: 0 | F64: 30 | G64: 60 | H64: B | I64: =IF(H64="L",E64,IF(H64="H",G64,F64)) -> 30 | J64: Transferable evidence | K64: Adjusted | L64: Women processors often burn cake as fuel; turning it into char means buying replacement fuel. | N64: Adamon 2021 | O64: https://independent.academia.edu/DavidADAMON | P64: 22.42 MJ / kg for the shea cake | Q64: Ghana CIC 2019 | R64: https://ghanacic.org/wp-content/uploads/2024/04/ECONOMIC-POTENTIAL-FOR-RESIDUAL-AGRO-AND-BIOMASS-FUELS-IN-GHANA_final.pdf | S64: Kernel shells … approx. GHS 0.3-0.7/kg
A65: B06 | B65: 4 Biochar | C65: Removal credit price, gross (sensitivity only) | D65: USD/t CO₂e | E65: 100 | F65: 140 | G65: 200 | H65: B | I65: =IF(H65="L",E65,IF(H65="H",G65,F65)) -> 140 | J65: Transferable evidence | K65: Confirmed | L65: Base revenue is 0 until a buyer signs. | M65: The Puro index page is stale (Nov 2024, EUR). | N65: S&P via CarbonCredits, Dec 2025 | O65: https://carboncredits.com/?p=39628 | P65: around $150 per tonne | Q65: IETA, Jun 2026 | R65: https://www.ieta.org/uploads/wp-content/2026/03/IETA_CMWG_BusinessBrief_Biochar_FinalJune2026.pdf | S65: $100–$300 | T65: Senken 2026 | U65: https://www.senken.io/carbon-removal/biochar | V65: Artisanal: €100–150
A66: B07 | B66: 4 Biochar | C66: CO₂e removed per t char, net | D66: t | E66: 1.3 | F66: 1.7 | G66: 2.2 | H66: B | I66: =IF(H66="L",E66,IF(H66="H",G66,F66)) -> 1.7 | J66: Transferable evidence | K66: Adjusted | L66: Carbon content × 44/12 × permanence × (1 − process emissions): 0.65 × 3.667 × 0.75 × 0.93 = 1.7. | M66: Swisscontact's '2–3 t' is generic, not about shea, and its own throughput numbers do not reconcile. | N66: EBC Artisan C-Sink guidelines | O66: https://www.european-biochar.org/media/doc/2/artisan-c-sink-guidelines_v1_0.pdf | P66: 2.67 t CO2e … 74% … after 100 years | Q66: Lartey-Young & Ziggah 2024 | R66: https://www.tropentag.de/2024/abstracts/links/Lartey-Young_d3Kv4wqE.php | S66: organic carbon content reached 58%
A67: B08 | B67: 4 Biochar | C67: Verification and registry cost | D67: % of credit revenue | E67: 0.15 | F67: 0.25 | G67: 0.35 | H67: B | I67: =IF(H67="L",E67,IF(H67="H",G67,F67)) -> 0.25 | J67: Analyst assumption | K67: Adjusted | L67: No registry fee schedule could be opened. 25% covers lab analysis, third-party verification, registry issuance and a broker margin for a small first project.
A68: S01 | B68: 5 Stoves | C68: Processing stove installed | D68: USD | E68: 250 | F68: 600 | G68: 1500 | H68: B | I68: =IF(H68="L",E68,IF(H68="H",G68,F68)) -> 600 | J68: Local field evidence | K68: Adjusted | L68: Only one direct shea-centre price found (USD 355); larger multi-pot stoves cost more. | M68: The GSA tender has no price, quantity or lifetime. | N68: Ntereso centre budget, Bole, 2019 | O68: https://www.globalgiving.org/pfil/39822/projdoc.pdf | P68: Morrison stove … 1,800 [GH₵] … 355 [USD] | Q68: ESMAP Burkina 2013 | R68: https://rise.esmap.org/data/files/library/burkina-faso/Clean%20Cooking/Burkina%20Faso_Impact%20assessment%20of%20improved%20cookstoves%20in%20Burkina%20Faso_2013.pdf | S68: environ 27 500 francs CFA
A69: S02 | B69: 5 Stoves | C69: Wood saved per kg butter | D69: % | E69: 0.3 | F69: 0.4 | G69: 0.55 | H69: B | I69: =IF(H69="L",E69,IF(H69="H",G69,F69)) -> 0.4 | J69: Local field evidence | K69: Adjusted | L69: The GSA baseline already includes semi-improved stoves, so 30–42% understates savings against fully traditional stoves. | N69: GSA stove tender, 2026 | O69: https://globalshea.com/gsamain/storage/img/news/docs/TOR%20FOR%20SUPPLY%20OF%20ENERGY%20SAVING%20COOKSTOVES.docx.pdf | P69: 2.0 – 2.4 kg … 1.4 kg of wood | Q69: AVSF Burkina | R69: https://www.avsf.org/app/uploads/2023/12/actions-innovantes_equite-_ugf_cnd_avsf_2019.pdf | S69: réduire la consommation en bois de 54%
A70: S03 | B70: 5 Stoves | C70: Stove life | D70: years | E70: 3 | F70: 5 | G70: 7 | H70: B | I70: =IF(H70="L",E70,IF(H70="H",G70,F70)) -> 5 | J70: Transferable evidence | K70: Confirmed | L70: Heavy batch use argues against more than 7 years. | N70: Envirofit SaverPro100 | O70: https://techxlab.org/solutions/envirofit-saverpro100-stove/ | P70: 5 year minimum
A71: S04 | B71: 5 Stoves | C71: Cut in tree-loss decline | D71: pts/yr | E71: 0.0005 | F71: 0.0015 | G71: 0.003 | H71: B | I71: =IF(H71="L",E71,IF(H71="H",G71,F71)) -> 0.0015 | J71: Analyst assumption | K71: Adjusted | L71: Farm clearing is the main named driver; no source gives fuelwood's share of shea felling. | N71: GCF FP137 ESMF | O71: https://files.acquia.undp.org/public/migration/gh/7edf98392d07687a6c332f8836d5f5378bbb4f2ffb5f1443d6ffdfbea6af7c58.pdf | P71: conversion to agriculture (at just under 40,000 ha per annum) … wood fuel harvesting and charcoal production
A72: S05 | B72: 5 Stoves | C72: Stoves installed | D72: count | E72: 25 | F72: 50 | G72: 100 | H72: B | I72: =IF(H72="L",E72,IF(H72="H",G72,F72)) -> 50 | J72: Analyst assumption | K72: New | L72: Programme design; now aimed at your own butter suppliers.
A73: S06 | B73: 5 Stoves | C73: Butter per stove | D73: t/yr | E73: 2 | F73: 4 | G73: 8 | H73: B | I73: =IF(H73="L",E73,IF(H73="H",G73,F73)) -> 4 | J73: Analyst assumption | K73: New | L73: Sets processor fuel savings in the farmer account.
A74: S07 | B74: 5 Stoves | C74: Fuelwood price, Northern Region | D74: USD/t | E74: 20 | F74: 35 | G74: 60 | H74: B | I74: =IF(H74="L",E74,IF(H74="H",G74,F74)) -> 35 | J74: Transferable evidence | K74: Adjusted | L74: No firewood price found. Charcoal (~30 MJ/kg) costs GH₵1.52/kg in Tamale; firewood (~15 MJ/kg) is worth at most half that per kg on energy parity (~USD 66/t). Base USD 35/t allows for wood being gathered rather than bought. | N74: CERSGIS, end 2023 | O74: https://cpsm.cersgis.org/media/reports/End_of_2023_Charcoal_price_tracking_v2.pdf | P74: Tamale at GH₵1.52 per kg [charcoal] | Q74: Adamon 2021 | R74: https://independent.academia.edu/DavidADAMON | S74: 18.7 MJ / kg for the shells
A75: S08 | B75: 5 Stoves | C75: Cookstove credit price (sensitivity only) | D75: USD/t | E75: 4 | F75: 10 | G75: 18 | H75: B | I75: =IF(H75="L",E75,IF(H75="H",G75,F75)) -> 10 | J75: Transferable evidence | K75: Adjusted | L75: USD 25 exceeded even the peak futures price (18.10). | N75: MSCI, May 2026 | O75: https://www.msci.com/research-and-insights/quick-take/clean-cooking-dominates-corsia-but-premium-faces-pressure | P75: above USD 14 … broader clean-cooking average of around USD 4 | Q75: ICVCM, Mar 2025 | R75: https://icvcm.org/?p=9246 | S75: do not meet the CCP Assessment Framework requirements
A76: D01 | B76: 6 Flood | C76: Concrete U-drain | D76: USD/m | E76: 55 | F76: 70 | G76: 95 | H76: B | I76: =IF(H76="L",E76,IF(H76="H",G76,F76)) -> 70 | J76: Local field evidence | K76: Adjusted | L76: Bottom-up from Aug 2026 material prices: ~USD 63/m before excavation. | M76: The paper gives no unit length; the previous USD 63–79/m treated the 550 mm height as length. | N76: KsTU 2024 | O76: https://ijid.kstu.edu.gh/index.php/ijid/article/download/33/29/111 | P76: Total cost for constructing the drain = GHȻ 400.00 | Q76: Yen.com.gh, Aug 2026 | R76: https://yen.com.gh/ghana/309707-what-ghc50000-cover-starting-a-building-project-ghana/ | S76: cement around GH¢75 to GH¢101 per bag
A77: D02 | B77: 6 Flood | C77: Drain length | D77: m | E77: 360 | F77: 570 | G77: 700 | H77: B | I77: =IF(H77="L",E77,IF(H77="H",G77,F77)) -> 570 | J77: Analyst assumption | K77: Confirmed | L77: Square perimeter of 2 acres = 360 m; of 5 acres = 569 m.
A78: D03 | B78: 6 Flood | C78: Excavation, bedding and outfall | D78: % on drain cost | E78: 0.4 | F78: 0.75 | G78: 1 | H78: B | I78: =IF(H78="L",E78,IF(H78="H",G78,F78)) -> 0.75 | J78: Analyst assumption | K78: Unsupported | L78: Trench volume ~0.7–1.0 m³ per metre; local quote needed.
A79: D04 | B79: 6 Flood | C79: Detention storage | D79: USD/m³ | E79: 10 | F79: 25 | G79: 55 | H79: B | I79: =IF(H79="L",E79,IF(H79="H",G79,F79)) -> 25 | J79: Transferable evidence | K79: Adjusted | L79: UK 2007 prices; unlined earth ponds in Ghana should cost less. | N79: UK Environment Agency SuDS costs | O79: https://assets.publishing.service.gov.uk/media/6034ee6c8fa8f54334a5a6a9/Cost_estimation_for_SUDS.pdf | P79: £15-£20 per m3 detention volume
A80: D05 | B80: 6 Flood | C80: Detention volume | D80: m³ | E80: 300 | F80: 500 | G80: 1000 | H80: B | I80: =IF(H80="L",E80,IF(H80="H",G80,F80)) -> 500 | J80: Analyst assumption | K80: New | L80: 100 mm of rain on 5 acres is ~2,000 m³; storage only needs to hold the excess over drain capacity.
A81: D06 | B81: 6 Flood | C81: Plinths, barriers, raised switchgear | D81: USD | E81: 15000 | F81: 35000 | G81: 70000 | H81: B | I81: =IF(H81="L",E81,IF(H81="H",G81,F81)) -> 35000 | J81: Analyst assumption | K81: Unsupported | L81: Bottom-up: machine plinths ~USD 3k, raising 300 m² by 0.3 m ~USD 10–15k, plus barriers and a transformer bund. | N81: UK FloodReady Review 2025 | O81: https://assets.publishing.service.gov.uk/media/68ef85ce2adc28a81b4ad0e9/FloodReadyReport-_an_action_plan_to_build_the_resilience_of_people_and_properties.pdf | P81: less than £1,200 per plot (household)
A82: D07 | B82: 6 Flood | C82: Flood depth with measures | D82: m | E82: 0 | F82: 0.1 | G82: 0.3 | H82: B | I82: =IF(H82="L",E82,IF(H82="H",G82,F82)) -> 0.1 | J82: Analyst assumption | K82: Unsupported | L82: Depends on hydraulic design; replace with engineer's estimate.
A83: D08 | B83: 6 Flood | C83: O&M | D83: % capex/yr | E83: 0.01 | F83: 0.02 | G83: 0.04 | H83: B | I83: =IF(H83="L",E83,IF(H83="H",G83,F83)) -> 0.02 | J83: Transferable evidence | K83: Confirmed | L83: Drain clearing before each rainy season. | N83: UK Environment Agency SuDS costs | O83: https://assets.publishing.service.gov.uk/media/6034ee6c8fa8f54334a5a6a9/Cost_estimation_for_SUDS.pdf | P83: 0.5–10% of capex
A84: E01 | B84: 7 Energy | C84: Solar PV installed | D84: USD/kWp | E84: 800 | F84: 1000 | G84: 1300 | H84: B | I84: =IF(H84="L",E84,IF(H84="H",G84,F84)) -> 1000 | J84: Local field evidence | K84: Adjusted | L84: Module prices fell after 2023; current Ghana examples sit near USD 1,000/kWp. Free Zone status should remove duty on panels and inverters. | N84: UKGCC 2023 | O84: https://ukgcc.com.gh/wp-content/uploads/2023/03/New-possibilities-for-solar-power-in-Ghana-2.pdf | P84: between $900 and $1400 per kW | Q84: SurgePV, Jun 2026 | R84: https://www.surgepv.com/blog/solar-incentives-in-ghana | S84: GHS 1,800,000 [150 kW]
A85: E02 | B85: 7 Energy | C85: Solar yield, Tema | D85: kWh/kWp/yr | E85: 1350 | F85: 1480 | G85: 1560 | H85: B | I85: =IF(H85="L",E85,IF(H85="H",G85,F85)) -> 1480 | J85: Local field evidence | K85: Adjusted | L85: Spot-checked. Harmattan dust lowers real output below the atlas figure. | M85: Previous high of 1,800 was unsupported. The Daystar/Nexans '47.7 MWh' figure is a typo. | N85: Global Solar Atlas | O85: https://api.globalsolaratlas.info/data/lta?loc=5.67,0.00 | P85: PVOUT 1514.36 kWh/kWp | Q85: Kasapreko 400 kWp project | R85: https://www.greenbuildingafrica.co.za/cross-boundary-gets-400kw-solar-pv-rooftop-project-over-the-line-in-ghana/ | S85: 570,570 kWh annually
A86: E03 | B86: 7 Energy | C86: Grid tariff avoided | D86: USD/kWh | E86: 0.18 | F86: 0.19 | G86: 0.21 | H86: B | I86: =IF(H86="L",E86,IF(H86="H",G86,F86)) -> 0.19 | J86: Local field evidence | K86: Confirmed | L86: Spot-checked. Levies are unresolved; VAT is recoverable for a registered manufacturer. | N86: PURC tariff, 1 Jul 2026 | O86: https://purc.com.gh/attachment/346541-20260729120703.pdf | P86: 301+ … 224.0395 GHp/kWh; SLT-LV 240.2104; SLT-MV 208.6329
A87: E04 | B87: 7 Energy | C87: Diesel generation fuel cost | D87: USD/kWh | E87: 0.45 | F87: 0.53 | G87: 0.68 | H87: B | I87: =IF(H87="L",E87,IF(H87="H",G87,F87)) -> 0.53 | J87: Local field evidence | K87: Adjusted | L87: Pump price ~USD 1.60–1.70/L × 0.28–0.40 L/kWh. | M87: Previous 0.41 used the September price floor. | N87: MyJoyOnline/NPA, 1 Oct 2026 | O87: https://www.myjoyonline.com/fuel-prices-to-rise-from-october-1-diesel-could-hit-gh%C2%A219-60-comac/ | P87: diesel from GH¢16.77 to GH¢17.97 per litre … GH¢19.60 | Q87: W Power fuel chart | R87: https://wpowerproducts.com/wp-content/uploads/2022/01/APPROXIMATE-FUEL-CONSUMPTION-CHART-Jan-2022.pdf | S87: 100 kW full load 7.4 gal/hr
A88: E05 | B88: 7 Energy | C88: Battery installed | D88: USD/kWh | E88: 250 | F88: 350 | G88: 500 | H88: B | I88: =IF(H88="L",E88,IF(H88="H",G88,F88)) -> 350 | J88: Transferable evidence | K88: Adjusted | L88: Small commercial systems in Ghana cost 2–3× the global turnkey average. Free Zone import relief may remove the 20% battery duty (unverified). | N88: BNEF via Energy-Storage.news, Dec 2025 | O88: https://www.energy-storage.news/?p=92133 | P88: turnkey … US$117/kWh
A89: E06a | B89: 7 Energy | C89: Critical electric load | D89: kW | E89: 20 | F89: 30 | G89: 50 | H89: B | I89: =IF(H89="L",E89,IF(H89="H",G89,F89)) -> 30 | J89: Analyst assumption | K89: Unsupported | L89: Heat is not electric; critical load is motors, vacuum, cold store, lab and IT. Needs a load audit. | N89: Nounagnon et al. 2024 | O89: https://ideas.repec.org/a/spr/envsyd/v44y2024i1d10.1007_s10669-023-09925-y.html | P89: 8–10 kWh of heat per kg
A90: E06b | B90: 7 Energy | C90: Battery backup hours | D90: h | E90: 4 | F90: 4 | G90: 6 | H90: B | I90: =IF(H90="L",E90,IF(H90="H",G90,F90)) -> 4 | J90: Analyst assumption | K90: Unsupported | L90: Heat is not electric; critical load is motors, vacuum, cold store, lab and IT. Needs a load audit. | N90: Nounagnon et al. 2024 | O90: https://ideas.repec.org/a/spr/envsyd/v44y2024i1d10.1007_s10669-023-09925-y.html | P90: 8–10 kWh of heat per kg
A91: E07 | B91: 7 Energy | C91: Spoilage and restart per outage | D91: USD | E91: 200 | F91: 500 | G91: 2000 | H91: B | I91: =IF(H91="L",E91,IF(H91="H",G91,F91)) -> 500 | J91: Analyst assumption | K91: Unsupported | L91: No per-event data. Total outage cost is cross-checked against the 0–10% of sales band. | N91: World Bank Enterprise Survey 2023 | O91: https://microdata.worldbank.org/catalog/6444 | P91: losses as % of annual sales … 5% … 10%
A92: E08 | B92: 7 Energy | C92: PPA discount to grid | D92: % | E92: 0.1 | F92: 0.2 | G92: 0.3 | H92: B | I92: =IF(H92="L",E92,IF(H92="H",G92,F92)) -> 0.2 | J92: Transferable evidence | K92: Adjusted | L92: At USD 1,000/kWp and 13% WACC, solar costs ~USD 0.10/kWh, leaving room for a 20–35% discount. | N92: Renewable Energy Magazine, 2019 | O92: https://renewableenergymagazine.com/pv_solar/daystar-power-expands-to-ghana-20190409 | P92: save clients up to 20 percent
A93: E09 | B93: 7 Energy | C93: PV size | D93: kWp | E93: 50 | F93: 100 | G93: 150 | H93: B | I93: =IF(H93="L",E93,IF(H93="H",G93,F93)) -> 100 | J93: Analyst assumption | K93: New | L93: Sized so daytime output stays below daytime load (no export credit needed).
A94: E10 | B94: 7 Energy | C94: Diesel genset installed | D94: USD/kVA | E94: 147 | F94: 346 | G94: 433 | H94: B | I94: =IF(H94="L",E94,IF(H94="H",G94,F94)) -> 346 | J94: Local field evidence | K94: Adjusted | L94: Seven new 50 kVA sets listed in Greater Accra: GH₵85,000–250,000 (USD 7.4k–21.6k), mostly GH₵200,000. Per kVA: USD 147 / 346 / 433. Classified listings, not quotes; installation may be extra. | N94: Jiji Ghana listings, Oct 2026 | O94: https://jiji.com.gh/search?query=50kva%20diesel%20generator | P94: 50KVA Stamford Silent Diesel Generator - GH₵ 85,000 … Perkins … GH₵ 200,000 … GH₵ 250,000
A95: E11 | B95: 7 Energy | C95: Outage protection from grid-tied PV alone (info only) | D95: % of outage | E95: 0 | F95: 0 | G95: 0 | H95: B | I95: =IF(H95="L",E95,IF(H95="H",G95,F95)) -> 0 | J95: Transferable evidence | K95: Confirmed | L95: Grid-tied PV without a battery shuts down in an outage; the Ghana anti-islanding clause itself was not verified. | N95: IEA policy database | O95: https://www.iea.org/policies/5646-net-metering-code | P95: only renewable energy generators with capacity up to 200 kW
A96: M01a | B96: 8 Diversification | C96: Mango butter yield, own screw press | D96: kg/t dry kernel | E96: 30 | F96: 50 | G96: 80 | H96: B | I96: =IF(H96="L",E96,IF(H96="H",G96,F96)) -> 50 | J96: Transferable evidence | K96: Adjusted | L96: 10% fat × 53% press recovery = 53 kg/t. Solvent toll extraction reaches ~90–95% recovery. | N96: Muchiri et al. 2012 | O96: https://link.springer.com/article/10.1007/s11746-012-2054-6 | P96: fat content … varied from 8.5 to 10.4 % | Q96: Barati et al. 2022 | R96: https://www.tropentag.de/2022/abstracts/posters/179.pdf | S96: oil recovery was 52.7%
A97: M01b | B97: 8 Diversification | C97: Mango butter yield, solvent toll extraction | D97: kg/t dry kernel | E97: 80 | F97: 100 | G97: 140 | H97: B | I97: =IF(H97="L",E97,IF(H97="H",G97,F97)) -> 100 | J97: Transferable evidence | K97: Adjusted | L97: 10% fat × 53% press recovery = 53 kg/t. Solvent toll extraction reaches ~90–95% recovery. | N97: Muchiri et al. 2012 | O97: https://link.springer.com/article/10.1007/s11746-012-2054-6 | P97: fat content … varied from 8.5 to 10.4 % | Q97: Barati et al. 2022 | R97: https://www.tropentag.de/2022/abstracts/posters/179.pdf | S97: oil recovery was 52.7%
A98: M02 | B98: 8 Diversification | C98: Mango butter price ex-factory | D98: USD/kg | E98: 5 | F98: 7.5 | G98: 11 | H98: B | I98: =IF(H98="L",E98,IF(H98="H",G98,F98)) -> 7.5 | J98: Transferable evidence | K98: Adjusted | L98: Ghana supply must compete with Indian refined butter (~USD 5.9–7.8/kg at ₹95.8/USD). | N98: IndiaMART, Oct 2026 | O98: https://m.indiamart.com/impcat/mango-butter.html | P98: Refined Mango Butter, Cosmetic Grade ₹565/kg | Q98: FRED DEXINUS, 25 Sep 2026 | R98: https://fred.stlouisfed.org/series/DEXINUS | S98: 95.8100
A99: M03 | B99: 8 Diversification | C99: Mango kernel cost | D99: USD/t | E99: 100 | F99: 200 | G99: 300 | H99: B | I99: =IF(H99="L",E99,IF(H99="H",G99,F99)) -> 200 | J99: Transferable evidence | K99: Adjusted | L99: Indian dried kernel ₹27–42/kg = USD 280–440/t at ₹95.8/USD. Ghanaian processor waste seeds are near-free at the gate; collection, de-husking and drying add cost. | N99: IndiaMART, Oct 2026 | O99: https://m.indiamart.com/impcat/mango-kernel.html | P99: ₹27/kg Dried White Mango Kernel | Q99: FRED DEXINUS, 25 Sep 2026 | R99: https://fred.stlouisfed.org/series/DEXINUS | S99: 95.8100
A100: M04 | B100: 8 Diversification | C100: Processing cost, toll or own press | D100: USD/kg butter | E100: 1.5 | F100: 2 | G100: 3 | H100: B | I100: =IF(H100="L",E100,IF(H100="H",G100,F100)) -> 2 | J100: Analyst assumption | K100: Adjusted | L100: No toll fee found. Bottom-up: solvent extraction toll of ~USD 50–100 per t kernel at ~100 kg butter per t, plus refining, gives USD 1.0–3.0 per kg butter.
A101: M05 | B101: 8 Diversification | C101: Share of shea replaceable in formulations | D101: % | E101: 0.1 | F101: 0.2 | G101: 0.35 | H101: B | I101: =IF(H101="L",E101,IF(H101="H",G101,F101)) -> 0.2 | J101: Analyst assumption | K101: Adjusted | L101: Mango butter and shea butter play the same role in formulations; 20% of shea volume replaceable without reformulating the main line is a reasoned base. Test in your products.
...

Sheet Hazards
A1: Flood depth-damage curves, industrial buildings (JRC, Huizinga et al. 2017)
A2: Share of asset value damaged by depth. Africa curve = Low/Base; Global curve = High (switch H09). Source: os-climate/physrisk copy of JRC data, spot-checked.
A4: Depth (m) | B4: Africa industrial | C4: Global industrial
A5: 0 | B5: 0 | C5: 0
A6: 0.5 | B6: 0.0627 | C6: 0.297
A7: 1 | B7: 0.2472 | C7: 0.48
A8: 1.5 | B8: 0.4033 | C8: 0.603
A9: 2 | B9: 0.4945 | C9: 0.694
A10: 3 | B10: 0.6847 | C10: 0.82
A12: Sources: https://raw.githubusercontent.com/os-climate/physrisk/main/docs/user_guide/vulnerability/vulnerability_functions/inundation_jrc/raw.csv
A13: https://publications.jrc.ec.europa.eu/repository/handle/JRC105688
A15: Scenario values used for hazard inputs (Inputs column E = Benign, F = Base, G = Stress):
A16: Input | B16: Benign | C16: Base | D16: Stress
A17: =Inputs!A25&" "&Inputs!C25 -> H01 Probability of a poor shea year | B17: =Inputs!E25 -> 0.15 | C17: =Inputs!F25 -> 0.3 | D17: =Inputs!G25 -> 0.5
A18: =Inputs!A26&" "&Inputs!C26 -> H02 Shortfall in a poor year | B18: =Inputs!E26 -> 0.2 | C18: =Inputs!F26 -> 0.3 | D18: =Inputs!G26 -> 0.5
A19: =Inputs!A28&" "&Inputs!C28 -> H04 Structural tree-loss decline | B19: =Inputs!E28 -> 0.005 | C19: =Inputs!F28 -> 0.015 | D19: =Inputs!G28 -> 0.025
A20: =Inputs!A29&" "&Inputs!C29 -> H05 Probability the Tema site floods | B20: =Inputs!E29 -> 0.05 | C20: =Inputs!F29 -> 0.1 | D20: =Inputs!G29 -> 0.25
A21: =Inputs!A30&" "&Inputs!C30 -> H06 Flood depth without measures | B21: =Inputs!E30 -> 0.3 | C21: =Inputs!F30 -> 0.5 | D21: =Inputs!G30 -> 1
A22: =Inputs!A32&" "&Inputs!C32 -> H08 Grid outage hours | B22: =Inputs!E32 -> 50 | C22: =Inputs!F32 -> 250 | D22: =Inputs!G32 -> 1100

Sheet Value chain
A1: Value chain: where the price of one jar goes, and how much stays in Ghana
A2: One 8 oz (227 g) shea body butter jar. Export channel = Amazon US via AWD and FBA; domestic channel = Ghana retail. Change the export share in Inputs G05.
A4: Crude butter per jar (kg) | B4: =in_V02/1000*in_V03/(1-in_V04) -> 0.16904255 | J4: Channel | K4: Stays in Ghana | L4: Leaves Ghana
A5: Retail units per year | B5: =in_C01*1000*in_C12/c_crude_kg -> 354940.21 | J5: Amazon US | K5: =E29 -> 4.0264108 | L5: =F29 -> 10.963589
A6: Amazon units per year | B6: =c_units*in_G05 -> 301699.18 | J6: Ghana retail | K6: =E42 -> 5.37 | L6: =F42 -> 0.63
A7: Customs value per jar (FOB, at cost) | B7: =SUM(B11:B15) -> 2.0233191
A10: Export channel: Amazon US | B10: USD per jar | C10: % of price | D10: Share in Ghana | E10: Stays in Ghana | F10: Leaves Ghana | G10: Inputs used
A11: Crude shea butter (paid to women processors) | B11: =c_crude_kg*in_C02 -> 0.47331915 | C11: =B11/in_V01 -> 0.03157566 | D11: 1 | E11: =B11*D11 -> 0.47331915 | F11: =B11-E11 -> 0 | G11: C02, V02–V04
A12: Other ingredients | B12: =in_V05 -> 0.3 | C12: =B12/in_V01 -> 0.020013342 | D12: =1-in_V06 -> 0.3 | E12: =B12*D12 -> 0.09 | F12: =B12-E12 -> 0.21 | G12: V05, V06
A13: Packaging | B13: =in_V07 -> 0.7 | C13: =B13/in_V01 -> 0.046697799 | D13: =1-in_V08 -> 0.4 | E13: =B13*D13 -> 0.28 | F13: =B13-E13 -> 0.42 | G13: V07, V08
A14: Factory conversion in Tema | B14: =in_V09 -> 0.5 | C14: =B14/in_V01 -> 0.03335557 | D14: 1 | E14: =B14*D14 -> 0.5 | F14: =B14-E14 -> 0 | G14: V09
A15: Ghana port, handling, documents | B15: =in_V10 -> 0.05 | C15: =B15/in_V01 -> 0.003335557 | D15: 1 | E15: =B15*D15 -> 0.05 | F15: =B15-E15 -> 0 | G15: V10
A16: Ocean freight to US | B16: =in_V12/in_V11 -> 0.1375 | C16: =B16/in_V01 -> 0.0091727819 | D16: 0 | E16: =B16*D16 -> 0 | F16: =B16-E16 -> 0.1375 | G16: V11, V12
A17: US import duty and tariff | B17: =(in_V13+in_V14)*c_fob -> 0.20233191 | C17: =B17/in_V01 -> 0.013497793 | D17: 0 | E17: =B17*D17 -> 0 | F17: =B17-E17 -> 0.20233191 | G17: V13, V14
A18: US broker, drayage, trucking | B18: =in_V15 -> 0.1 | C18: =B18/in_V01 -> 0.0066711141 | D18: 0 | E18: =B18*D18 -> 0 | F18: =B18-E18 -> 0.1 | G18: V15
A19: Amazon AWD storage | B19: =in_V16*in_V18*in_V17 -> 0.024 | C19: =B19/in_V01 -> 0.0016010674 | D19: 0 | E19: =B19*D19 -> 0 | F19: =B19-E19 -> 0.024 | G19: V16–V18
A20: Amazon AWD processing | B20: =in_V20/in_V19 -> 0.11666667 | C20: =B20/in_V01 -> 0.0077829664 | D20: 0 | E20: =B20*D20 -> 0 | F20: =B20-E20 -> 0.11666667 | G20: V19, V20
A21: Amazon AWD transport to FBA | B21: =in_V21*in_V18 -> 0.035 | C21: =B21/in_V01 -> 0.0023348899 | D21: 0 | E21: =B21*D21 -> 0 | F21: =B21-E21 -> 0.035 | G21: V18, V21
A22: Amazon FBA fulfillment fee | B22: =in_V22 -> 5.2 | C22: =B22/in_V01 -> 0.34689793 | D22: 0 | E22: =B22*D22 -> 0 | F22: =B22-E22 -> 5.2 | G22: V22
A23: Amazon FBA storage (1 month) | B23: =in_V23*in_V18 -> 0.0195 | C23: =B23/in_V01 -> 0.0013008672 | D23: 0 | E23: =B23*D23 -> 0 | F23: =B23-E23 -> 0.0195 | G23: V18, V23
A24: Amazon referral fee | B24: =IF(in_V01<=10,in_V32,in_V24)*in_V01 -> 2.2485 | C24: =B24/in_V01 -> 0.15 | D24: 0 | E24: =B24*D24 -> 0 | F24: =B24-E24 -> 2.2485 | G24: V01, V24
A25: Amazon advertising | B25: =in_V25*in_V01 -> 1.7988 | C25: =B25/in_V01 -> 0.12 | D25: 0 | E25: =B25*D25 -> 0 | F25: =B25-E25 -> 1.7988 | G25: V25
A26: Returns and damages | B26: =in_V26*in_V01 -> 0.4497 | C26: =B26/in_V01 -> 0.03 | D26: 0 | E26: =B26*D26 -> 0 | F26: =B26-E26 -> 0.4497 | G26: V26
A27: Amazon Professional plan | B27: =IF(c_units_amz>0,in_V31*12/c_units_amz,0) -> 0.001590591 | C27: =B27/in_V01 -> 0.00010611014 | D27: 0 | E27: =B27*D27 -> 0 | F27: =B27-E27 -> 0.001590591 | G27: V31
A28: Brand contribution margin (Ghanaian company) | B28: =in_V01-SUM(B11:B27) -> 2.6330917 | C28: =B28/in_V01 -> 0.17565655 | D28: 1 | E28: =B28*D28 -> 2.6330917 | F28: =B28-E28 -> 0 | G28: Free Zone: 0% tax years 1–10
A29: Retail price | B29: =SUM(B11:B28) -> 14.99 | C29: =SUM(C11:C28) -> 1 | E29: =SUM(E11:E28) -> 4.0264108 | F29: =SUM(F11:F28) -> 10.963589
A30: Share of the retail price that stays in Ghana | E30: =E29/B29 -> 0.26860646
A31: Share captured by Amazon (fees, storage, ads, plan) | E31: =(SUM(B19:B25)+B27)/B29 -> 0.63002383
A33: Domestic channel: Ghana retail | B33: USD per jar | C33: % of price | D33: Share in Ghana | E33: Stays in Ghana | F33: Leaves Ghana | G33: Inputs used
A34: Crude shea butter (paid to women processors) | B34: =c_crude_kg*in_C02 -> 0.47331915 | C34: =B34/in_V27 -> 0.078886525 | D34: 1 | E34: =B34*D34 -> 0.47331915 | F34: =B34-E34 -> 0 | G34: C02, V02–V04
A35: Other ingredients | B35: =in_V05 -> 0.3 | C35: =B35/in_V27 -> 0.05 | D35: =1-in_V06 -> 0.3 | E35: =B35*D35 -> 0.09 | F35: =B35-E35 -> 0.21 | G35: V05, V06
A36: Packaging | B36: =in_V07 -> 0.7 | C36: =B36/in_V27 -> 0.11666667 | D36: =1-in_V08 -> 0.4 | E36: =B36*D36 -> 0.28 | F36: =B36-E36 -> 0.42 | G36: V07, V08
A37: Factory conversion in Tema | B37: =in_V09 -> 0.5 | C37: =B37/in_V27 -> 0.083333333 | D37: 1 | E37: =B37*D37 -> 0.5 | F37: =B37-E37 -> 0 | G37: V09
A38: Domestic distribution | B38: =in_V30 -> 0.2 | C38: =B38/in_V27 -> 0.033333333 | D38: 1 | E38: =B38*D38 -> 0.2 | F38: =B38-E38 -> 0 | G38: V30
A39: Retailer and distributor margin | B39: =in_V28*in_V27 -> 2.1 | C39: =B39/in_V27 -> 0.35 | D39: 1 | E39: =B39*D39 -> 2.1 | F39: =B39-E39 -> 0 | G39: V28
A40: VAT and levies | B40: =in_V27*in_V29/(1+in_V29) -> 1 | C40: =B40/in_V27 -> 0.16666667 | D40: 1 | E40: =B40*D40 -> 1 | F40: =B40-E40 -> 0 | G40: V29
A41: Brand contribution margin (Ghanaian company) | B41: =in_V27-SUM(B34:B40) -> 0.72668085 | C41: =B41/in_V27 -> 0.12111348 | D41: 1 | E41: =B41*D41 -> 0.72668085 | F41: =B41-E41 -> 0
A42: Retail price | B42: =SUM(B34:B41) -> 6 | C42: =SUM(C34:C41) -> 1 | E42: =SUM(E34:E41) -> 5.37 | F42: =SUM(F34:F41) -> 0.63
A43: Share of the retail price that stays in Ghana | E43: =E42/B42 -> 0.895
A45: Summary
A46: Measure | B46: Amazon | C46: Ghana retail | D46: Weighted by export share | G46: Notes
A47: Retail price per jar | B47: =B29 -> 14.99 | C47: =B42 -> 6 | D47: =in_G05*B47+(1-in_G05)*C47 -> 13.6415
A48: Stays in Ghana per jar | B48: =E29 -> 4.0264108 | C48: =E42 -> 5.37 | D48: =in_G05*B48+(1-in_G05)*C48 -> 4.2279492
A49: Share of price staying in Ghana | B49: =E30 -> 0.26860646 | C49: =E43 -> 0.895 | D49: =D48/D47 -> 0.30993287 | G49: Value-weighted across channels
A50: Paid to women processors per jar | B50: =B11 -> 0.47331915 | C50: =B34 -> 0.47331915 | D50: =in_G05*B50+(1-in_G05)*C50 -> 0.47331915
A51: Women processors' share of price | B51: =B50/B47 -> 0.03157566 | C51: =C50/C47 -> 0.078886525 | D51: =D50/D47 -> 0.034697002
A52: Brand margin per jar | B52: ='Value chain'!$B$28 -> 2.6330917 | C52: ='Value chain'!$B$41 -> 0.72668085 | D52: =in_G05*B52+(1-in_G05)*C52 -> 2.3471301
A54: Whole business per year (retail jars + bulk refined butter)
A55: Measure | B55: USD per year | G55: Notes
A56: Retail revenue | B56: =c_units*D47 -> 4841916.9 | G56: C01 × C12 ÷ crude kg per jar × weighted price
A57: Retail revenue staying in Ghana | B57: =c_units*D48 -> 1500669.2
A58: Bulk refined butter revenue (FOB) | B58: =in_C01*(1-in_C12)*(1-in_V04)*1000*in_C15 -> 723800 | G58: Buyer pays freight; ~all stays in Ghana
A59: Total revenue | B59: =B56+B58 -> 5565716.9
A60: Revenue staying in Ghana | B60: =B57+B58 -> 2224469.2
A61: Share of total revenue staying in Ghana | B61: =B60/B59 -> 0.39967343
A62: Contribution margin per t crude butter, retail | B62: =D52/c_crude_kg*1000 -> 13884.847 | G62: Feeds C11 = 2
A64: Share of jar price staying in Ghana at different export shares (live)
A65: Export share | B65: Share staying in Ghana | G65: Notes
A66: 0 | B66: =(A66*E29+(1-A66)*E42)/(A66*B29+(1-A66)*B42) -> 0.895
A67: 0.25 | B67: =(A67*E29+(1-A67)*E42)/(A67*B29+(1-A67)*B42) -> 0.61037923
A68: 0.5 | B68: =(A68*E29+(1-A68)*E42)/(A68*B29+(1-A68)*B42) -> 0.44766131
A69: 0.7 | B69: =(A69*E29+(1-A69)*E42)/(A69*B29+(1-A69)*B42) -> 0.360326
A70: 0.85 | B70: =(A70*E29+(1-A70)*E42)/(A70*B29+(1-A70)*B42) -> 0.30993287 | G70: Base case (G05 = 85%)
A71: 1 | B71: =(A71*E29+(1-A71)*E42)/(A71*B29+(1-A71)*B42) -> 0.26860646

Sheet Calc
A1: Derived quantities (formulas only)
A3: Quantity | B3: Name | C3: Value | D3: Formula logic
A4: Contribution margin per t crude butter, active | B4: c_margin | C4: =IF(in_C11=1,in_C03,in_C12*c_margin_vc+(1-in_C12)*in_C03) -> 5215.4542 | D4: C11 = 1 uses bulk benchmark C03; 2 blends value-chain margin (share C12) with bulk
A5: Value of one secured tonne of butter | B5: c_VST | C5: =(1-in_C05)*in_C04+in_C05*c_margin -> 2037.1363 | D5: Replaceable share pays premium C04; unreplaceable share loses margin
A6: Kernel needed | B6: c_kernel | C6: =in_C01/in_C13 -> 540.54054 | D6: t kernel per year
A7: Sourcing area | B7: c_catch | C7: =c_kernel*1000/(in_R05*in_F06) -> 6756.7568 | D7: ha = kernel kg ÷ (kg per tree × trees per ha)
A8: Annual contribution margin | B8: c_annual | C8: =in_C01*c_margin -> 1043090.8
A9: Daily contribution margin | B9: c_daily | C9: =c_annual/in_C14 -> 4172.3634
A10: Hourly contribution margin | B10: c_hourly | C10: =c_daily/in_C09 -> 260.77271
A11: Outage hours inside operating shifts | B11: c_out_hrs | C11: =in_H08*in_C09/24*in_C14/365 -> 114.15525 | D11: Outages spread over the year; only those in shifts on operating days count
A12: Average plant load | B12: c_avg_kw | C12: =in_C08*1000/(in_C14*in_C09) -> 62.5 | D12: kW
A13: Lost production margin from outages | B13: c_out_prod | C13: =c_out_hrs*c_hourly*in_C10 -> 14884.287
A14: Spoilage and restart from outages | B14: c_out_spoil | C14: =c_out_hrs/in_H10*in_E07 -> 19025.875
A15: Baseline outage cost per year | B15: c_out_cost | C15: =c_out_prod+c_out_spoil -> 33910.162 | D15: Lost margin not recovered + spoilage per outage event
A16: Outage cost avoided by battery | B16: c_bat_avoid | C16: =in_E14*(c_out_spoil+c_out_prod*MIN(1,in_E06a/c_avg_kw)) -> 18319.233 | D16: Critical loads protected; production continues only in proportion to load covered
A17: Outage cost avoided by genset | B17: c_gen_avoid | C17: =c_out_spoil+c_out_prod*MIN(1,in_E25/c_avg_kw) -> 26170.333
A18: Outage cost as share of sales | B18: c_out_pct | C18: =IF(c_sales>0,c_out_cost/c_sales,0) -> 0.0060926854 | D18: Check against 0–10% band reported by Ghanaian firms (WBES)
A19: Damage share at flood depth without measures | B19: c_D0 | C19: =INDEX(CHOOSE(in_H09,Hazards!$B$5:$B$10,Hazards!$C$5:$C$10),MATCH(MIN(MAX(in_H06,0),3),Hazards!$A$5:$A$10,1))+IF(MATCH(MIN(MAX(in_H06,0),3),Hazards!$A$5:$A$10,1)=6,0,(INDEX(CHOOSE(in_H09,Hazards!$B$5:$B$10,Hazards!$C$5:$C$10),MIN(MATCH(MIN(MAX(in_H06,0),3),Hazards!$A$5:$A$10,1)+1,6))-INDEX(CHOOSE(in_H09,Hazards!$B$5:$B$10,Hazards!$C$5:$C$10),MATCH(MIN(MAX(in_H06,0),3),Hazards!$A$5:$A$10,1)))*(MIN(MAX(in_H06,0),3)-INDEX(Hazards!$A$5:$A$10,MATCH(MIN(MAX(in_H06,0),3),Hazards!$A$5:$A$10,1)))/(INDEX(Hazards!$A$5:$A$10,MIN(MATCH(MIN(MAX(in_H06,0),3),Hazards!$A$5:$A$10,1)+1,6))-INDEX(Hazards!$A$5:$A$10,MATCH(MIN(MAX(in_H06,0),3),Hazards!$A$5:$A$10,1)))) -> 0.0627 | D19: Interpolated on Hazards curve
A20: Damage share at depth with measures | B20: c_D1 | C20: =INDEX(CHOOSE(in_H09,Hazards!$B$5:$B$10,Hazards!$C$5:$C$10),MATCH(MIN(MAX(in_D07,0),3),Hazards!$A$5:$A$10,1))+IF(MATCH(MIN(MAX(in_D07,0),3),Hazards!$A$5:$A$10,1)=6,0,(INDEX(CHOOSE(in_H09,Hazards!$B$5:$B$10,Hazards!$C$5:$C$10),MIN(MATCH(MIN(MAX(in_D07,0),3),Hazards!$A$5:$A$10,1)+1,6))-INDEX(CHOOSE(in_H09,Hazards!$B$5:$B$10,Hazards!$C$5:$C$10),MATCH(MIN(MAX(in_D07,0),3),Hazards!$A$5:$A$10,1)))*(MIN(MAX(in_D07,0),3)-INDEX(Hazards!$A$5:$A$10,MATCH(MIN(MAX(in_D07,0),3),Hazards!$A$5:$A$10,1)))/(INDEX(Hazards!$A$5:$A$10,MIN(MATCH(MIN(MAX(in_D07,0),3),Hazards!$A$5:$A$10,1)+1,6))-INDEX(Hazards!$A$5:$A$10,MATCH(MIN(MAX(in_D07,0),3),Hazards!$A$5:$A$10,1)))) -> 0.01254
A21: Property loss per flood, without | B21: c_prop0 | C21: =in_C07*c_D0 -> 112860
A22: Property loss per flood, with measures | B22: c_prop1 | C22: =in_C07*c_D1 -> 22572
A23: Downtime loss per flood, without | B23: c_bi0 | C23: =in_H07*c_daily*in_C10 -> 10430.908
A24: Downtime loss per flood, with measures | B24: c_bi1 | C24: =in_D09*c_daily*in_C10 -> 2086.1817
A25: Total loss per flood, without | B25: c_floss0 | C25: =c_prop0+c_bi0 -> 123290.91
A26: Total loss per flood, with measures | B26: c_floss1 | C26: =c_prop1+c_bi1 -> 24658.182
A27: Insurance recovery per flood, without works | B27: c_rec0 | C27: =in_N04*(MAX(0,c_prop0-MAX(in_N03a*c_prop0,in_N03b))+c_bi0) -> 78403.436 | D27: After deductible and under-insurance
A28: Insurance recovery per flood, with works | B28: c_rec1 | C28: =in_N04*(MAX(0,c_prop1-MAX(in_N03a*c_prop1,in_N03b))+c_bi1) -> 10260.727
A29: Annual insurance premium | B29: c_premium | C29: =in_N01*in_C07+in_N02*c_annual -> 7629.2725 | D29: Property incl. flood + business interruption on contribution margin
A30: Flood works capex | B30: c_flood_cap | C30: =in_D02*in_D01*(1+in_D03)+in_D05*in_D04+in_D06 -> 117325
A31: PV capex | B31: c_pv_cap | C31: =in_E09*in_E01 -> 100000
A32: Battery nameplate | B32: c_bat_kwh | C32: =in_E06a*in_E06b/(in_E16*in_E17*in_E18) -> 208.33333 | D32: kWh
A33: Battery capex incl. islanding | B33: c_bat_cap | C33: =c_bat_kwh*in_E05+in_E13 -> 82916.667
A34: Genset size | B34: c_gen_kva | C34: =in_E25*in_E19 -> 46.8 | D34: kVA
A35: Genset capex | B35: c_gen_cap | C35: =c_gen_kva*in_E10 -> 16192.8
A36: Genset fuel per year | B36: c_gen_fuel | C36: =c_out_hrs*MIN(in_E25,c_avg_kw)*in_E04 -> 1815.0685
A37: Irrigation capex incl. dry holes | B37: c_irr_cap | C37: =in_I03*(in_I01+(1/in_I02-1)*in_I08) -> 120577.78
A38: Apiary share of sourcing area | B38: c_api_share | C38: =MIN(1,in_A08/in_A10*PI()*in_A11^2*100/c_catch) -> 0.23247786 | D38: Apiaries × π r² (km² → ha) ÷ sourcing area
A39: Beeswax harvested | B39: c_wax | C39: =in_A08*in_A04*in_A02*in_A03 -> 104 | D39: kg per year
A40: Regeneration area planted | B40: c_regen_ha | C40: =in_R07/in_R09 -> 100 | D40: ha
A41: Share of supply served by stoves | B41: c_stove_served | C41: =MIN(1,in_S05*in_S06/in_C01) -> 1
A42: Biochar produced | B42: c_char | C42: =in_B01*in_B02 -> 60 | D42: t per year
A43: Mango butter yield, active route | B43: c_mango_yield | C43: =IF(in_M10=1,in_M01a,in_M01b) -> 100 | D43: kg per t kernel
A44: Mango butter produced | B44: c_mango_t | C44: =in_M06*c_mango_yield/1000 -> 10 | D44: t per year
A45: Mango pilot margin per year | B45: c_mango_margin | C45: =in_M06*c_mango_yield*(in_M02-in_M04)-in_M06*in_M03 -> 35000 | D45: Before overhead M11
A46: Mango margin per t | B46: c_mango_mpt | C46: =IF(c_mango_t>0,c_mango_margin/c_mango_t,0) -> 3500
A47: Mango substituted for shea in a poor year | B47: c_sub_t | C47: =MIN(c_mango_t,in_M05*in_H02*in_C01)*(1-in_G07) -> 7 | D47: t; capped by mango output and formulation limit, scaled by correlation

Sheet Supply
A1: Supply model: tonnes of crude butter and the value of supply lost (USD)
A2: Loss each year = (structural deficit + poor-year shortfall) × value of a secured tonne. Options cut the decline rate d, cut the poor-year loss (reduction), or add new supply.
A3: Year | D3: 0 | E3: 1 | F3: 2 | G3: 3 | H3: 4 | I3: 5 | J3: 6 | K3: 7 | L3: 8 | M3: 9 | N3: 10 | O3: 11 | P3: 12 | Q3: 13 | R3: 14 | S3: 15 | T3: 16 | U3: 17 | V3: 18 | W3: 19 | X3: 20 | Y3: 21 | Z3: 22 | AA3: 23 | AB3: 24 | AC3: 25 | AD3: 26 | AE3: 27 | AF3: 28 | AG3: 29 | AH3: 30
A5: Baseline (no options)
A6: Supply available (t butter) | D6: =IF(D$3=0,0,in_C01*in_C06*(1-in_H04)^D$3) -> 0 | E6: =IF(E$3=0,0,in_C01*in_C06*(1-in_H04)^E$3) -> 246.25 | F6: =IF(F$3=0,0,in_C01*in_C06*(1-in_H04)^F$3) -> 242.55625 | G6: =IF(G$3=0,0,in_C01*in_C06*(1-in_H04)^G$3) -> 238.91791 | H6: =IF(H$3=0,0,in_C01*in_C06*(1-in_H04)^H$3) -> 235.33414 | I6: =IF(I$3=0,0,in_C01*in_C06*(1-in_H04)^I$3) -> 231.80413 | J6: =IF(J$3=0,0,in_C01*in_C06*(1-in_H04)^J$3) -> 228.32706 | K6: =IF(K$3=0,0,in_C01*in_C06*(1-in_H04)^K$3) -> 224.90216 | ... AH6: =IF(AH$3=0,0,in_C01*in_C06*(1-in_H04)^AH$3) -> 158.86452
A7: Value of supply lost (USD) | D7: =IF(D$3=0,0,(MAX(0,in_C01-D6)+in_H01*in_H02*MIN(in_C01,D6))*c_VST) -> 0 | E7: =IF(E$3=0,0,(MAX(0,in_C01-E6)+in_H01*in_H02*MIN(in_C01,E6))*c_VST) -> 36668.453 | F7: =IF(F$3=0,0,(MAX(0,in_C01-F6)+in_H01*in_H02*MIN(in_C01,F6))*c_VST) -> 36668.453 | G7: =IF(G$3=0,0,(MAX(0,in_C01-G6)+in_H01*in_H02*MIN(in_C01,G6))*c_VST) -> 36668.453 | H7: =IF(H$3=0,0,(MAX(0,in_C01-H6)+in_H01*in_H02*MIN(in_C01,H6))*c_VST) -> 36668.453 | I7: =IF(I$3=0,0,(MAX(0,in_C01-I6)+in_H01*in_H02*MIN(in_C01,I6))*c_VST) -> 36668.453 | J7: =IF(J$3=0,0,(MAX(0,in_C01-J6)+in_H01*in_H02*MIN(in_C01,J6))*c_VST) -> 36668.453 | K7: =IF(K$3=0,0,(MAX(0,in_C01-K6)+in_H01*in_H02*MIN(in_C01,K6))*c_VST) -> 36668.453 | ... AH7: =IF(AH$3=0,0,(MAX(0,in_C01-AH6)+in_H01*in_H02*MIN(in_C01,AH6))*c_VST) -> 112925.15
A9: 1 Solar irrigation
A10: Decline rate d | B10: =in_H04 -> 0.015
A11: Poor-year loss reduction | B11: =in_P01*in_I05 -> 0.025
A12: New supply added (t butter) | D12: =IF(D$3=0,0,0) -> 0 | E12: =IF(E$3=0,0,0) -> 0 | F12: =IF(F$3=0,0,0) -> 0 | G12: =IF(G$3=0,0,0) -> 0 | H12: =IF(H$3=0,0,0) -> 0 | I12: =IF(I$3=0,0,0) -> 0 | J12: =IF(J$3=0,0,0) -> 0 | K12: =IF(K$3=0,0,0) -> 0 | ... AH12: =IF(AH$3=0,0,0) -> 0
A13: Supply available (t butter) | D13: =IF(D$3=0,0,in_C01*in_C06*(1-$B$10)^D$3+D12) -> 0 | E13: =IF(E$3=0,0,in_C01*in_C06*(1-$B$10)^E$3+E12) -> 246.25 | F13: =IF(F$3=0,0,in_C01*in_C06*(1-$B$10)^F$3+F12) -> 242.55625 | G13: =IF(G$3=0,0,in_C01*in_C06*(1-$B$10)^G$3+G12) -> 238.91791 | H13: =IF(H$3=0,0,in_C01*in_C06*(1-$B$10)^H$3+H12) -> 235.33414 | I13: =IF(I$3=0,0,in_C01*in_C06*(1-$B$10)^I$3+I12) -> 231.80413 | J13: =IF(J$3=0,0,in_C01*in_C06*(1-$B$10)^J$3+J12) -> 228.32706 | K13: =IF(K$3=0,0,in_C01*in_C06*(1-$B$10)^K$3+K12) -> 224.90216 | ... AH13: =IF(AH$3=0,0,in_C01*in_C06*(1-$B$10)^AH$3+AH12) -> 158.86452
A14: Value of supply lost (USD) | D14: =IF(D$3=0,0,(MAX(0,in_C01-D13)+in_H01*in_H02*MIN(in_C01,D13)*(1-$B$11))*c_VST) -> 0 | E14: =IF(E$3=0,0,(MAX(0,in_C01-E13)+in_H01*in_H02*MIN(in_C01,E13)*(1-$B$11))*c_VST) -> 35751.741 | F14: =IF(F$3=0,0,(MAX(0,in_C01-F13)+in_H01*in_H02*MIN(in_C01,F13)*(1-$B$11))*c_VST) -> 35751.741 | G14: =IF(G$3=0,0,(MAX(0,in_C01-G13)+in_H01*in_H02*MIN(in_C01,G13)*(1-$B$11))*c_VST) -> 35751.741 | H14: =IF(H$3=0,0,(MAX(0,in_C01-H13)+in_H01*in_H02*MIN(in_C01,H13)*(1-$B$11))*c_VST) -> 35751.741 | I14: =IF(I$3=0,0,(MAX(0,in_C01-I13)+in_H01*in_H02*MIN(in_C01,I13)*(1-$B$11))*c_VST) -> 35751.741 | J14: =IF(J$3=0,0,(MAX(0,in_C01-J13)+in_H01*in_H02*MIN(in_C01,J13)*(1-$B$11))*c_VST) -> 35751.741 | K14: =IF(K$3=0,0,(MAX(0,in_C01-K13)+in_H01*in_H02*MIN(in_C01,K13)*(1-$B$11))*c_VST) -> 35751.741 | ... AH14: =IF(AH$3=0,0,(MAX(0,in_C01-AH13)+in_H01*in_H02*MIN(in_C01,AH13)*(1-$B$11))*c_VST) -> 112196.99
A15: Supply benefit vs baseline (USD) | D15: =D7-D14 -> 0 | E15: =E7-E14 -> 916.71132 | F15: =F7-F14 -> 916.71132 | G15: =G7-G14 -> 916.71132 | H15: =H7-H14 -> 916.71132 | I15: =I7-I14 -> 916.71132 | J15: =J7-J14 -> 916.71132 | K15: =K7-K14 -> 916.71132 | ... AH15: =AH7-AH14 -> 728.16453
A16: 2 Apiaries
A17: Decline rate d | B17: =in_H04 -> 0.015
A18: Poor-year loss reduction | B18: =c_api_share*in_A07*in_H03 -> 0.0034871678
A19: New supply added (t butter) | D19: =IF(D$3=0,0,in_A06*c_api_share*D6) -> 0 | E19: =IF(E$3=0,0,in_A06*c_api_share*E6) -> 0 | F19: =IF(F$3=0,0,in_A06*c_api_share*F6) -> 0 | G19: =IF(G$3=0,0,in_A06*c_api_share*G6) -> 0 | H19: =IF(H$3=0,0,in_A06*c_api_share*H6) -> 0 | I19: =IF(I$3=0,0,in_A06*c_api_share*I6) -> 0 | J19: =IF(J$3=0,0,in_A06*c_api_share*J6) -> 0 | K19: =IF(K$3=0,0,in_A06*c_api_share*K6) -> 0 | ... AH19: =IF(AH$3=0,0,in_A06*c_api_share*AH6) -> 0
A20: Supply available (t butter) | D20: =IF(D$3=0,0,in_C01*in_C06*(1-$B$17)^D$3+D19) -> 0 | E20: =IF(E$3=0,0,in_C01*in_C06*(1-$B$17)^E$3+E19) -> 246.25 | F20: =IF(F$3=0,0,in_C01*in_C06*(1-$B$17)^F$3+F19) -> 242.55625 | G20: =IF(G$3=0,0,in_C01*in_C06*(1-$B$17)^G$3+G19) -> 238.91791 | H20: =IF(H$3=0,0,in_C01*in_C06*(1-$B$17)^H$3+H19) -> 235.33414 | I20: =IF(I$3=0,0,in_C01*in_C06*(1-$B$17)^I$3+I19) -> 231.80413 | J20: =IF(J$3=0,0,in_C01*in_C06*(1-$B$17)^J$3+J19) -> 228.32706 | K20: =IF(K$3=0,0,in_C01*in_C06*(1-$B$17)^K$3+K19) -> 224.90216 | ... AH20: =IF(AH$3=0,0,in_C01*in_C06*(1-$B$17)^AH$3+AH19) -> 158.86452
A21: Value of supply lost (USD) | D21: =IF(D$3=0,0,(MAX(0,in_C01-D20)+in_H01*in_H02*MIN(in_C01,D20)*(1-$B$18))*c_VST) -> 0 | E21: =IF(E$3=0,0,(MAX(0,in_C01-E20)+in_H01*in_H02*MIN(in_C01,E20)*(1-$B$18))*c_VST) -> 36540.584 | F21: =IF(F$3=0,0,(MAX(0,in_C01-F20)+in_H01*in_H02*MIN(in_C01,F20)*(1-$B$18))*c_VST) -> 36540.584 | G21: =IF(G$3=0,0,(MAX(0,in_C01-G20)+in_H01*in_H02*MIN(in_C01,G20)*(1-$B$18))*c_VST) -> 36540.584 | H21: =IF(H$3=0,0,(MAX(0,in_C01-H20)+in_H01*in_H02*MIN(in_C01,H20)*(1-$B$18))*c_VST) -> 36540.584 | I21: =IF(I$3=0,0,(MAX(0,in_C01-I20)+in_H01*in_H02*MIN(in_C01,I20)*(1-$B$18))*c_VST) -> 36540.584 | J21: =IF(J$3=0,0,(MAX(0,in_C01-J20)+in_H01*in_H02*MIN(in_C01,J20)*(1-$B$18))*c_VST) -> 36540.584 | K21: =IF(K$3=0,0,(MAX(0,in_C01-K20)+in_H01*in_H02*MIN(in_C01,K20)*(1-$B$18))*c_VST) -> 36540.584 | ... AH21: =IF(AH$3=0,0,(MAX(0,in_C01-AH20)+in_H01*in_H02*MIN(in_C01,AH20)*(1-$B$18))*c_VST) -> 112823.58
A22: Supply benefit vs baseline (USD) | D22: =D7-D21 -> 0 | E22: =E7-E21 -> 127.86905 | F22: =F7-F21 -> 127.86905 | G22: =G7-G21 -> 127.86905 | H22: =H7-H21 -> 127.86905 | I22: =I7-I21 -> 127.86905 | J22: =J7-J21 -> 127.86905 | K22: =K7-K21 -> 127.86905 | ... AH22: =AH7-AH21 -> 101.56928
A23: 3 Regeneration
A24: Decline rate d | B24: =in_H04 -> 0.015
A25: Poor-year loss reduction | B25: 0
A26: New supply added (t butter) | D26: =IF(D$3=0,0,in_R07*in_R03*in_R05/1000*in_C13*MIN(1,MAX(0,(D$3-in_R04a)/(in_R04b-in_R04a)))*in_R06) -> 0 | E26: =IF(E$3=0,0,in_R07*in_R03*in_R05/1000*in_C13*MIN(1,MAX(0,(E$3-in_R04a)/(in_R04b-in_R04a)))*in_R06) -> 0 | F26: =IF(F$3=0,0,in_R07*in_R03*in_R05/1000*in_C13*MIN(1,MAX(0,(F$3-in_R04a)/(in_R04b-in_R04a)))*in_R06) -> 0 | G26: =IF(G$3=0,0,in_R07*in_R03*in_R05/1000*in_C13*MIN(1,MAX(0,(G$3-in_R04a)/(in_R04b-in_R04a)))*in_R06) -> 0 | H26: =IF(H$3=0,0,in_R07*in_R03*in_R05/1000*in_C13*MIN(1,MAX(0,(H$3-in_R04a)/(in_R04b-in_R04a)))*in_R06) -> 0 | I26: =IF(I$3=0,0,in_R07*in_R03*in_R05/1000*in_C13*MIN(1,MAX(0,(I$3-in_R04a)/(in_R04b-in_R04a)))*in_R06) -> 0 | J26: =IF(J$3=0,0,in_R07*in_R03*in_R05/1000*in_C13*MIN(1,MAX(0,(J$3-in_R04a)/(in_R04b-in_R04a)))*in_R06) -> 0 | K26: =IF(K$3=0,0,in_R07*in_R03*in_R05/1000*in_C13*MIN(1,MAX(0,(K$3-in_R04a)/(in_R04b-in_R04a)))*in_R06) -> 0.296 | ... AH26: =IF(AH$3=0,0,in_R07*in_R03*in_R05/1000*in_C13*MIN(1,MAX(0,(AH$3-in_R04a)/(in_R04b-in_R04a)))*in_R06) -> 2.368
A27: Supply available (t butter) | D27: =IF(D$3=0,0,in_C01*in_C06*(1-$B$24)^D$3+D26) -> 0 | E27: =IF(E$3=0,0,in_C01*in_C06*(1-$B$24)^E$3+E26) -> 246.25 | F27: =IF(F$3=0,0,in_C01*in_C06*(1-$B$24)^F$3+F26) -> 242.55625 | G27: =IF(G$3=0,0,in_C01*in_C06*(1-$B$24)^G$3+G26) -> 238.91791 | H27: =IF(H$3=0,0,in_C01*in_C06*(1-$B$24)^H$3+H26) -> 235.33414 | I27: =IF(I$3=0,0,in_C01*in_C06*(1-$B$24)^I$3+I26) -> 231.80413 | J27: =IF(J$3=0,0,in_C01*in_C06*(1-$B$24)^J$3+J26) -> 228.32706 | K27: =IF(K$3=0,0,in_C01*in_C06*(1-$B$24)^K$3+K26) -> 225.19816 | ... AH27: =IF(AH$3=0,0,in_C01*in_C06*(1-$B$24)^AH$3+AH26) -> 161.23252
A28: Value of supply lost (USD) | D28: =IF(D$3=0,0,(MAX(0,in_C01-D27)+in_H01*in_H02*MIN(in_C01,D27)*(1-$B$25))*c_VST) -> 0 | E28: =IF(E$3=0,0,(MAX(0,in_C01-E27)+in_H01*in_H02*MIN(in_C01,E27)*(1-$B$25))*c_VST) -> 36668.453 | F28: =IF(F$3=0,0,(MAX(0,in_C01-F27)+in_H01*in_H02*MIN(in_C01,F27)*(1-$B$25))*c_VST) -> 36668.453 | G28: =IF(G$3=0,0,(MAX(0,in_C01-G27)+in_H01*in_H02*MIN(in_C01,G27)*(1-$B$25))*c_VST) -> 36668.453 | H28: =IF(H$3=0,0,(MAX(0,in_C01-H27)+in_H01*in_H02*MIN(in_C01,H27)*(1-$B$25))*c_VST) -> 36668.453 | I28: =IF(I$3=0,0,(MAX(0,in_C01-I27)+in_H01*in_H02*MIN(in_C01,I27)*(1-$B$25))*c_VST) -> 36668.453 | J28: =IF(J$3=0,0,(MAX(0,in_C01-J27)+in_H01*in_H02*MIN(in_C01,J27)*(1-$B$25))*c_VST) -> 36668.453 | K28: =IF(K$3=0,0,(MAX(0,in_C01-K27)+in_H01*in_H02*MIN(in_C01,K27)*(1-$B$25))*c_VST) -> 36668.453 | ... AH28: =IF(AH$3=0,0,(MAX(0,in_C01-AH27)+in_H01*in_H02*MIN(in_C01,AH27)*(1-$B$25))*c_VST) -> 108535.37
A29: Supply benefit vs baseline (USD) | D29: =D7-D28 -> 0 | E29: =E7-E28 -> 0 | F29: =F7-F28 -> 0 | G29: =G7-G28 -> 0 | H29: =H7-H28 -> 0 | I29: =I7-I28 -> 0 | J29: =J7-J28 -> 0 | K29: =K7-K28 -> 0 | ... AH29: =AH7-AH28 -> 4389.7842
A30: 5 Processing stoves
A31: Decline rate d | B31: =in_H04-in_S04 -> 0.0135
A32: Poor-year loss reduction | B32: =c_stove_served*in_I05 -> 0.05
A33: New supply added (t butter) | D33: =IF(D$3=0,0,0) -> 0 | E33: =IF(E$3=0,0,0) -> 0 | F33: =IF(F$3=0,0,0) -> 0 | G33: =IF(G$3=0,0,0) -> 0 | H33: =IF(H$3=0,0,0) -> 0 | I33: =IF(I$3=0,0,0) -> 0 | J33: =IF(J$3=0,0,0) -> 0 | K33: =IF(K$3=0,0,0) -> 0 | ... AH33: =IF(AH$3=0,0,0) -> 0
A34: Supply available (t butter) | D34: =IF(D$3=0,0,in_C01*in_C06*(1-$B$31)^D$3+D33) -> 0 | E34: =IF(E$3=0,0,in_C01*in_C06*(1-$B$31)^E$3+E33) -> 246.625 | F34: =IF(F$3=0,0,in_C01*in_C06*(1-$B$31)^F$3+F33) -> 243.29556 | G34: =IF(G$3=0,0,in_C01*in_C06*(1-$B$31)^G$3+G33) -> 240.01107 | H34: =IF(H$3=0,0,in_C01*in_C06*(1-$B$31)^H$3+H33) -> 236.77092 | I34: =IF(I$3=0,0,in_C01*in_C06*(1-$B$31)^I$3+I33) -> 233.57452 | J34: =IF(J$3=0,0,in_C01*in_C06*(1-$B$31)^J$3+J33) -> 230.42126 | K34: =IF(K$3=0,0,in_C01*in_C06*(1-$B$31)^K$3+K33) -> 227.31057 | ... AH34: =IF(AH$3=0,0,in_C01*in_C06*(1-$B$31)^AH$3+AH33) -> 166.28486
A35: Value of supply lost (USD) | D35: =IF(D$3=0,0,(MAX(0,in_C01-D34)+in_H01*in_H02*MIN(in_C01,D34)*(1-$B$32))*c_VST) -> 0 | E35: =IF(E$3=0,0,(MAX(0,in_C01-E34)+in_H01*in_H02*MIN(in_C01,E34)*(1-$B$32))*c_VST) -> 34835.03 | F35: =IF(F$3=0,0,(MAX(0,in_C01-F34)+in_H01*in_H02*MIN(in_C01,F34)*(1-$B$32))*c_VST) -> 34835.03 | G35: =IF(G$3=0,0,(MAX(0,in_C01-G34)+in_H01*in_H02*MIN(in_C01,G34)*(1-$B$32))*c_VST) -> 34835.03 | H35: =IF(H$3=0,0,(MAX(0,in_C01-H34)+in_H01*in_H02*MIN(in_C01,H34)*(1-$B$32))*c_VST) -> 34835.03 | I35: =IF(I$3=0,0,(MAX(0,in_C01-I34)+in_H01*in_H02*MIN(in_C01,I34)*(1-$B$32))*c_VST) -> 34835.03 | J35: =IF(J$3=0,0,(MAX(0,in_C01-J34)+in_H01*in_H02*MIN(in_C01,J34)*(1-$B$32))*c_VST) -> 34835.03 | K35: =IF(K$3=0,0,(MAX(0,in_C01-K34)+in_H01*in_H02*MIN(in_C01,K34)*(1-$B$32))*c_VST) -> 34835.03 | ... AH35: =IF(AH$3=0,0,(MAX(0,in_C01-AH34)+in_H01*in_H02*MIN(in_C01,AH34)*(1-$B$32))*c_VST) -> 97645.034
A36: Supply benefit vs baseline (USD) | D36: =D7-D35 -> 0 | E36: =E7-E35 -> 1833.4226 | F36: =F7-F35 -> 1833.4226 | G36: =G7-G35 -> 1833.4226 | H36: =H7-H35 -> 1833.4226 | I36: =I7-I35 -> 1833.4226 | J36: =J7-J35 -> 1833.4226 | K36: =K7-K35 -> 1833.4226 | ... AH36: =AH7-AH35 -> 15280.119
A37: 8 Mango substitution hedge
A38: Decline rate d | B38: =in_H04 -> 0.015
A39: Poor-year loss reduction | B39: =c_sub_t/(in_H02*in_C01) -> 0.11666667
A40: New supply added (t butter) | D40: =IF(D$3=0,0,0) -> 0 | E40: =IF(E$3=0,0,0) -> 0 | F40: =IF(F$3=0,0,0) -> 0 | G40: =IF(G$3=0,0,0) -> 0 | H40: =IF(H$3=0,0,0) -> 0 | I40: =IF(I$3=0,0,0) -> 0 | J40: =IF(J$3=0,0,0) -> 0 | K40: =IF(K$3=0,0,0) -> 0 | ... AH40: =IF(AH$3=0,0,0) -> 0
A41: Supply available (t butter) | D41: =IF(D$3=0,0,in_C01*in_C06*(1-$B$38)^D$3+D40) -> 0 | E41: =IF(E$3=0,0,in_C01*in_C06*(1-$B$38)^E$3+E40) -> 246.25 | F41: =IF(F$3=0,0,in_C01*in_C06*(1-$B$38)^F$3+F40) -> 242.55625 | G41: =IF(G$3=0,0,in_C01*in_C06*(1-$B$38)^G$3+G40) -> 238.91791 | H41: =IF(H$3=0,0,in_C01*in_C06*(1-$B$38)^H$3+H40) -> 235.33414 | I41: =IF(I$3=0,0,in_C01*in_C06*(1-$B$38)^I$3+I40) -> 231.80413 | J41: =IF(J$3=0,0,in_C01*in_C06*(1-$B$38)^J$3+J40) -> 228.32706 | K41: =IF(K$3=0,0,in_C01*in_C06*(1-$B$38)^K$3+K40) -> 224.90216 | ... AH41: =IF(AH$3=0,0,in_C01*in_C06*(1-$B$38)^AH$3+AH40) -> 158.86452
A42: Value of supply lost (USD) | D42: =IF(D$3=0,0,(MAX(0,in_C01-D41)+in_H01*in_H02*MIN(in_C01,D41)*(1-$B$39))*c_VST) -> 0 | E42: =IF(E$3=0,0,(MAX(0,in_C01-E41)+in_H01*in_H02*MIN(in_C01,E41)*(1-$B$39))*c_VST) -> 32390.467 | F42: =IF(F$3=0,0,(MAX(0,in_C01-F41)+in_H01*in_H02*MIN(in_C01,F41)*(1-$B$39))*c_VST) -> 32390.467 | G42: =IF(G$3=0,0,(MAX(0,in_C01-G41)+in_H01*in_H02*MIN(in_C01,G41)*(1-$B$39))*c_VST) -> 32390.467 | H42: =IF(H$3=0,0,(MAX(0,in_C01-H41)+in_H01*in_H02*MIN(in_C01,H41)*(1-$B$39))*c_VST) -> 32390.467 | I42: =IF(I$3=0,0,(MAX(0,in_C01-I41)+in_H01*in_H02*MIN(in_C01,I41)*(1-$B$39))*c_VST) -> 32390.467 | J42: =IF(J$3=0,0,(MAX(0,in_C01-J41)+in_H01*in_H02*MIN(in_C01,J41)*(1-$B$39))*c_VST) -> 32390.467 | K42: =IF(K$3=0,0,(MAX(0,in_C01-K41)+in_H01*in_H02*MIN(in_C01,K41)*(1-$B$39))*c_VST) -> 32390.467 | ... AH42: =IF(AH$3=0,0,(MAX(0,in_C01-AH41)+in_H01*in_H02*MIN(in_C01,AH41)*(1-$B$39))*c_VST) -> 109527.05
A43: Supply benefit vs baseline (USD) | D43: =D7-D42 -> 0 | E43: =E7-E42 -> 4277.9862 | F43: =F7-F42 -> 4277.9862 | G43: =G7-G42 -> 4277.9862 | H43: =H7-H42 -> 4277.9862 | I43: =I7-I42 -> 4277.9862 | J43: =J7-J42 -> 4277.9862 | K43: =K7-K42 -> 4277.9862 | ... AH43: =AH7-AH42 -> 3398.1012
A44: 9 Fire management
A45: Decline rate d | B45: =in_H04-in_F05*in_F03 -> 0.014
A46: Poor-year loss reduction | B46: =in_F03*in_H03*in_F04 -> 0.03
A47: New supply added (t butter) | D47: =IF(D$3=0,0,0) -> 0 | E47: =IF(E$3=0,0,0) -> 0 | F47: =IF(F$3=0,0,0) -> 0 | G47: =IF(G$3=0,0,0) -> 0 | H47: =IF(H$3=0,0,0) -> 0 | I47: =IF(I$3=0,0,0) -> 0 | J47: =IF(J$3=0,0,0) -> 0 | K47: =IF(K$3=0,0,0) -> 0 | ... AH47: =IF(AH$3=0,0,0) -> 0
A48: Supply available (t butter) | D48: =IF(D$3=0,0,in_C01*in_C06*(1-$B$45)^D$3+D47) -> 0 | E48: =IF(E$3=0,0,in_C01*in_C06*(1-$B$45)^E$3+E47) -> 246.5 | F48: =IF(F$3=0,0,in_C01*in_C06*(1-$B$45)^F$3+F47) -> 243.049 | G48: =IF(G$3=0,0,in_C01*in_C06*(1-$B$45)^G$3+G47) -> 239.64631 | H48: =IF(H$3=0,0,in_C01*in_C06*(1-$B$45)^H$3+H47) -> 236.29127 | I48: =IF(I$3=0,0,in_C01*in_C06*(1-$B$45)^I$3+I47) -> 232.98319 | J48: =IF(J$3=0,0,in_C01*in_C06*(1-$B$45)^J$3+J47) -> 229.72142 | K48: =IF(K$3=0,0,in_C01*in_C06*(1-$B$45)^K$3+K47) -> 226.50532 | ... AH48: =IF(AH$3=0,0,in_C01*in_C06*(1-$B$45)^AH$3+AH47) -> 163.77494
A49: Value of supply lost (USD) | D49: =IF(D$3=0,0,(MAX(0,in_C01-D48)+in_H01*in_H02*MIN(in_C01,D48)*(1-$B$46))*c_VST) -> 0 | E49: =IF(E$3=0,0,(MAX(0,in_C01-E48)+in_H01*in_H02*MIN(in_C01,E48)*(1-$B$46))*c_VST) -> 35568.399 | F49: =IF(F$3=0,0,(MAX(0,in_C01-F48)+in_H01*in_H02*MIN(in_C01,F48)*(1-$B$46))*c_VST) -> 35568.399 | G49: =IF(G$3=0,0,(MAX(0,in_C01-G48)+in_H01*in_H02*MIN(in_C01,G48)*(1-$B$46))*c_VST) -> 35568.399 | H49: =IF(H$3=0,0,(MAX(0,in_C01-H48)+in_H01*in_H02*MIN(in_C01,H48)*(1-$B$46))*c_VST) -> 35568.399 | I49: =IF(I$3=0,0,(MAX(0,in_C01-I48)+in_H01*in_H02*MIN(in_C01,I48)*(1-$B$46))*c_VST) -> 35568.399 | J49: =IF(J$3=0,0,(MAX(0,in_C01-J48)+in_H01*in_H02*MIN(in_C01,J48)*(1-$B$46))*c_VST) -> 35568.399 | K49: =IF(K$3=0,0,(MAX(0,in_C01-K48)+in_H01*in_H02*MIN(in_C01,K48)*(1-$B$46))*c_VST) -> 35568.399 | ... AH49: =IF(AH$3=0,0,(MAX(0,in_C01-AH48)+in_H01*in_H02*MIN(in_C01,AH48)*(1-$B$46))*c_VST) -> 102921.44
A50: Supply benefit vs baseline (USD) | D50: =D7-D49 -> 0 | E50: =E7-E49 -> 1100.0536 | F50: =F7-F49 -> 1100.0536 | G50: =G7-G49 -> 1100.0536 | H50: =H7-H49 -> 1100.0536 | I50: =I7-I49 -> 1100.0536 | J50: =J7-J49 -> 1100.0536 | K50: =K7-K49 -> 1100.0536 | ... AH50: =AH7-AH49 -> 10003.713
A51: Portfolio (selected options combined)
A52: Decline rate d | B52: =in_H04-Portfolio!$C$9*in_S04-Portfolio!$C$16*in_F05*in_F03 -> 0.0135
A53: Poor-year loss reduction | B53: =1-(1-in_I05*MAX(Portfolio!$C$5*in_P01,Portfolio!$C$9*c_stove_served))*(1-Portfolio!$C$6*Supply!$B$18)*(1-Portfolio!$C$15*Supply!$B$39)*(1-Portfolio!$C$16*Supply!$B$46) -> 0.16375965
A54: New supply added (t butter) | D54: =IF(D$3=0,0,Portfolio!$C$6*D19+Portfolio!$C$7*D26*MIN(1,in_R03+Portfolio!$C$5*in_I06)/in_R03) -> 0 | E54: =IF(E$3=0,0,Portfolio!$C$6*E19+Portfolio!$C$7*E26*MIN(1,in_R03+Portfolio!$C$5*in_I06)/in_R03) -> 0 | F54: =IF(F$3=0,0,Portfolio!$C$6*F19+Portfolio!$C$7*F26*MIN(1,in_R03+Portfolio!$C$5*in_I06)/in_R03) -> 0 | G54: =IF(G$3=0,0,Portfolio!$C$6*G19+Portfolio!$C$7*G26*MIN(1,in_R03+Portfolio!$C$5*in_I06)/in_R03) -> 0 | H54: =IF(H$3=0,0,Portfolio!$C$6*H19+Portfolio!$C$7*H26*MIN(1,in_R03+Portfolio!$C$5*in_I06)/in_R03) -> 0 | I54: =IF(I$3=0,0,Portfolio!$C$6*I19+Portfolio!$C$7*I26*MIN(1,in_R03+Portfolio!$C$5*in_I06)/in_R03) -> 0 | J54: =IF(J$3=0,0,Portfolio!$C$6*J19+Portfolio!$C$7*J26*MIN(1,in_R03+Portfolio!$C$5*in_I06)/in_R03) -> 0 | K54: =IF(K$3=0,0,Portfolio!$C$6*K19+Portfolio!$C$7*K26*MIN(1,in_R03+Portfolio!$C$5*in_I06)/in_R03) -> 0 | ... AH54: =IF(AH$3=0,0,Portfolio!$C$6*AH19+Portfolio!$C$7*AH26*MIN(1,in_R03+Portfolio!$C$5*in_I06)/in_R03) -> 0
A55: Supply available (t butter) | D55: =IF(D$3=0,0,in_C01*in_C06*(1-$B$52)^D$3+D54) -> 0 | E55: =IF(E$3=0,0,in_C01*in_C06*(1-$B$52)^E$3+E54) -> 246.625 | F55: =IF(F$3=0,0,in_C01*in_C06*(1-$B$52)^F$3+F54) -> 243.29556 | G55: =IF(G$3=0,0,in_C01*in_C06*(1-$B$52)^G$3+G54) -> 240.01107 | H55: =IF(H$3=0,0,in_C01*in_C06*(1-$B$52)^H$3+H54) -> 236.77092 | I55: =IF(I$3=0,0,in_C01*in_C06*(1-$B$52)^I$3+I54) -> 233.57452 | J55: =IF(J$3=0,0,in_C01*in_C06*(1-$B$52)^J$3+J54) -> 230.42126 | K55: =IF(K$3=0,0,in_C01*in_C06*(1-$B$52)^K$3+K54) -> 227.31057 | ... AH55: =IF(AH$3=0,0,in_C01*in_C06*(1-$B$52)^AH$3+AH54) -> 166.28486
A56: Value of supply lost (USD) | D56: =IF(D$3=0,0,(MAX(0,in_C01-D55)+in_H01*in_H02*MIN(in_C01,D55)*(1-$B$53))*c_VST) -> 0 | E56: =IF(E$3=0,0,(MAX(0,in_C01-E55)+in_H01*in_H02*MIN(in_C01,E55)*(1-$B$53))*c_VST) -> 30663.64 | F56: =IF(F$3=0,0,(MAX(0,in_C01-F55)+in_H01*in_H02*MIN(in_C01,F55)*(1-$B$53))*c_VST) -> 30663.64 | G56: =IF(G$3=0,0,(MAX(0,in_C01-G55)+in_H01*in_H02*MIN(in_C01,G55)*(1-$B$53))*c_VST) -> 30663.64 | H56: =IF(H$3=0,0,(MAX(0,in_C01-H55)+in_H01*in_H02*MIN(in_C01,H55)*(1-$B$53))*c_VST) -> 30663.64 | I56: =IF(I$3=0,0,(MAX(0,in_C01-I55)+in_H01*in_H02*MIN(in_C01,I55)*(1-$B$53))*c_VST) -> 30663.64 | J56: =IF(J$3=0,0,(MAX(0,in_C01-J55)+in_H01*in_H02*MIN(in_C01,J55)*(1-$B$53))*c_VST) -> 30663.64 | K56: =IF(K$3=0,0,(MAX(0,in_C01-K55)+in_H01*in_H02*MIN(in_C01,K55)*(1-$B$53))*c_VST) -> 30663.64 | ... AH56: =IF(AH$3=0,0,(MAX(0,in_C01-AH55)+in_H01*in_H02*MIN(in_C01,AH55)*(1-$B$53))*c_VST) -> 94176.839
A57: Supply benefit vs baseline (USD) | D57: =D7-D56 -> 0 | E57: =E7-E56 -> 6004.8129 | F57: =F7-F56 -> 6004.8129 | G57: =G7-G56 -> 6004.8129 | H57: =H7-H56 -> 6004.8129 | I57: =I7-I56 -> 6004.8129 | J57: =J7-J56 -> 6004.8129 | K57: =K7-K56 -> 6004.8129 | ... AH57: =AH7-AH56 -> 18748.314

Sheet Engine
A1: Factory cash flows by option (USD, constant 2026 dollars)
A2: FCF = (supply benefit + other benefit − opex) − capex − tax, set to zero after the option's horizon. Free Zone tax: 0% to year G04a, then export/domestic blend.
A3: Year | C3: NPV / total | D3: 0 | E3: 1 | F3: 2 | G3: 3 | H3: 4 | I3: 5 | J3: 6 | K3: 7 | L3: 8 | M3: 9 | N3: 10 | O3: 11 | P3: 12 | Q3: 13 | R3: 14 | S3: 15 | T3: 16 | U3: 17 | V3: 18 | W3: 19 | X3: 20 | Y3: 21 | Z3: 22 | AA3: 23 | AB3: 24 | AC3: 25 | AD3: 26 | AE3: 27 | AF3: 28 | AG3: 29 | AH3: 30
A4: Tax rate | D4: =IF(D$3<=in_G04a,0,in_G05*in_G04b+(1-in_G05)*in_G04c) -> 0 | E4: =IF(E$3<=in_G04a,0,in_G05*in_G04b+(1-in_G05)*in_G04c) -> 0 | F4: =IF(F$3<=in_G04a,0,in_G05*in_G04b+(1-in_G05)*in_G04c) -> 0 | G4: =IF(G$3<=in_G04a,0,in_G05*in_G04b+(1-in_G05)*in_G04c) -> 0 | H4: =IF(H$3<=in_G04a,0,in_G05*in_G04b+(1-in_G05)*in_G04c) -> 0 | I4: =IF(I$3<=in_G04a,0,in_G05*in_G04b+(1-in_G05)*in_G04c) -> 0 | J4: =IF(J$3<=in_G04a,0,in_G05*in_G04b+(1-in_G05)*in_G04c) -> 0 | K4: =IF(K$3<=in_G04a,0,in_G05*in_G04b+(1-in_G05)*in_G04c) -> 0 | ... AH4: =IF(AH$3<=in_G04a,0,in_G05*in_G04b+(1-in_G05)*in_G04c) -> 0.165
A5: Discount factor | D5: =1/(1+in_G01)^D$3 -> 1 | E5: =1/(1+in_G01)^E$3 -> 0.88495575 | F5: =1/(1+in_G01)^F$3 -> 0.78314668 | G5: =1/(1+in_G01)^G$3 -> 0.69305016 | H5: =1/(1+in_G01)^H$3 -> 0.61331873 | I5: =1/(1+in_G01)^I$3 -> 0.54275994 | J5: =1/(1+in_G01)^J$3 -> 0.48031853 | K5: =1/(1+in_G01)^K$3 -> 0.42506064 | ... AH5: =1/(1+in_G01)^AH$3 -> 0.025565053
A7: 1 Solar irrigation (nurseries + gardens) | B7: Horizon | C7: =in_G02a -> 20
A8: Active (1 = within horizon) | D8: =IF(D$3<=in_G02a,1,0) -> 1 | E8: =IF(E$3<=in_G02a,1,0) -> 1 | F8: =IF(F$3<=in_G02a,1,0) -> 1 | G8: =IF(G$3<=in_G02a,1,0) -> 1 | H8: =IF(H$3<=in_G02a,1,0) -> 1 | I8: =IF(I$3<=in_G02a,1,0) -> 1 | J8: =IF(J$3<=in_G02a,1,0) -> 1 | K8: =IF(K$3<=in_G02a,1,0) -> 1 | ... AH8: =IF(AH$3<=in_G02a,1,0) -> 0
A9: Capex | C9: =SUMPRODUCT(D9:AH9,D$5:AH$5) -> 125961.4 | D9: =IF(D$3=0,c_irr_cap,0)*(1-in_P02)+IF(AND(D$3>0,D$3<in_G02a,MOD(D$3,in_I10)=0),in_I03*in_I09*(1-in_P02),0) -> 120577.78 | E9: =IF(E$3=0,c_irr_cap,0)*(1-in_P02)+IF(AND(E$3>0,E$3<in_G02a,MOD(E$3,in_I10)=0),in_I03*in_I09*(1-in_P02),0) -> 0 | F9: =IF(F$3=0,c_irr_cap,0)*(1-in_P02)+IF(AND(F$3>0,F$3<in_G02a,MOD(F$3,in_I10)=0),in_I03*in_I09*(1-in_P02),0) -> 0 | G9: =IF(G$3=0,c_irr_cap,0)*(1-in_P02)+IF(AND(G$3>0,G$3<in_G02a,MOD(G$3,in_I10)=0),in_I03*in_I09*(1-in_P02),0) -> 0 | H9: =IF(H$3=0,c_irr_cap,0)*(1-in_P02)+IF(AND(H$3>0,H$3<in_G02a,MOD(H$3,in_I10)=0),in_I03*in_I09*(1-in_P02),0) -> 0 | I9: =IF(I$3=0,c_irr_cap,0)*(1-in_P02)+IF(AND(I$3>0,I$3<in_G02a,MOD(I$3,in_I10)=0),in_I03*in_I09*(1-in_P02),0) -> 0 | J9: =IF(J$3=0,c_irr_cap,0)*(1-in_P02)+IF(AND(J$3>0,J$3<in_G02a,MOD(J$3,in_I10)=0),in_I03*in_I09*(1-in_P02),0) -> 0 | K9: =IF(K$3=0,c_irr_cap,0)*(1-in_P02)+IF(AND(K$3>0,K$3<in_G02a,MOD(K$3,in_I10)=0),in_I03*in_I09*(1-in_P02),0) -> 0 | ... AH9: =IF(AH$3=0,c_irr_cap,0)*(1-in_P02)+IF(AND(AH$3>0,AH$3<in_G02a,MOD(AH$3,in_I10)=0),in_I03*in_I09*(1-in_P02),0) -> 0
A10: Supply benefit | D10: =Supply!D15 -> 0 | E10: =Supply!E15 -> 916.71132 | F10: =Supply!F15 -> 916.71132 | G10: =Supply!G15 -> 916.71132 | H10: =Supply!H15 -> 916.71132 | I10: =Supply!I15 -> 916.71132 | J10: =Supply!J15 -> 916.71132 | K10: =Supply!K15 -> 916.71132 | ... AH10: =Supply!AH15 -> 728.16453
A11: Other benefit | D11: =0 -> 0 | E11: =0 -> 0 | F11: =0 -> 0 | G11: =0 -> 0 | H11: =0 -> 0 | I11: =0 -> 0 | J11: =0 -> 0 | K11: =0 -> 0 | ... AH11: =0 -> 0
A12: Opex | D12: =IF(D$3=0,0,in_I07*in_I03*in_I01) -> 0 | E12: =IF(E$3=0,0,in_I07*in_I03*in_I01) -> 2216 | F12: =IF(F$3=0,0,in_I07*in_I03*in_I01) -> 2216 | G12: =IF(G$3=0,0,in_I07*in_I03*in_I01) -> 2216 | H12: =IF(H$3=0,0,in_I07*in_I03*in_I01) -> 2216 | I12: =IF(I$3=0,0,in_I07*in_I03*in_I01) -> 2216 | J12: =IF(J$3=0,0,in_I07*in_I03*in_I01) -> 2216 | K12: =IF(K$3=0,0,in_I07*in_I03*in_I01) -> 2216 | ... AH12: =IF(AH$3=0,0,in_I07*in_I03*in_I01) -> 2216
A13: Operating flow | D13: =D10+D11-D12 -> 0 | E13: =E10+E11-E12 -> -1299.2887 | F13: =F10+F11-F12 -> -1299.2887 | G13: =G10+G11-G12 -> -1299.2887 | H13: =H10+H11-H12 -> -1299.2887 | I13: =I10+I11-I12 -> -1299.2887 | J13: =J10+J11-J12 -> -1299.2887 | K13: =K10+K11-K12 -> -1299.2887 | ... AH13: =AH10+AH11-AH12 -> -1487.8355
A14: Tax | D14: =D$4*MAX(0,D13) -> 0 | E14: =E$4*MAX(0,E13) -> 0 | F14: =F$4*MAX(0,F13) -> 0 | G14: =G$4*MAX(0,G13) -> 0 | H14: =H$4*MAX(0,H13) -> 0 | I14: =I$4*MAX(0,I13) -> 0 | J14: =J$4*MAX(0,J13) -> 0 | K14: =K$4*MAX(0,K13) -> 0 | ... AH14: =AH$4*MAX(0,AH13) -> 0
A15: Free cash flow | C15: =SUMPRODUCT(D15:AH15,D$5:AH$5) -> -135111.79 | D15: =(D13-D9-D14)*D8 -> -120577.78 | E15: =(E13-E9-E14)*E8 -> -1299.2887 | F15: =(F13-F9-F14)*F8 -> -1299.2887 | G15: =(G13-G9-G14)*G8 -> -1299.2887 | H15: =(H13-H9-H14)*H8 -> -1299.2887 | I15: =(I13-I9-I14)*I8 -> -1299.2887 | J15: =(J13-J9-J14)*J8 -> -1299.2887 | K15: =(K13-K9-K14)*K8 -> -1299.2887 | ... AH15: =(AH13-AH9-AH14)*AH8 -> 0
A16: Supplier income (supplier account) | C16: =SUMPRODUCT(D16:AH16,D$5:AH$5) -> 70247.516 | D16: =(IF(D$3=0,0,in_I03*in_I04))*D8 -> 0 | E16: =(IF(E$3=0,0,in_I03*in_I04))*E8 -> 10000 | F16: =(IF(F$3=0,0,in_I03*in_I04))*F8 -> 10000 | G16: =(IF(G$3=0,0,in_I03*in_I04))*G8 -> 10000 | H16: =(IF(H$3=0,0,in_I03*in_I04))*H8 -> 10000 | I16: =(IF(I$3=0,0,in_I03*in_I04))*I8 -> 10000 | J16: =(IF(J$3=0,0,in_I03*in_I04))*J8 -> 10000 | K16: =(IF(K$3=0,0,in_I03*in_I04))*K8 -> 10000 | ... AH16: =(IF(AH$3=0,0,in_I03*in_I04))*AH8 -> 0
A17: PV of supply benefit (pre-tax) | C17: =SUMPRODUCT(D17:AH17,D$5:AH$5) -> 6416.4597 | D17: =D10*D8 -> 0 | E17: =E10*E8 -> 916.71132 | F17: =F10*F8 -> 916.71132 | G17: =G10*G8 -> 916.71132 | H17: =H10*H8 -> 916.71132 | I17: =I10*I8 -> 916.71132 | J17: =J10*J8 -> 916.71132 | K17: =K10*K8 -> 916.71132 | ... AH17: =AH10*AH8 -> 0
A19: 2 Apiaries | B19: Horizon | C19: =in_G02a -> 20
A20: Active (1 = within horizon) | D20: =IF(D$3<=in_G02a,1,0) -> 1 | E20: =IF(E$3<=in_G02a,1,0) -> 1 | F20: =IF(F$3<=in_G02a,1,0) -> 1 | G20: =IF(G$3<=in_G02a,1,0) -> 1 | H20: =IF(H$3<=in_G02a,1,0) -> 1 | I20: =IF(I$3<=in_G02a,1,0) -> 1 | J20: =IF(J$3<=in_G02a,1,0) -> 1 | K20: =IF(K$3<=in_G02a,1,0) -> 1 | ... AH20: =IF(AH$3<=in_G02a,1,0) -> 0
A21: Capex | C21: =SUMPRODUCT(D21:AH21,D$5:AH$5) -> 32114.744 | D21: =IF(AND(MOD(D$3,in_A13)=0,D$3<in_G02a),in_A08*in_A01*(1-in_P02),0) -> 20000 | E21: =IF(AND(MOD(E$3,in_A13)=0,E$3<in_G02a),in_A08*in_A01*(1-in_P02),0) -> 0 | F21: =IF(AND(MOD(F$3,in_A13)=0,F$3<in_G02a),in_A08*in_A01*(1-in_P02),0) -> 0 | G21: =IF(AND(MOD(G$3,in_A13)=0,G$3<in_G02a),in_A08*in_A01*(1-in_P02),0) -> 0 | H21: =IF(AND(MOD(H$3,in_A13)=0,H$3<in_G02a),in_A08*in_A01*(1-in_P02),0) -> 0 | I21: =IF(AND(MOD(I$3,in_A13)=0,I$3<in_G02a),in_A08*in_A01*(1-in_P02),0) -> 0 | J21: =IF(AND(MOD(J$3,in_A13)=0,J$3<in_G02a),in_A08*in_A01*(1-in_P02),0) -> 0 | K21: =IF(AND(MOD(K$3,in_A13)=0,K$3<in_G02a),in_A08*in_A01*(1-in_P02),0) -> 20000 | ... AH21: =IF(AND(MOD(AH$3,in_A13)=0,AH$3<in_G02a),in_A08*in_A01*(1-in_P02),0) -> 0
A22: Supply benefit | D22: =Supply!D22 -> 0 | E22: =Supply!E22 -> 127.86905 | F22: =Supply!F22 -> 127.86905 | G22: =Supply!G22 -> 127.86905 | H22: =Supply!H22 -> 127.86905 | I22: =Supply!I22 -> 127.86905 | J22: =Supply!J22 -> 127.86905 | K22: =Supply!K22 -> 127.86905 | ... AH22: =Supply!AH22 -> 101.56928
A23: Other benefit | D23: =IF(D$3=0,0,c_wax*MAX(0,in_A09-in_A05)) -> 0 | E23: =IF(E$3=0,0,c_wax*MAX(0,in_A09-in_A05)) -> 0 | F23: =IF(F$3=0,0,c_wax*MAX(0,in_A09-in_A05)) -> 0 | G23: =IF(G$3=0,0,c_wax*MAX(0,in_A09-in_A05)) -> 0 | H23: =IF(H$3=0,0,c_wax*MAX(0,in_A09-in_A05)) -> 0 | I23: =IF(I$3=0,0,c_wax*MAX(0,in_A09-in_A05)) -> 0 | J23: =IF(J$3=0,0,c_wax*MAX(0,in_A09-in_A05)) -> 0 | K23: =IF(K$3=0,0,c_wax*MAX(0,in_A09-in_A05)) -> 0 | ... AH23: =IF(AH$3=0,0,c_wax*MAX(0,in_A09-in_A05)) -> 0
A24: Opex | D24: =0 -> 0 | E24: =0 -> 0 | F24: =0 -> 0 | G24: =0 -> 0 | H24: =0 -> 0 | I24: =0 -> 0 | J24: =0 -> 0 | K24: =0 -> 0 | ... AH24: =0 -> 0
A25: Operating flow | D25: =D22+D23-D24 -> 0 | E25: =E22+E23-E24 -> 127.86905 | F25: =F22+F23-F24 -> 127.86905 | G25: =G22+G23-G24 -> 127.86905 | H25: =H22+H23-H24 -> 127.86905 | I25: =I22+I23-I24 -> 127.86905 | J25: =J22+J23-J24 -> 127.86905 | K25: =K22+K23-K24 -> 127.86905 | ... AH25: =AH22+AH23-AH24 -> 101.56928
A26: Tax | D26: =D$4*MAX(0,D25) -> 0 | E26: =E$4*MAX(0,E25) -> 0 | F26: =F$4*MAX(0,F25) -> 0 | G26: =G$4*MAX(0,G25) -> 0 | H26: =H$4*MAX(0,H25) -> 0 | I26: =I$4*MAX(0,I25) -> 0 | J26: =J$4*MAX(0,J25) -> 0 | K26: =K$4*MAX(0,K25) -> 0 | ... AH26: =AH$4*MAX(0,AH25) -> 16.758931
A27: Free cash flow | C27: =SUMPRODUCT(D27:AH27,D$5:AH$5) -> -31252.925 | D27: =(D25-D21-D26)*D20 -> -20000 | E27: =(E25-E21-E26)*E20 -> 127.86905 | F27: =(F25-F21-F26)*F20 -> 127.86905 | G27: =(G25-G21-G26)*G20 -> 127.86905 | H27: =(H25-H21-H26)*H20 -> 127.86905 | I27: =(I25-I21-I26)*I20 -> 127.86905 | J27: =(J25-J21-J26)*J20 -> 127.86905 | K27: =(K25-K21-K26)*K20 -> -19872.131 | ... AH27: =(AH25-AH21-AH26)*AH20 -> 0
A28: Supplier income (supplier account) | C28: =SUMPRODUCT(D28:AH28,D$5:AH$5) -> 60381.955 | D28: =(IF(D$3=0,0,in_A08*in_A04*in_A02*in_A12+c_wax*in_A05))*D20 -> 0 | E28: =(IF(E$3=0,0,in_A08*in_A04*in_A02*in_A12+c_wax*in_A05))*E20 -> 8595.6 | F28: =(IF(F$3=0,0,in_A08*in_A04*in_A02*in_A12+c_wax*in_A05))*F20 -> 8595.6 | G28: =(IF(G$3=0,0,in_A08*in_A04*in_A02*in_A12+c_wax*in_A05))*G20 -> 8595.6 | H28: =(IF(H$3=0,0,in_A08*in_A04*in_A02*in_A12+c_wax*in_A05))*H20 -> 8595.6 | I28: =(IF(I$3=0,0,in_A08*in_A04*in_A02*in_A12+c_wax*in_A05))*I20 -> 8595.6 | J28: =(IF(J$3=0,0,in_A08*in_A04*in_A02*in_A12+c_wax*in_A05))*J20 -> 8595.6 | K28: =(IF(K$3=0,0,in_A08*in_A04*in_A02*in_A12+c_wax*in_A05))*K20 -> 8595.6 | ... AH28: =(IF(AH$3=0,0,in_A08*in_A04*in_A02*in_A12+c_wax*in_A05))*AH20 -> 0
A29: PV of supply benefit (pre-tax) | C29: =SUMPRODUCT(D29:AH29,D$5:AH$5) -> 895.01088 | D29: =D22*D20 -> 0 | E29: =E22*E20 -> 127.86905 | F29: =F22*F20 -> 127.86905 | G29: =G22*G20 -> 127.86905 | H29: =H22*H20 -> 127.86905 | I29: =I22*I20 -> 127.86905 | J29: =J22*J20 -> 127.86905 | K29: =K22*K20 -> 127.86905 | ... AH29: =AH22*AH20 -> 0
A31: 3 Regeneration & agroforestry | B31: Horizon | C31: =in_G02b -> 30
A32: Active (1 = within horizon) | D32: =IF(D$3<=in_G02b,1,0) -> 1 | E32: =IF(E$3<=in_G02b,1,0) -> 1 | F32: =IF(F$3<=in_G02b,1,0) -> 1 | G32: =IF(G$3<=in_G02b,1,0) -> 1 | H32: =IF(H$3<=in_G02b,1,0) -> 1 | I32: =IF(I$3<=in_G02b,1,0) -> 1 | J32: =IF(J$3<=in_G02b,1,0) -> 1 | K32: =IF(K$3<=in_G02b,1,0) -> 1 | ... AH32: =IF(AH$3<=in_G02b,1,0) -> 1
A33: Capex | C33: =SUMPRODUCT(D33:AH33,D$5:AH$5) -> 49410.085 | D33: =(IF(D$3=0,in_R07*in_R01,0)+IF(D$3<=in_R10,c_regen_ha*in_R02/(in_R10+1),0))*(1-in_P02) -> 28750 | E33: =(IF(E$3=0,in_R07*in_R01,0)+IF(E$3<=in_R10,c_regen_ha*in_R02/(in_R10+1),0))*(1-in_P02) -> 8750 | F33: =(IF(F$3=0,in_R07*in_R01,0)+IF(F$3<=in_R10,c_regen_ha*in_R02/(in_R10+1),0))*(1-in_P02) -> 8750 | G33: =(IF(G$3=0,in_R07*in_R01,0)+IF(G$3<=in_R10,c_regen_ha*in_R02/(in_R10+1),0))*(1-in_P02) -> 8750 | H33: =(IF(H$3=0,in_R07*in_R01,0)+IF(H$3<=in_R10,c_regen_ha*in_R02/(in_R10+1),0))*(1-in_P02) -> 0 | I33: =(IF(I$3=0,in_R07*in_R01,0)+IF(I$3<=in_R10,c_regen_ha*in_R02/(in_R10+1),0))*(1-in_P02) -> 0 | J33: =(IF(J$3=0,in_R07*in_R01,0)+IF(J$3<=in_R10,c_regen_ha*in_R02/(in_R10+1),0))*(1-in_P02) -> 0 | K33: =(IF(K$3=0,in_R07*in_R01,0)+IF(K$3<=in_R10,c_regen_ha*in_R02/(in_R10+1),0))*(1-in_P02) -> 0 | ... AH33: =(IF(AH$3=0,in_R07*in_R01,0)+IF(AH$3<=in_R10,c_regen_ha*in_R02/(in_R10+1),0))*(1-in_P02) -> 0
A34: Supply benefit | D34: =Supply!D29 -> 0 | E34: =Supply!E29 -> 0 | F34: =Supply!F29 -> 0 | G34: =Supply!G29 -> 0 | H34: =Supply!H29 -> 0 | I34: =Supply!I29 -> 0 | J34: =Supply!J29 -> 0 | K34: =Supply!K29 -> 0 | ... AH34: =Supply!AH29 -> 4389.7842
A35: Other benefit | D35: =IF(D$3=0,0,in_G08*c_regen_ha*in_R03*in_R08a*in_R08b*MIN(1,D$3/in_R11)) -> 0 | E35: =IF(E$3=0,0,in_G08*c_regen_ha*in_R03*in_R08a*in_R08b*MIN(1,E$3/in_R11)) -> 0 | F35: =IF(F$3=0,0,in_G08*c_regen_ha*in_R03*in_R08a*in_R08b*MIN(1,F$3/in_R11)) -> 0 | G35: =IF(G$3=0,0,in_G08*c_regen_ha*in_R03*in_R08a*in_R08b*MIN(1,G$3/in_R11)) -> 0 | H35: =IF(H$3=0,0,in_G08*c_regen_ha*in_R03*in_R08a*in_R08b*MIN(1,H$3/in_R11)) -> 0 | I35: =IF(I$3=0,0,in_G08*c_regen_ha*in_R03*in_R08a*in_R08b*MIN(1,I$3/in_R11)) -> 0 | J35: =IF(J$3=0,0,in_G08*c_regen_ha*in_R03*in_R08a*in_R08b*MIN(1,J$3/in_R11)) -> 0 | K35: =IF(K$3=0,0,in_G08*c_regen_ha*in_R03*in_R08a*in_R08b*MIN(1,K$3/in_R11)) -> 0 | ... AH35: =IF(AH$3=0,0,in_G08*c_regen_ha*in_R03*in_R08a*in_R08b*MIN(1,AH$3/in_R11)) -> 0
A36: Opex | D36: =0 -> 0 | E36: =0 -> 0 | F36: =0 -> 0 | G36: =0 -> 0 | H36: =0 -> 0 | I36: =0 -> 0 | J36: =0 -> 0 | K36: =0 -> 0 | ... AH36: =0 -> 0
A37: Operating flow | D37: =D34+D35-D36 -> 0 | E37: =E34+E35-E36 -> 0 | F37: =F34+F35-F36 -> 0 | G37: =G34+G35-G36 -> 0 | H37: =H34+H35-H36 -> 0 | I37: =I34+I35-I36 -> 0 | J37: =J34+J35-J36 -> 0 | K37: =K34+K35-K36 -> 0 | ... AH37: =AH34+AH35-AH36 -> 4389.7842
A38: Tax | D38: =D$4*MAX(0,D37) -> 0 | E38: =E$4*MAX(0,E37) -> 0 | F38: =F$4*MAX(0,F37) -> 0 | G38: =G$4*MAX(0,G37) -> 0 | H38: =H$4*MAX(0,H37) -> 0 | I38: =I$4*MAX(0,I37) -> 0 | J38: =J$4*MAX(0,J37) -> 0 | K38: =K$4*MAX(0,K37) -> 0 | ... AH38: =AH$4*MAX(0,AH37) -> 724.31439
A39: Free cash flow | C39: =SUMPRODUCT(D39:AH39,D$5:AH$5) -> -45446.693 | D39: =(D37-D33-D38)*D32 -> -28750 | E39: =(E37-E33-E38)*E32 -> -8750 | F39: =(F37-F33-F38)*F32 -> -8750 | G39: =(G37-G33-G38)*G32 -> -8750 | H39: =(H37-H33-H38)*H32 -> 0 | I39: =(I37-I33-I38)*I32 -> 0 | J39: =(J37-J33-J38)*J32 -> 0 | K39: =(K37-K33-K38)*K32 -> 0 | ... AH39: =(AH37-AH33-AH38)*AH32 -> 3665.4698
A40: Supplier income (supplier account) | C40: =SUMPRODUCT(D40:AH40,D$5:AH$5) -> 0 | D40: =0 -> 0 | E40: =0 -> 0 | F40: =0 -> 0 | G40: =0 -> 0 | H40: =0 -> 0 | I40: =0 -> 0 | J40: =0 -> 0 | K40: =0 -> 0 | ... AH40: =0 -> 0
A41: PV of supply benefit (pre-tax) | C41: =SUMPRODUCT(D41:AH41,D$5:AH$5) -> 4746.5774 | D41: =D34*D32 -> 0 | E41: =E34*E32 -> 0 | F41: =F34*F32 -> 0 | G41: =G34*G32 -> 0 | H41: =H34*H32 -> 0 | I41: =I34*I32 -> 0 | J41: =J34*J32 -> 0 | K41: =K34*K32 -> 0 | ... AH41: =AH34*AH32 -> 4389.7842
A43: 4 Biochar at village processing centres | B43: Horizon | C43: =in_G02a -> 20
A44: Active (1 = within horizon) | D44: =IF(D$3<=in_G02a,1,0) -> 1 | E44: =IF(E$3<=in_G02a,1,0) -> 1 | F44: =IF(F$3<=in_G02a,1,0) -> 1 | G44: =IF(G$3<=in_G02a,1,0) -> 1 | H44: =IF(H$3<=in_G02a,1,0) -> 1 | I44: =IF(I$3<=in_G02a,1,0) -> 1 | J44: =IF(J$3<=in_G02a,1,0) -> 1 | K44: =IF(K$3<=in_G02a,1,0) -> 1 | ... AH44: =IF(AH$3<=in_G02a,1,0) -> 0
A45: Capex | C45: =SUMPRODUCT(D45:AH45,D$5:AH$5) -> 25000 | D45: =IF(D$3=0,in_B03*(1-in_P02),0) -> 25000 | E45: =IF(E$3=0,in_B03*(1-in_P02),0) -> 0 | F45: =IF(F$3=0,in_B03*(1-in_P02),0) -> 0 | G45: =IF(G$3=0,in_B03*(1-in_P02),0) -> 0 | H45: =IF(H$3=0,in_B03*(1-in_P02),0) -> 0 | I45: =IF(I$3=0,in_B03*(1-in_P02),0) -> 0 | J45: =IF(J$3=0,in_B03*(1-in_P02),0) -> 0 | K45: =IF(K$3=0,in_B03*(1-in_P02),0) -> 0 | ... AH45: =IF(AH$3=0,in_B03*(1-in_P02),0) -> 0
A46: Supply benefit | D46: =0 -> 0 | E46: =0 -> 0 | F46: =0 -> 0 | G46: =0 -> 0 | H46: =0 -> 0 | I46: =0 -> 0 | J46: =0 -> 0 | K46: =0 -> 0 | ... AH46: =0 -> 0
A47: Other benefit | D47: =IF(D$3=0,0,in_G08*c_char*in_B07*in_B06*(1-in_B08)) -> 0 | E47: =IF(E$3=0,0,in_G08*c_char*in_B07*in_B06*(1-in_B08)) -> 0 | F47: =IF(F$3=0,0,in_G08*c_char*in_B07*in_B06*(1-in_B08)) -> 0 | G47: =IF(G$3=0,0,in_G08*c_char*in_B07*in_B06*(1-in_B08)) -> 0 | H47: =IF(H$3=0,0,in_G08*c_char*in_B07*in_B06*(1-in_B08)) -> 0 | I47: =IF(I$3=0,0,in_G08*c_char*in_B07*in_B06*(1-in_B08)) -> 0 | J47: =IF(J$3=0,0,in_G08*c_char*in_B07*in_B06*(1-in_B08)) -> 0 | K47: =IF(K$3=0,0,in_G08*c_char*in_B07*in_B06*(1-in_B08)) -> 0 | ... AH47: =IF(AH$3=0,0,in_G08*c_char*in_B07*in_B06*(1-in_B08)) -> 0
A48: Opex | D48: =IF(D$3=0,0,c_char*in_B04+in_B01*in_B05) -> 0 | E48: =IF(E$3=0,0,c_char*in_B04+in_B01*in_B05) -> 14400 | F48: =IF(F$3=0,0,c_char*in_B04+in_B01*in_B05) -> 14400 | G48: =IF(G$3=0,0,c_char*in_B04+in_B01*in_B05) -> 14400 | H48: =IF(H$3=0,0,c_char*in_B04+in_B01*in_B05) -> 14400 | I48: =IF(I$3=0,0,c_char*in_B04+in_B01*in_B05) -> 14400 | J48: =IF(J$3=0,0,c_char*in_B04+in_B01*in_B05) -> 14400 | K48: =IF(K$3=0,0,c_char*in_B04+in_B01*in_B05) -> 14400 | ... AH48: =IF(AH$3=0,0,c_char*in_B04+in_B01*in_B05) -> 14400
A49: Operating flow | D49: =D46+D47-D48 -> 0 | E49: =E46+E47-E48 -> -14400 | F49: =F46+F47-F48 -> -14400 | G49: =G46+G47-G48 -> -14400 | H49: =H46+H47-H48 -> -14400 | I49: =I46+I47-I48 -> -14400 | J49: =J46+J47-J48 -> -14400 | K49: =K46+K47-K48 -> -14400 | ... AH49: =AH46+AH47-AH48 -> -14400
A50: Tax | D50: =D$4*MAX(0,D49) -> 0 | E50: =E$4*MAX(0,E49) -> 0 | F50: =F$4*MAX(0,F49) -> 0 | G50: =G$4*MAX(0,G49) -> 0 | H50: =H$4*MAX(0,H49) -> 0 | I50: =I$4*MAX(0,I49) -> 0 | J50: =J$4*MAX(0,J49) -> 0 | K50: =K$4*MAX(0,K49) -> 0 | ... AH50: =AH$4*MAX(0,AH49) -> 0
A51: Free cash flow | C51: =SUMPRODUCT(D51:AH51,D$5:AH$5) -> -126156.42 | D51: =(D49-D45-D50)*D44 -> -25000 | E51: =(E49-E45-E50)*E44 -> -14400 | F51: =(F49-F45-F50)*F44 -> -14400 | G51: =(G49-G45-G50)*G44 -> -14400 | H51: =(H49-H45-H50)*H44 -> -14400 | I51: =(I49-I45-I50)*I44 -> -14400 | J51: =(J49-J45-J50)*J44 -> -14400 | K51: =(K49-K45-K50)*K44 -> -14400 | ... AH51: =(AH49-AH45-AH50)*AH44 -> 0
A52: Supplier income (supplier account) | C52: =SUMPRODUCT(D52:AH52,D$5:AH$5) -> 0 | D52: =0 -> 0 | E52: =0 -> 0 | F52: =0 -> 0 | G52: =0 -> 0 | H52: =0 -> 0 | I52: =0 -> 0 | J52: =0 -> 0 | K52: =0 -> 0 | ... AH52: =0 -> 0
A53: PV of supply benefit (pre-tax) | C53: =SUMPRODUCT(D53:AH53,D$5:AH$5) -> 0 | D53: =D46*D44 -> 0 | E53: =E46*E44 -> 0 | F53: =F46*F44 -> 0 | G53: =G46*G44 -> 0 | H53: =H46*H44 -> 0 | I53: =I46*I44 -> 0 | J53: =J46*J44 -> 0 | K53: =K46*K44 -> 0 | ... AH53: =AH46*AH44 -> 0
A55: 5 Processing stoves for butter suppliers | B55: Horizon | C55: =in_G02a -> 20
A56: Active (1 = within horizon) | D56: =IF(D$3<=in_G02a,1,0) -> 1 | E56: =IF(E$3<=in_G02a,1,0) -> 1 | F56: =IF(F$3<=in_G02a,1,0) -> 1 | G56: =IF(G$3<=in_G02a,1,0) -> 1 | H56: =IF(H$3<=in_G02a,1,0) -> 1 | I56: =IF(I$3<=in_G02a,1,0) -> 1 | J56: =IF(J$3<=in_G02a,1,0) -> 1 | K56: =IF(K$3<=in_G02a,1,0) -> 1 | ... AH56: =IF(AH$3<=in_G02a,1,0) -> 0
A57: Capex | C57: =SUMPRODUCT(D57:AH57,D$5:AH$5) -> 59917.171 | D57: =IF(AND(MOD(D$3,in_S03)=0,D$3<in_G02a),in_S05*in_S01*(1-in_P02),0) -> 30000 | E57: =IF(AND(MOD(E$3,in_S03)=0,E$3<in_G02a),in_S05*in_S01*(1-in_P02),0) -> 0 | F57: =IF(AND(MOD(F$3,in_S03)=0,F$3<in_G02a),in_S05*in_S01*(1-in_P02),0) -> 0 | G57: =IF(AND(MOD(G$3,in_S03)=0,G$3<in_G02a),in_S05*in_S01*(1-in_P02),0) -> 0 | H57: =IF(AND(MOD(H$3,in_S03)=0,H$3<in_G02a),in_S05*in_S01*(1-in_P02),0) -> 0 | I57: =IF(AND(MOD(I$3,in_S03)=0,I$3<in_G02a),in_S05*in_S01*(1-in_P02),0) -> 30000 | J57: =IF(AND(MOD(J$3,in_S03)=0,J$3<in_G02a),in_S05*in_S01*(1-in_P02),0) -> 0 | K57: =IF(AND(MOD(K$3,in_S03)=0,K$3<in_G02a),in_S05*in_S01*(1-in_P02),0) -> 0 | ... AH57: =IF(AND(MOD(AH$3,in_S03)=0,AH$3<in_G02a),in_S05*in_S01*(1-in_P02),0) -> 0
A58: Supply benefit | D58: =Supply!D36 -> 0 | E58: =Supply!E36 -> 1833.4226 | F58: =Supply!F36 -> 1833.4226 | G58: =Supply!G36 -> 1833.4226 | H58: =Supply!H36 -> 1833.4226 | I58: =Supply!I36 -> 1833.4226 | J58: =Supply!J36 -> 1833.4226 | K58: =Supply!K36 -> 1833.4226 | ... AH58: =Supply!AH36 -> 15280.119
A59: Other benefit | D59: =IF(D$3=0,0,in_G08*in_S05*in_S10*in_S08*(1-in_B08)) -> 0 | E59: =IF(E$3=0,0,in_G08*in_S05*in_S10*in_S08*(1-in_B08)) -> 0 | F59: =IF(F$3=0,0,in_G08*in_S05*in_S10*in_S08*(1-in_B08)) -> 0 | G59: =IF(G$3=0,0,in_G08*in_S05*in_S10*in_S08*(1-in_B08)) -> 0 | H59: =IF(H$3=0,0,in_G08*in_S05*in_S10*in_S08*(1-in_B08)) -> 0 | I59: =IF(I$3=0,0,in_G08*in_S05*in_S10*in_S08*(1-in_B08)) -> 0 | J59: =IF(J$3=0,0,in_G08*in_S05*in_S10*in_S08*(1-in_B08)) -> 0 | K59: =IF(K$3=0,0,in_G08*in_S05*in_S10*in_S08*(1-in_B08)) -> 0 | ... AH59: =IF(AH$3=0,0,in_G08*in_S05*in_S10*in_S08*(1-in_B08)) -> 0
A60: Opex | D60: =0 -> 0 | E60: =0 -> 0 | F60: =0 -> 0 | G60: =0 -> 0 | H60: =0 -> 0 | I60: =0 -> 0 | J60: =0 -> 0 | K60: =0 -> 0 | ... AH60: =0 -> 0
A61: Operating flow | D61: =D58+D59-D60 -> 0 | E61: =E58+E59-E60 -> 1833.4226 | F61: =F58+F59-F60 -> 1833.4226 | G61: =G58+G59-G60 -> 1833.4226 | H61: =H58+H59-H60 -> 1833.4226 | I61: =I58+I59-I60 -> 1833.4226 | J61: =J58+J59-J60 -> 1833.4226 | K61: =K58+K59-K60 -> 1833.4226 | ... AH61: =AH58+AH59-AH60 -> 15280.119
A62: Tax | D62: =D$4*MAX(0,D61) -> 0 | E62: =E$4*MAX(0,E61) -> 0 | F62: =F$4*MAX(0,F61) -> 0 | G62: =G$4*MAX(0,G61) -> 0 | H62: =H$4*MAX(0,H61) -> 0 | I62: =I$4*MAX(0,I61) -> 0 | J62: =J$4*MAX(0,J61) -> 0 | K62: =K$4*MAX(0,K61) -> 0 | ... AH62: =AH$4*MAX(0,AH61) -> 2521.2196
A63: Free cash flow | C63: =SUMPRODUCT(D63:AH63,D$5:AH$5) -> -43059.931 | D63: =(D61-D57-D62)*D56 -> -30000 | E63: =(E61-E57-E62)*E56 -> 1833.4226 | F63: =(F61-F57-F62)*F56 -> 1833.4226 | G63: =(G61-G57-G62)*G56 -> 1833.4226 | H63: =(H61-H57-H62)*H56 -> 1833.4226 | I63: =(I61-I57-I62)*I56 -> -28166.577 | J63: =(J61-J57-J62)*J56 -> 1833.4226 | K63: =(K61-K57-K62)*K56 -> 1833.4226 | ... AH63: =(AH61-AH57-AH62)*AH56 -> 0
A64: Supplier income (supplier account) | C64: =SUMPRODUCT(D64:AH64,D$5:AH$5) -> 43272.47 | D64: =(IF(D$3=0,0,MIN(in_C01,in_S05*in_S06)*in_S09*in_S02*in_S07))*D56 -> 0 | E64: =(IF(E$3=0,0,MIN(in_C01,in_S05*in_S06)*in_S09*in_S02*in_S07))*E56 -> 6160 | F64: =(IF(F$3=0,0,MIN(in_C01,in_S05*in_S06)*in_S09*in_S02*in_S07))*F56 -> 6160 | G64: =(IF(G$3=0,0,MIN(in_C01,in_S05*in_S06)*in_S09*in_S02*in_S07))*G56 -> 6160 | H64: =(IF(H$3=0,0,MIN(in_C01,in_S05*in_S06)*in_S09*in_S02*in_S07))*H56 -> 6160 | I64: =(IF(I$3=0,0,MIN(in_C01,in_S05*in_S06)*in_S09*in_S02*in_S07))*I56 -> 6160 | J64: =(IF(J$3=0,0,MIN(in_C01,in_S05*in_S06)*in_S09*in_S02*in_S07))*J56 -> 6160 | K64: =(IF(K$3=0,0,MIN(in_C01,in_S05*in_S06)*in_S09*in_S02*in_S07))*K56 -> 6160 | ... AH64: =(IF(AH$3=0,0,MIN(in_C01,in_S05*in_S06)*in_S09*in_S02*in_S07))*AH56 -> 0
A65: PV of supply benefit (pre-tax) | C65: =SUMPRODUCT(D65:AH65,D$5:AH$5) -> 18222.421 | D65: =D58*D56 -> 0 | E65: =E58*E56 -> 1833.4226 | F65: =F58*F56 -> 1833.4226 | G65: =G58*G56 -> 1833.4226 | H65: =H58*H56 -> 1833.4226 | I65: =I58*I56 -> 1833.4226 | J65: =J58*J56 -> 1833.4226 | K65: =K58*K56 -> 1833.4226 | ... AH65: =AH58*AH56 -> 0
A67: 6 Flood drainage, detention, plinths | B67: Horizon | C67: =in_G02a -> 20
A68: Active (1 = within horizon) | D68: =IF(D$3<=in_G02a,1,0) -> 1 | E68: =IF(E$3<=in_G02a,1,0) -> 1 | F68: =IF(F$3<=in_G02a,1,0) -> 1 | G68: =IF(G$3<=in_G02a,1,0) -> 1 | H68: =IF(H$3<=in_G02a,1,0) -> 1 | I68: =IF(I$3<=in_G02a,1,0) -> 1 | J68: =IF(J$3<=in_G02a,1,0) -> 1 | K68: =IF(K$3<=in_G02a,1,0) -> 1 | ... AH68: =IF(AH$3<=in_G02a,1,0) -> 0
A69: Capex | C69: =SUMPRODUCT(D69:AH69,D$5:AH$5) -> 117325 | D69: =IF(D$3=0,c_flood_cap,0) -> 117325 | E69: =IF(E$3=0,c_flood_cap,0) -> 0 | F69: =IF(F$3=0,c_flood_cap,0) -> 0 | G69: =IF(G$3=0,c_flood_cap,0) -> 0 | H69: =IF(H$3=0,c_flood_cap,0) -> 0 | I69: =IF(I$3=0,c_flood_cap,0) -> 0 | J69: =IF(J$3=0,c_flood_cap,0) -> 0 | K69: =IF(K$3=0,c_flood_cap,0) -> 0 | ... AH69: =IF(AH$3=0,c_flood_cap,0) -> 0
A70: Supply benefit | D70: =0 -> 0 | E70: =0 -> 0 | F70: =0 -> 0 | G70: =0 -> 0 | H70: =0 -> 0 | I70: =0 -> 0 | J70: =0 -> 0 | K70: =0 -> 0 | ... AH70: =0 -> 0
A71: Other benefit | D71: =IF(D$3=0,0,in_H05*((c_floss0-in_N05*c_rec0)-(c_floss1-in_N05*c_rec1))) -> 0 | E71: =IF(E$3=0,0,in_H05*((c_floss0-in_N05*c_rec0)-(c_floss1-in_N05*c_rec1))) -> 9863.2727 | F71: =IF(F$3=0,0,in_H05*((c_floss0-in_N05*c_rec0)-(c_floss1-in_N05*c_rec1))) -> 9863.2727 | G71: =IF(G$3=0,0,in_H05*((c_floss0-in_N05*c_rec0)-(c_floss1-in_N05*c_rec1))) -> 9863.2727 | H71: =IF(H$3=0,0,in_H05*((c_floss0-in_N05*c_rec0)-(c_floss1-in_N05*c_rec1))) -> 9863.2727 | I71: =IF(I$3=0,0,in_H05*((c_floss0-in_N05*c_rec0)-(c_floss1-in_N05*c_rec1))) -> 9863.2727 | J71: =IF(J$3=0,0,in_H05*((c_floss0-in_N05*c_rec0)-(c_floss1-in_N05*c_rec1))) -> 9863.2727 | K71: =IF(K$3=0,0,in_H05*((c_floss0-in_N05*c_rec0)-(c_floss1-in_N05*c_rec1))) -> 9863.2727 | ... AH71: =IF(AH$3=0,0,in_H05*((c_floss0-in_N05*c_rec0)-(c_floss1-in_N05*c_rec1))) -> 9863.2727
A72: Opex | D72: =IF(D$3=0,0,in_D08*c_flood_cap) -> 0 | E72: =IF(E$3=0,0,in_D08*c_flood_cap) -> 2346.5 | F72: =IF(F$3=0,0,in_D08*c_flood_cap) -> 2346.5 | G72: =IF(G$3=0,0,in_D08*c_flood_cap) -> 2346.5 | H72: =IF(H$3=0,0,in_D08*c_flood_cap) -> 2346.5 | I72: =IF(I$3=0,0,in_D08*c_flood_cap) -> 2346.5 | J72: =IF(J$3=0,0,in_D08*c_flood_cap) -> 2346.5 | K72: =IF(K$3=0,0,in_D08*c_flood_cap) -> 2346.5 | ... AH72: =IF(AH$3=0,0,in_D08*c_flood_cap) -> 2346.5
A73: Operating flow | D73: =D70+D71-D72 -> 0 | E73: =E70+E71-E72 -> 7516.7727 | F73: =F70+F71-F72 -> 7516.7727 | G73: =G70+G71-G72 -> 7516.7727 | H73: =H70+H71-H72 -> 7516.7727 | I73: =I70+I71-I72 -> 7516.7727 | J73: =J70+J71-J72 -> 7516.7727 | K73: =K70+K71-K72 -> 7516.7727 | ... AH73: =AH70+AH71-AH72 -> 7516.7727
A74: Tax | D74: =D$4*MAX(0,D73) -> 0 | E74: =E$4*MAX(0,E73) -> 0 | F74: =F$4*MAX(0,F73) -> 0 | G74: =G$4*MAX(0,G73) -> 0 | H74: =H$4*MAX(0,H73) -> 0 | I74: =I$4*MAX(0,I73) -> 0 | J74: =J$4*MAX(0,J73) -> 0 | K74: =K$4*MAX(0,K73) -> 0 | ... AH74: =AH$4*MAX(0,AH73) -> 1240.2675
A75: Free cash flow | C75: =SUMPRODUCT(D75:AH75,D$5:AH$5) -> -66504.117 | D75: =(D73-D69-D74)*D68 -> -117325 | E75: =(E73-E69-E74)*E68 -> 7516.7727 | F75: =(F73-F69-F74)*F68 -> 7516.7727 | G75: =(G73-G69-G74)*G68 -> 7516.7727 | H75: =(H73-H69-H74)*H68 -> 7516.7727 | I75: =(I73-I69-I74)*I68 -> 7516.7727 | J75: =(J73-J69-J74)*J68 -> 7516.7727 | K75: =(K73-K69-K74)*K68 -> 7516.7727 | ... AH75: =(AH73-AH69-AH74)*AH68 -> 0
A76: Supplier income (supplier account) | C76: =SUMPRODUCT(D76:AH76,D$5:AH$5) -> 0 | D76: =0 -> 0 | E76: =0 -> 0 | F76: =0 -> 0 | G76: =0 -> 0 | H76: =0 -> 0 | I76: =0 -> 0 | J76: =0 -> 0 | K76: =0 -> 0 | ... AH76: =0 -> 0
A77: PV of supply benefit (pre-tax) | C77: =SUMPRODUCT(D77:AH77,D$5:AH$5) -> 0 | D77: =D70*D68 -> 0 | E77: =E70*E68 -> 0 | F77: =F70*F68 -> 0 | G77: =G70*G68 -> 0 | H77: =H70*H68 -> 0 | I77: =I70*I68 -> 0 | J77: =J70*J68 -> 0 | K77: =K70*K68 -> 0 | ... AH77: =AH70*AH68 -> 0
A79: 7a Solar PV, grid-tied | B79: Horizon | C79: =in_G02a -> 20
A80: Active (1 = within horizon) | D80: =IF(D$3<=in_G02a,1,0) -> 1 | E80: =IF(E$3<=in_G02a,1,0) -> 1 | F80: =IF(F$3<=in_G02a,1,0) -> 1 | G80: =IF(G$3<=in_G02a,1,0) -> 1 | H80: =IF(H$3<=in_G02a,1,0) -> 1 | I80: =IF(I$3<=in_G02a,1,0) -> 1 | J80: =IF(J$3<=in_G02a,1,0) -> 1 | K80: =IF(K$3<=in_G02a,1,0) -> 1 | ... AH80: =IF(AH$3<=in_G02a,1,0) -> 0
A81: Capex | C81: =SUMPRODUCT(D81:AH81,D$5:AH$5) -> 102768.47 | D81: =IF(D$3=0,c_pv_cap,0)+IF(D$3=in_E26,in_E12*c_pv_cap,0) -> 100000 | E81: =IF(E$3=0,c_pv_cap,0)+IF(E$3=in_E26,in_E12*c_pv_cap,0) -> 0 | F81: =IF(F$3=0,c_pv_cap,0)+IF(F$3=in_E26,in_E12*c_pv_cap,0) -> 0 | G81: =IF(G$3=0,c_pv_cap,0)+IF(G$3=in_E26,in_E12*c_pv_cap,0) -> 0 | H81: =IF(H$3=0,c_pv_cap,0)+IF(H$3=in_E26,in_E12*c_pv_cap,0) -> 0 | I81: =IF(I$3=0,c_pv_cap,0)+IF(I$3=in_E26,in_E12*c_pv_cap,0) -> 0 | J81: =IF(J$3=0,c_pv_cap,0)+IF(J$3=in_E26,in_E12*c_pv_cap,0) -> 0 | K81: =IF(K$3=0,c_pv_cap,0)+IF(K$3=in_E26,in_E12*c_pv_cap,0) -> 0 | ... AH81: =IF(AH$3=0,c_pv_cap,0)+IF(AH$3=in_E26,in_E12*c_pv_cap,0) -> 0
A82: Supply benefit | D82: =0 -> 0 | E82: =0 -> 0 | F82: =0 -> 0 | G82: =0 -> 0 | H82: =0 -> 0 | I82: =0 -> 0 | J82: =0 -> 0 | K82: =0 -> 0 | ... AH82: =0 -> 0
A83: Other benefit | D83: =IF(D$3=0,0,MIN(in_C08*1000,in_E09*in_E02*(1-in_E23)^(D$3-1))*in_E03) -> 0 | E83: =IF(E$3=0,0,MIN(in_C08*1000,in_E09*in_E02*(1-in_E23)^(E$3-1))*in_E03) -> 28120 | F83: =IF(F$3=0,0,MIN(in_C08*1000,in_E09*in_E02*(1-in_E23)^(F$3-1))*in_E03) -> 27979.4 | G83: =IF(G$3=0,0,MIN(in_C08*1000,in_E09*in_E02*(1-in_E23)^(G$3-1))*in_E03) -> 27839.503 | H83: =IF(H$3=0,0,MIN(in_C08*1000,in_E09*in_E02*(1-in_E23)^(H$3-1))*in_E03) -> 27700.305 | I83: =IF(I$3=0,0,MIN(in_C08*1000,in_E09*in_E02*(1-in_E23)^(I$3-1))*in_E03) -> 27561.804 | J83: =IF(J$3=0,0,MIN(in_C08*1000,in_E09*in_E02*(1-in_E23)^(J$3-1))*in_E03) -> 27423.995 | K83: =IF(K$3=0,0,MIN(in_C08*1000,in_E09*in_E02*(1-in_E23)^(K$3-1))*in_E03) -> 27286.875 | ... AH83: =IF(AH$3=0,0,MIN(in_C08*1000,in_E09*in_E02*(1-in_E23)^(AH$3-1))*in_E03) -> 24315.581
A84: Opex | D84: =IF(D$3=0,0,in_E22*c_pv_cap) -> 0 | E84: =IF(E$3=0,0,in_E22*c_pv_cap) -> 1500 | F84: =IF(F$3=0,0,in_E22*c_pv_cap) -> 1500 | G84: =IF(G$3=0,0,in_E22*c_pv_cap) -> 1500 | H84: =IF(H$3=0,0,in_E22*c_pv_cap) -> 1500 | I84: =IF(I$3=0,0,in_E22*c_pv_cap) -> 1500 | J84: =IF(J$3=0,0,in_E22*c_pv_cap) -> 1500 | K84: =IF(K$3=0,0,in_E22*c_pv_cap) -> 1500 | ... AH84: =IF(AH$3=0,0,in_E22*c_pv_cap) -> 1500
A85: Operating flow | D85: =D82+D83-D84 -> 0 | E85: =E82+E83-E84 -> 26620 | F85: =F82+F83-F84 -> 26479.4 | G85: =G82+G83-G84 -> 26339.503 | H85: =H82+H83-H84 -> 26200.305 | I85: =I82+I83-I84 -> 26061.804 | J85: =J82+J83-J84 -> 25923.995 | K85: =K82+K83-K84 -> 25786.875 | ... AH85: =AH82+AH83-AH84 -> 22815.581
A86: Tax | D86: =D$4*MAX(0,D85) -> 0 | E86: =E$4*MAX(0,E85) -> 0 | F86: =F$4*MAX(0,F85) -> 0 | G86: =G$4*MAX(0,G85) -> 0 | H86: =H$4*MAX(0,H85) -> 0 | I86: =I$4*MAX(0,I85) -> 0 | J86: =J$4*MAX(0,J85) -> 0 | K86: =K$4*MAX(0,K85) -> 0 | ... AH86: =AH$4*MAX(0,AH85) -> 3764.5709
A87: Free cash flow | C87: =SUMPRODUCT(D87:AH87,D$5:AH$5) -> 72102.621 | D87: =(D85-D81-D86)*D80 -> -100000 | E87: =(E85-E81-E86)*E80 -> 26620 | F87: =(F85-F81-F86)*F80 -> 26479.4 | G87: =(G85-G81-G86)*G80 -> 26339.503 | H87: =(H85-H81-H86)*H80 -> 26200.305 | I87: =(I85-I81-I86)*I80 -> 26061.804 | J87: =(J85-J81-J86)*J80 -> 25923.995 | K87: =(K85-K81-K86)*K80 -> 25786.875 | ... AH87: =(AH85-AH81-AH86)*AH80 -> 0
A88: Supplier income (supplier account) | C88: =SUMPRODUCT(D88:AH88,D$5:AH$5) -> 0 | D88: =0 -> 0 | E88: =0 -> 0 | F88: =0 -> 0 | G88: =0 -> 0 | H88: =0 -> 0 | I88: =0 -> 0 | J88: =0 -> 0 | K88: =0 -> 0 | ... AH88: =0 -> 0
A89: PV of supply benefit (pre-tax) | C89: =SUMPRODUCT(D89:AH89,D$5:AH$5) -> 0 | D89: =D82*D80 -> 0 | E89: =E82*E80 -> 0 | F89: =F82*F80 -> 0 | G89: =G82*G80 -> 0 | H89: =H82*H80 -> 0 | I89: =I82*I80 -> 0 | J89: =J82*J80 -> 0 | K89: =K82*K80 -> 0 | ... AH89: =AH82*AH80 -> 0
A91: 7b Battery + islanding (critical loads) | B91: Horizon | C91: =in_G02a -> 20
A92: Active (1 = within horizon) | D92: =IF(D$3<=in_G02a,1,0) -> 1 | E92: =IF(E$3<=in_G02a,1,0) -> 1 | F92: =IF(F$3<=in_G02a,1,0) -> 1 | G92: =IF(G$3<=in_G02a,1,0) -> 1 | H92: =IF(H$3<=in_G02a,1,0) -> 1 | I92: =IF(I$3<=in_G02a,1,0) -> 1 | J92: =IF(J$3<=in_G02a,1,0) -> 1 | K92: =IF(K$3<=in_G02a,1,0) -> 1 | ... AH92: =IF(AH$3<=in_G02a,1,0) -> 0
A93: Capex | C93: =SUMPRODUCT(D93:AH93,D$5:AH$5) -> 95804.907 | D93: =IF(D$3=0,c_bat_cap,0)+IF(D$3=in_E27,in_E15*c_bat_kwh*in_E05,0) -> 82916.667 | E93: =IF(E$3=0,c_bat_cap,0)+IF(E$3=in_E27,in_E15*c_bat_kwh*in_E05,0) -> 0 | F93: =IF(F$3=0,c_bat_cap,0)+IF(F$3=in_E27,in_E15*c_bat_kwh*in_E05,0) -> 0 | G93: =IF(G$3=0,c_bat_cap,0)+IF(G$3=in_E27,in_E15*c_bat_kwh*in_E05,0) -> 0 | H93: =IF(H$3=0,c_bat_cap,0)+IF(H$3=in_E27,in_E15*c_bat_kwh*in_E05,0) -> 0 | I93: =IF(I$3=0,c_bat_cap,0)+IF(I$3=in_E27,in_E15*c_bat_kwh*in_E05,0) -> 0 | J93: =IF(J$3=0,c_bat_cap,0)+IF(J$3=in_E27,in_E15*c_bat_kwh*in_E05,0) -> 0 | K93: =IF(K$3=0,c_bat_cap,0)+IF(K$3=in_E27,in_E15*c_bat_kwh*in_E05,0) -> 0 | ... AH93: =IF(AH$3=0,c_bat_cap,0)+IF(AH$3=in_E27,in_E15*c_bat_kwh*in_E05,0) -> 0
A94: Supply benefit | D94: =0 -> 0 | E94: =0 -> 0 | F94: =0 -> 0 | G94: =0 -> 0 | H94: =0 -> 0 | I94: =0 -> 0 | J94: =0 -> 0 | K94: =0 -> 0 | ... AH94: =0 -> 0
A95: Other benefit | D95: =IF(D$3=0,0,c_bat_avoid) -> 0 | E95: =IF(E$3=0,0,c_bat_avoid) -> 18319.233 | F95: =IF(F$3=0,0,c_bat_avoid) -> 18319.233 | G95: =IF(G$3=0,0,c_bat_avoid) -> 18319.233 | H95: =IF(H$3=0,0,c_bat_avoid) -> 18319.233 | I95: =IF(I$3=0,0,c_bat_avoid) -> 18319.233 | J95: =IF(J$3=0,0,c_bat_avoid) -> 18319.233 | K95: =IF(K$3=0,0,c_bat_avoid) -> 18319.233 | ... AH95: =IF(AH$3=0,0,c_bat_avoid) -> 18319.233
A96: Opex | D96: =IF(D$3=0,0,in_E24*c_bat_cap) -> 0 | E96: =IF(E$3=0,0,in_E24*c_bat_cap) -> 829.16667 | F96: =IF(F$3=0,0,in_E24*c_bat_cap) -> 829.16667 | G96: =IF(G$3=0,0,in_E24*c_bat_cap) -> 829.16667 | H96: =IF(H$3=0,0,in_E24*c_bat_cap) -> 829.16667 | I96: =IF(I$3=0,0,in_E24*c_bat_cap) -> 829.16667 | J96: =IF(J$3=0,0,in_E24*c_bat_cap) -> 829.16667 | K96: =IF(K$3=0,0,in_E24*c_bat_cap) -> 829.16667 | ... AH96: =IF(AH$3=0,0,in_E24*c_bat_cap) -> 829.16667
A97: Operating flow | D97: =D94+D95-D96 -> 0 | E97: =E94+E95-E96 -> 17490.066 | F97: =F94+F95-F96 -> 17490.066 | G97: =G94+G95-G96 -> 17490.066 | H97: =H94+H95-H96 -> 17490.066 | I97: =I94+I95-I96 -> 17490.066 | J97: =J94+J95-J96 -> 17490.066 | K97: =K94+K95-K96 -> 17490.066 | ... AH97: =AH94+AH95-AH96 -> 17490.066
A98: Tax | D98: =D$4*MAX(0,D97) -> 0 | E98: =E$4*MAX(0,E97) -> 0 | F98: =F$4*MAX(0,F97) -> 0 | G98: =G$4*MAX(0,G97) -> 0 | H98: =H$4*MAX(0,H97) -> 0 | I98: =I$4*MAX(0,I97) -> 0 | J98: =J$4*MAX(0,J97) -> 0 | K98: =K$4*MAX(0,K97) -> 0 | ... AH98: =AH$4*MAX(0,AH97) -> 2885.861
A99: Free cash flow | C99: =SUMPRODUCT(D99:AH99,D$5:AH$5) -> 22445.393 | D99: =(D97-D93-D98)*D92 -> -82916.667 | E99: =(E97-E93-E98)*E92 -> 17490.066 | F99: =(F97-F93-F98)*F92 -> 17490.066 | G99: =(G97-G93-G98)*G92 -> 17490.066 | H99: =(H97-H93-H98)*H92 -> 17490.066 | I99: =(I97-I93-I98)*I92 -> 17490.066 | J99: =(J97-J93-J98)*J92 -> 17490.066 | K99: =(K97-K93-K98)*K92 -> 17490.066 | ... AH99: =(AH97-AH93-AH98)*AH92 -> 0
A100: Supplier income (supplier account) | C100: =SUMPRODUCT(D100:AH100,D$5:AH$5) -> 0 | D100: =0 -> 0 | E100: =0 -> 0 | F100: =0 -> 0 | G100: =0 -> 0 | H100: =0 -> 0 | I100: =0 -> 0 | J100: =0 -> 0 | K100: =0 -> 0 | ... AH100: =0 -> 0
A101: PV of supply benefit (pre-tax) | C101: =SUMPRODUCT(D101:AH101,D$5:AH$5) -> 0 | D101: =D94*D92 -> 0 | E101: =E94*E92 -> 0 | F101: =F94*F92 -> 0 | G101: =G94*G92 -> 0 | H101: =H94*H92 -> 0 | I101: =I94*I92 -> 0 | J101: =J94*J92 -> 0 | K101: =K94*K92 -> 0 | ... AH101: =AH94*AH92 -> 0
A103: 7c Solar PPA (no capex) | B103: Horizon | C103: =in_G02a -> 20
A104: Active (1 = within horizon) | D104: =IF(D$3<=in_G02a,1,0) -> 1 | E104: =IF(E$3<=in_G02a,1,0) -> 1 | F104: =IF(F$3<=in_G02a,1,0) -> 1 | G104: =IF(G$3<=in_G02a,1,0) -> 1 | H104: =IF(H$3<=in_G02a,1,0) -> 1 | I104: =IF(I$3<=in_G02a,1,0) -> 1 | J104: =IF(J$3<=in_G02a,1,0) -> 1 | K104: =IF(K$3<=in_G02a,1,0) -> 1 | ... AH104: =IF(AH$3<=in_G02a,1,0) -> 0
A105: Capex | C105: =SUMPRODUCT(D105:AH105,D$5:AH$5) -> 0 | D105: =0 -> 0 | E105: =0 -> 0 | F105: =0 -> 0 | G105: =0 -> 0 | H105: =0 -> 0 | I105: =0 -> 0 | J105: =0 -> 0 | K105: =0 -> 0 | ... AH105: =0 -> 0
A106: Supply benefit | D106: =0 -> 0 | E106: =0 -> 0 | F106: =0 -> 0 | G106: =0 -> 0 | H106: =0 -> 0 | I106: =0 -> 0 | J106: =0 -> 0 | K106: =0 -> 0 | ... AH106: =0 -> 0
A107: Other benefit | D107: =IF(D$3=0,0,MIN(in_C08*1000,in_E09*in_E02*(1-in_E23)^(D$3-1))*in_E03*in_E08) -> 0 | E107: =IF(E$3=0,0,MIN(in_C08*1000,in_E09*in_E02*(1-in_E23)^(E$3-1))*in_E03*in_E08) -> 5624 | F107: =IF(F$3=0,0,MIN(in_C08*1000,in_E09*in_E02*(1-in_E23)^(F$3-1))*in_E03*in_E08) -> 5595.88 | G107: =IF(G$3=0,0,MIN(in_C08*1000,in_E09*in_E02*(1-in_E23)^(G$3-1))*in_E03*in_E08) -> 5567.9006 | H107: =IF(H$3=0,0,MIN(in_C08*1000,in_E09*in_E02*(1-in_E23)^(H$3-1))*in_E03*in_E08) -> 5540.0611 | I107: =IF(I$3=0,0,MIN(in_C08*1000,in_E09*in_E02*(1-in_E23)^(I$3-1))*in_E03*in_E08) -> 5512.3608 | J107: =IF(J$3=0,0,MIN(in_C08*1000,in_E09*in_E02*(1-in_E23)^(J$3-1))*in_E03*in_E08) -> 5484.799 | K107: =IF(K$3=0,0,MIN(in_C08*1000,in_E09*in_E02*(1-in_E23)^(K$3-1))*in_E03*in_E08) -> 5457.375 | ... AH107: =IF(AH$3=0,0,MIN(in_C08*1000,in_E09*in_E02*(1-in_E23)^(AH$3-1))*in_E03*in_E08) -> 4863.1163
A108: Opex | D108: =0 -> 0 | E108: =0 -> 0 | F108: =0 -> 0 | G108: =0 -> 0 | H108: =0 -> 0 | I108: =0 -> 0 | J108: =0 -> 0 | K108: =0 -> 0 | ... AH108: =0 -> 0
A109: Operating flow | D109: =D106+D107-D108 -> 0 | E109: =E106+E107-E108 -> 5624 | F109: =F106+F107-F108 -> 5595.88 | G109: =G106+G107-G108 -> 5567.9006 | H109: =H106+H107-H108 -> 5540.0611 | I109: =I106+I107-I108 -> 5512.3608 | J109: =J106+J107-J108 -> 5484.799 | K109: =K106+K107-K108 -> 5457.375 | ... AH109: =AH106+AH107-AH108 -> 4863.1163
...

Sheet Portfolio
A1: Portfolio: switch options on (1) or off (0); costs counted once, overlapping benefits combined
A2: Supply effects combine as 1 − Π(1 − r). Interactions: flood works lower insurance recoveries; battery adds nothing if the genset is also on; PPA and owned PV are alternatives. Horizon = G02a for all.
A4: Option | B4: ID | C4: Include (1/0)
A5: 1 Solar irrigation (nurseries + gardens) | B5: 1 | C5: 0 | E5: Portfolio factory NPV | F5: =C30 -> 260114.9
A6: 2 Apiaries | B6: 2 | C6: 1 | E6: Portfolio capex (PV) | F6: =C21 -> 239728.96
A7: 3 Regeneration & agroforestry | B7: 3 | C7: 0 | E7: Portfolio NPV incl. supplier income | F7: =C30+C31 -> 363769.33
A8: 4 Biochar at village processing centres | B8: 4 | C8: 0
A9: 5 Processing stoves for butter suppliers | B9: 5 | C9: 1
A10: 6 Flood drainage, detention, plinths | B10: 6 | C10: 0
A11: 7a Solar PV, grid-tied | B11: 7a | C11: 1
A12: 7b Battery + islanding (critical loads) | B12: 7b | C12: 0
A13: 7c Solar PPA (no capex) | B13: 7c | C13: 0
A14: 7d Diesel genset (comparator) | B14: 7d | C14: 1
A15: 8 Mango toll pilot (substitution hedge) | B15: 8 | C15: 1
A16: 9 Community fire management | B16: 9 | C16: 0
A17: 10 Insurance: property incl. flood + BI | B17: 10 | C17: 1
A19: Year | C19: NPV / total | D19: 0 | E19: 1 | F19: 2 | G19: 3 | H19: 4 | I19: 5 | J19: 6 | K19: 7 | L19: 8 | M19: 9 | N19: 10 | O19: 11 | P19: 12 | Q19: 13 | R19: 14 | S19: 15 | T19: 16 | U19: 17 | V19: 18 | W19: 19 | X19: 20 | Y19: 21 | Z19: 22 | AA19: 23 | AB19: 24 | AC19: 25 | AD19: 26 | AE19: 27 | AF19: 28 | AG19: 29 | AH19: 30
A20: Active | D20: =IF(D$19<=in_G02a,1,0) -> 1 | E20: =IF(E$19<=in_G02a,1,0) -> 1 | F20: =IF(F$19<=in_G02a,1,0) -> 1 | G20: =IF(G$19<=in_G02a,1,0) -> 1 | H20: =IF(H$19<=in_G02a,1,0) -> 1 | I20: =IF(I$19<=in_G02a,1,0) -> 1 | J20: =IF(J$19<=in_G02a,1,0) -> 1 | K20: =IF(K$19<=in_G02a,1,0) -> 1 | ... AH20: =IF(AH$19<=in_G02a,1,0) -> 0
A21: Capex | C21: =SUMPRODUCT(D21:AH21,Engine!D$5:AH$5) -> 239728.96 | D21: =(Portfolio!$C$5*Engine!D9+Portfolio!$C$6*Engine!D21+Portfolio!$C$7*Engine!D33+Portfolio!$C$8*Engine!D45+Portfolio!$C$9*Engine!D57+Portfolio!$C$10*Engine!D69+Portfolio!$C$11*Engine!D81+Portfolio!$C$12*Engine!D93+Portfolio!$C$13*Engine!D105+Portfolio!$C$14*Engine!D117+Portfolio!$C$15*Engine!D129+Portfolio!$C$16*Engine!D141+Portfolio!$C$17*Engine!D153) -> 191192.8 | E21: =(Portfolio!$C$5*Engine!E9+Portfolio!$C$6*Engine!E21+Portfolio!$C$7*Engine!E33+Portfolio!$C$8*Engine!E45+Portfolio!$C$9*Engine!E57+Portfolio!$C$10*Engine!E69+Portfolio!$C$11*Engine!E81+Portfolio!$C$12*Engine!E93+Portfolio!$C$13*Engine!E105+Portfolio!$C$14*Engine!E117+Portfolio!$C$15*Engine!E129+Portfolio!$C$16*Engine!E141+Portfolio!$C$17*Engine!E153) -> 0 | F21: =(Portfolio!$C$5*Engine!F9+Portfolio!$C$6*Engine!F21+Portfolio!$C$7*Engine!F33+Portfolio!$C$8*Engine!F45+Portfolio!$C$9*Engine!F57+Portfolio!$C$10*Engine!F69+Portfolio!$C$11*Engine!F81+Portfolio!$C$12*Engine!F93+Portfolio!$C$13*Engine!F105+Portfolio!$C$14*Engine!F117+Portfolio!$C$15*Engine!F129+Portfolio!$C$16*Engine!F141+Portfolio!$C$17*Engine!F153) -> 0 | G21: =(Portfolio!$C$5*Engine!G9+Portfolio!$C$6*Engine!G21+Portfolio!$C$7*Engine!G33+Portfolio!$C$8*Engine!G45+Portfolio!$C$9*Engine!G57+Portfolio!$C$10*Engine!G69+Portfolio!$C$11*Engine!G81+Portfolio!$C$12*Engine!G93+Portfolio!$C$13*Engine!G105+Portfolio!$C$14*Engine!G117+Portfolio!$C$15*Engine!G129+Portfolio!$C$16*Engine!G141+Portfolio!$C$17*Engine!G153) -> 0 | H21: =(Portfolio!$C$5*Engine!H9+Portfolio!$C$6*Engine!H21+Portfolio!$C$7*Engine!H33+Portfolio!$C$8*Engine!H45+Portfolio!$C$9*Engine!H57+Portfolio!$C$10*Engine!H69+Portfolio!$C$11*Engine!H81+Portfolio!$C$12*Engine!H93+Portfolio!$C$13*Engine!H105+Portfolio!$C$14*Engine!H117+Portfolio!$C$15*Engine!H129+Portfolio!$C$16*Engine!H141+Portfolio!$C$17*Engine!H153) -> 0 | I21: =(Portfolio!$C$5*Engine!I9+Portfolio!$C$6*Engine!I21+Portfolio!$C$7*Engine!I33+Portfolio!$C$8*Engine!I45+Portfolio!$C$9*Engine!I57+Portfolio!$C$10*Engine!I69+Portfolio!$C$11*Engine!I81+Portfolio!$C$12*Engine!I93+Portfolio!$C$13*Engine!I105+Portfolio!$C$14*Engine!I117+Portfolio!$C$15*Engine!I129+Portfolio!$C$16*Engine!I141+Portfolio!$C$17*Engine!I153) -> 30000 | J21: =(Portfolio!$C$5*Engine!J9+Portfolio!$C$6*Engine!J21+Portfolio!$C$7*Engine!J33+Portfolio!$C$8*Engine!J45+Portfolio!$C$9*Engine!J57+Portfolio!$C$10*Engine!J69+Portfolio!$C$11*Engine!J81+Portfolio!$C$12*Engine!J93+Portfolio!$C$13*Engine!J105+Portfolio!$C$14*Engine!J117+Portfolio!$C$15*Engine!J129+Portfolio!$C$16*Engine!J141+Portfolio!$C$17*Engine!J153) -> 0 | K21: =(Portfolio!$C$5*Engine!K9+Portfolio!$C$6*Engine!K21+Portfolio!$C$7*Engine!K33+Portfolio!$C$8*Engine!K45+Portfolio!$C$9*Engine!K57+Portfolio!$C$10*Engine!K69+Portfolio!$C$11*Engine!K81+Portfolio!$C$12*Engine!K93+Portfolio!$C$13*Engine!K105+Portfolio!$C$14*Engine!K117+Portfolio!$C$15*Engine!K129+Portfolio!$C$16*Engine!K141+Portfolio!$C$17*Engine!K153) -> 20000 | ... AH21: =(Portfolio!$C$5*Engine!AH9+Portfolio!$C$6*Engine!AH21+Portfolio!$C$7*Engine!AH33+Portfolio!$C$8*Engine!AH45+Portfolio!$C$9*Engine!AH57+Portfolio!$C$10*Engine!AH69+Portfolio!$C$11*Engine!AH81+Portfolio!$C$12*Engine!AH93+Portfolio!$C$13*Engine!AH105+Portfolio!$C$14*Engine!AH117+Portfolio!$C$15*Engine!AH129+Portfolio!$C$16*Engine!AH141+Portfolio!$C$17*Engine!AH153) -> 0
A22: Supply benefit, combined | C22: =SUMPRODUCT(D22:AH22,Engine!D$5:AH$5) -> 55720.723 | D22: =Supply!D57 -> 0 | E22: =Supply!E57 -> 6004.8129 | F22: =Supply!F57 -> 6004.8129 | G22: =Supply!G57 -> 6004.8129 | H22: =Supply!H57 -> 6004.8129 | I22: =Supply!I57 -> 6004.8129 | J22: =Supply!J57 -> 6004.8129 | K22: =Supply!K57 -> 6004.8129 | ... AH22: =Supply!AH57 -> 18748.314
A23: Other benefit | C23: =SUMPRODUCT(D23:AH23,Engine!D$5:AH$5) -> 665901.72 | D23: =(Portfolio!$C$5*Engine!D11+Portfolio!$C$6*Engine!D23+Portfolio!$C$7*Engine!D35+Portfolio!$C$8*Engine!D47+Portfolio!$C$9*Engine!D59+Portfolio!$C$10*Engine!D71+Portfolio!$C$11*Engine!D83+Portfolio!$C$12*Engine!D95+Portfolio!$C$13*Engine!D107+Portfolio!$C$14*Engine!D119+Portfolio!$C$15*Engine!D131+Portfolio!$C$16*Engine!D143+Portfolio!$C$17*Engine!D155) -> 0 | E23: =(Portfolio!$C$5*Engine!E11+Portfolio!$C$6*Engine!E23+Portfolio!$C$7*Engine!E35+Portfolio!$C$8*Engine!E47+Portfolio!$C$9*Engine!E59+Portfolio!$C$10*Engine!E71+Portfolio!$C$11*Engine!E83+Portfolio!$C$12*Engine!E95+Portfolio!$C$13*Engine!E107+Portfolio!$C$14*Engine!E119+Portfolio!$C$15*Engine!E131+Portfolio!$C$16*Engine!E143+Portfolio!$C$17*Engine!E155) -> 89780.677 | F23: =(Portfolio!$C$5*Engine!F11+Portfolio!$C$6*Engine!F23+Portfolio!$C$7*Engine!F35+Portfolio!$C$8*Engine!F47+Portfolio!$C$9*Engine!F59+Portfolio!$C$10*Engine!F71+Portfolio!$C$11*Engine!F83+Portfolio!$C$12*Engine!F95+Portfolio!$C$13*Engine!F107+Portfolio!$C$14*Engine!F119+Portfolio!$C$15*Engine!F131+Portfolio!$C$16*Engine!F143+Portfolio!$C$17*Engine!F155) -> 89640.077 | G23: =(Portfolio!$C$5*Engine!G11+Portfolio!$C$6*Engine!G23+Portfolio!$C$7*Engine!G35+Portfolio!$C$8*Engine!G47+Portfolio!$C$9*Engine!G59+Portfolio!$C$10*Engine!G71+Portfolio!$C$11*Engine!G83+Portfolio!$C$12*Engine!G95+Portfolio!$C$13*Engine!G107+Portfolio!$C$14*Engine!G119+Portfolio!$C$15*Engine!G131+Portfolio!$C$16*Engine!G143+Portfolio!$C$17*Engine!G155) -> 89500.18 | H23: =(Portfolio!$C$5*Engine!H11+Portfolio!$C$6*Engine!H23+Portfolio!$C$7*Engine!H35+Portfolio!$C$8*Engine!H47+Portfolio!$C$9*Engine!H59+Portfolio!$C$10*Engine!H71+Portfolio!$C$11*Engine!H83+Portfolio!$C$12*Engine!H95+Portfolio!$C$13*Engine!H107+Portfolio!$C$14*Engine!H119+Portfolio!$C$15*Engine!H131+Portfolio!$C$16*Engine!H143+Portfolio!$C$17*Engine!H155) -> 89360.982 | I23: =(Portfolio!$C$5*Engine!I11+Portfolio!$C$6*Engine!I23+Portfolio!$C$7*Engine!I35+Portfolio!$C$8*Engine!I47+Portfolio!$C$9*Engine!I59+Portfolio!$C$10*Engine!I71+Portfolio!$C$11*Engine!I83+Portfolio!$C$12*Engine!I95+Portfolio!$C$13*Engine!I107+Portfolio!$C$14*Engine!I119+Portfolio!$C$15*Engine!I131+Portfolio!$C$16*Engine!I143+Portfolio!$C$17*Engine!I155) -> 89222.481 | J23: =(Portfolio!$C$5*Engine!J11+Portfolio!$C$6*Engine!J23+Portfolio!$C$7*Engine!J35+Portfolio!$C$8*Engine!J47+Portfolio!$C$9*Engine!J59+Portfolio!$C$10*Engine!J71+Portfolio!$C$11*Engine!J83+Portfolio!$C$12*Engine!J95+Portfolio!$C$13*Engine!J107+Portfolio!$C$14*Engine!J119+Portfolio!$C$15*Engine!J131+Portfolio!$C$16*Engine!J143+Portfolio!$C$17*Engine!J155) -> 89084.672 | K23: =(Portfolio!$C$5*Engine!K11+Portfolio!$C$6*Engine!K23+Portfolio!$C$7*Engine!K35+Portfolio!$C$8*Engine!K47+Portfolio!$C$9*Engine!K59+Portfolio!$C$10*Engine!K71+Portfolio!$C$11*Engine!K83+Portfolio!$C$12*Engine!K95+Portfolio!$C$13*Engine!K107+Portfolio!$C$14*Engine!K119+Portfolio!$C$15*Engine!K131+Portfolio!$C$16*Engine!K143+Portfolio!$C$17*Engine!K155) -> 88947.552 | ... AH23: =(Portfolio!$C$5*Engine!AH11+Portfolio!$C$6*Engine!AH23+Portfolio!$C$7*Engine!AH35+Portfolio!$C$8*Engine!AH47+Portfolio!$C$9*Engine!AH59+Portfolio!$C$10*Engine!AH71+Portfolio!$C$11*Engine!AH83+Portfolio!$C$12*Engine!AH95+Portfolio!$C$13*Engine!AH107+Portfolio!$C$14*Engine!AH119+Portfolio!$C$15*Engine!AH131+Portfolio!$C$16*Engine!AH143+Portfolio!$C$17*Engine!AH155) -> 85976.258
A24: Interaction: flood works reduce insurance recoveries | C24: =SUMPRODUCT(D24:AH24,Engine!D$5:AH$5) -> 0 | D24: =-Portfolio!$C$10*Portfolio!$C$17*(1-in_N05)*IF(D$19=0,0,in_H05*(c_rec0-c_rec1)) -> 0 | E24: =-Portfolio!$C$10*Portfolio!$C$17*(1-in_N05)*IF(E$19=0,0,in_H05*(c_rec0-c_rec1)) -> 0 | F24: =-Portfolio!$C$10*Portfolio!$C$17*(1-in_N05)*IF(F$19=0,0,in_H05*(c_rec0-c_rec1)) -> 0 | G24: =-Portfolio!$C$10*Portfolio!$C$17*(1-in_N05)*IF(G$19=0,0,in_H05*(c_rec0-c_rec1)) -> 0 | H24: =-Portfolio!$C$10*Portfolio!$C$17*(1-in_N05)*IF(H$19=0,0,in_H05*(c_rec0-c_rec1)) -> 0 | I24: =-Portfolio!$C$10*Portfolio!$C$17*(1-in_N05)*IF(I$19=0,0,in_H05*(c_rec0-c_rec1)) -> 0 | J24: =-Portfolio!$C$10*Portfolio!$C$17*(1-in_N05)*IF(J$19=0,0,in_H05*(c_rec0-c_rec1)) -> 0 | K24: =-Portfolio!$C$10*Portfolio!$C$17*(1-in_N05)*IF(K$19=0,0,in_H05*(c_rec0-c_rec1)) -> 0 | ... AH24: =-Portfolio!$C$10*Portfolio!$C$17*(1-in_N05)*IF(AH$19=0,0,in_H05*(c_rec0-c_rec1)) -> 0
A25: Interaction: battery redundant when genset is on | C25: =SUMPRODUCT(D25:AH25,Engine!D$5:AH$5) -> 0 | D25: =-Portfolio!$C$12*Portfolio!$C$14*Engine!D95 -> 0 | E25: =-Portfolio!$C$12*Portfolio!$C$14*Engine!E95 -> 0 | F25: =-Portfolio!$C$12*Portfolio!$C$14*Engine!F95 -> 0 | G25: =-Portfolio!$C$12*Portfolio!$C$14*Engine!G95 -> 0 | H25: =-Portfolio!$C$12*Portfolio!$C$14*Engine!H95 -> 0 | I25: =-Portfolio!$C$12*Portfolio!$C$14*Engine!I95 -> 0 | J25: =-Portfolio!$C$12*Portfolio!$C$14*Engine!J95 -> 0 | K25: =-Portfolio!$C$12*Portfolio!$C$14*Engine!K95 -> 0 | ... AH25: =-Portfolio!$C$12*Portfolio!$C$14*Engine!AH95 -> 0
A26: Interaction: PPA and owned PV are alternatives | C26: =SUMPRODUCT(D26:AH26,Engine!D$5:AH$5) -> 0 | D26: =-Portfolio!$C$11*Portfolio!$C$13*Engine!D107 -> 0 | E26: =-Portfolio!$C$11*Portfolio!$C$13*Engine!E107 -> 0 | F26: =-Portfolio!$C$11*Portfolio!$C$13*Engine!F107 -> 0 | G26: =-Portfolio!$C$11*Portfolio!$C$13*Engine!G107 -> 0 | H26: =-Portfolio!$C$11*Portfolio!$C$13*Engine!H107 -> 0 | I26: =-Portfolio!$C$11*Portfolio!$C$13*Engine!I107 -> 0 | J26: =-Portfolio!$C$11*Portfolio!$C$13*Engine!J107 -> 0 | K26: =-Portfolio!$C$11*Portfolio!$C$13*Engine!K107 -> 0 | ... AH26: =-Portfolio!$C$11*Portfolio!$C$13*Engine!AH107 -> 0
A27: Opex | C27: =SUMPRODUCT(D27:AH27,Engine!D$5:AH$5) -> 163060.3 | D27: =(Portfolio!$C$5*Engine!D12+Portfolio!$C$6*Engine!D24+Portfolio!$C$7*Engine!D36+Portfolio!$C$8*Engine!D48+Portfolio!$C$9*Engine!D60+Portfolio!$C$10*Engine!D72+Portfolio!$C$11*Engine!D84+Portfolio!$C$12*Engine!D96+Portfolio!$C$13*Engine!D108+Portfolio!$C$14*Engine!D120+Portfolio!$C$15*Engine!D132+Portfolio!$C$16*Engine!D144+Portfolio!$C$17*Engine!D156) -> 0 | E27: =(Portfolio!$C$5*Engine!E12+Portfolio!$C$6*Engine!E24+Portfolio!$C$7*Engine!E36+Portfolio!$C$8*Engine!E48+Portfolio!$C$9*Engine!E60+Portfolio!$C$10*Engine!E72+Portfolio!$C$11*Engine!E84+Portfolio!$C$12*Engine!E96+Portfolio!$C$13*Engine!E108+Portfolio!$C$14*Engine!E120+Portfolio!$C$15*Engine!E132+Portfolio!$C$16*Engine!E144+Portfolio!$C$17*Engine!E156) -> 21753.981 | F27: =(Portfolio!$C$5*Engine!F12+Portfolio!$C$6*Engine!F24+Portfolio!$C$7*Engine!F36+Portfolio!$C$8*Engine!F48+Portfolio!$C$9*Engine!F60+Portfolio!$C$10*Engine!F72+Portfolio!$C$11*Engine!F84+Portfolio!$C$12*Engine!F96+Portfolio!$C$13*Engine!F108+Portfolio!$C$14*Engine!F120+Portfolio!$C$15*Engine!F132+Portfolio!$C$16*Engine!F144+Portfolio!$C$17*Engine!F156) -> 21753.981 | G27: =(Portfolio!$C$5*Engine!G12+Portfolio!$C$6*Engine!G24+Portfolio!$C$7*Engine!G36+Portfolio!$C$8*Engine!G48+Portfolio!$C$9*Engine!G60+Portfolio!$C$10*Engine!G72+Portfolio!$C$11*Engine!G84+Portfolio!$C$12*Engine!G96+Portfolio!$C$13*Engine!G108+Portfolio!$C$14*Engine!G120+Portfolio!$C$15*Engine!G132+Portfolio!$C$16*Engine!G144+Portfolio!$C$17*Engine!G156) -> 21753.981 | H27: =(Portfolio!$C$5*Engine!H12+Portfolio!$C$6*Engine!H24+Portfolio!$C$7*Engine!H36+Portfolio!$C$8*Engine!H48+Portfolio!$C$9*Engine!H60+Portfolio!$C$10*Engine!H72+Portfolio!$C$11*Engine!H84+Portfolio!$C$12*Engine!H96+Portfolio!$C$13*Engine!H108+Portfolio!$C$14*Engine!H120+Portfolio!$C$15*Engine!H132+Portfolio!$C$16*Engine!H144+Portfolio!$C$17*Engine!H156) -> 21753.981 | I27: =(Portfolio!$C$5*Engine!I12+Portfolio!$C$6*Engine!I24+Portfolio!$C$7*Engine!I36+Portfolio!$C$8*Engine!I48+Portfolio!$C$9*Engine!I60+Portfolio!$C$10*Engine!I72+Portfolio!$C$11*Engine!I84+Portfolio!$C$12*Engine!I96+Portfolio!$C$13*Engine!I108+Portfolio!$C$14*Engine!I120+Portfolio!$C$15*Engine!I132+Portfolio!$C$16*Engine!I144+Portfolio!$C$17*Engine!I156) -> 21753.981 | J27: =(Portfolio!$C$5*Engine!J12+Portfolio!$C$6*Engine!J24+Portfolio!$C$7*Engine!J36+Portfolio!$C$8*Engine!J48+Portfolio!$C$9*Engine!J60+Portfolio!$C$10*Engine!J72+Portfolio!$C$11*Engine!J84+Portfolio!$C$12*Engine!J96+Portfolio!$C$13*Engine!J108+Portfolio!$C$14*Engine!J120+Portfolio!$C$15*Engine!J132+Portfolio!$C$16*Engine!J144+Portfolio!$C$17*Engine!J156) -> 21753.981 | K27: =(Portfolio!$C$5*Engine!K12+Portfolio!$C$6*Engine!K24+Portfolio!$C$7*Engine!K36+Portfolio!$C$8*Engine!K48+Portfolio!$C$9*Engine!K60+Portfolio!$C$10*Engine!K72+Portfolio!$C$11*Engine!K84+Portfolio!$C$12*Engine!K96+Portfolio!$C$13*Engine!K108+Portfolio!$C$14*Engine!K120+Portfolio!$C$15*Engine!K132+Portfolio!$C$16*Engine!K144+Portfolio!$C$17*Engine!K156) -> 21753.981 | ... AH27: =(Portfolio!$C$5*Engine!AH12+Portfolio!$C$6*Engine!AH24+Portfolio!$C$7*Engine!AH36+Portfolio!$C$8*Engine!AH48+Portfolio!$C$9*Engine!AH60+Portfolio!$C$10*Engine!AH72+Portfolio!$C$11*Engine!AH84+Portfolio!$C$12*Engine!AH96+Portfolio!$C$13*Engine!AH108+Portfolio!$C$14*Engine!AH120+Portfolio!$C$15*Engine!AH132+Portfolio!$C$16*Engine!AH144+Portfolio!$C$17*Engine!AH156) -> 21753.981
A28: Operating flow | C28: =SUMPRODUCT(D28:AH28,Engine!D$5:AH$5) -> 558562.14 | D28: =D22+D23+D24+D25+D26-D27 -> 0 | E28: =E22+E23+E24+E25+E26-E27 -> 74031.509 | F28: =F22+F23+F24+F25+F26-F27 -> 73890.909 | G28: =G22+G23+G24+G25+G26-G27 -> 73751.012 | H28: =H22+H23+H24+H25+H26-H27 -> 73611.814 | I28: =I22+I23+I24+I25+I26-I27 -> 73473.312 | J28: =J22+J23+J24+J25+J26-J27 -> 73335.503 | K28: =K22+K23+K24+K25+K26-K27 -> 73198.383 | ... AH28: =AH22+AH23+AH24+AH25+AH26-AH27 -> 82970.591
A29: Tax | C29: =SUMPRODUCT(D29:AH29,Engine!D$5:AH$5) -> 26317.586 | D29: =Engine!D$4*MAX(0,D28) -> 0 | E29: =Engine!E$4*MAX(0,E28) -> 0 | F29: =Engine!F$4*MAX(0,F28) -> 0 | G29: =Engine!G$4*MAX(0,G28) -> 0 | H29: =Engine!H$4*MAX(0,H28) -> 0 | I29: =Engine!I$4*MAX(0,I28) -> 0 | J29: =Engine!J$4*MAX(0,J28) -> 0 | K29: =Engine!K$4*MAX(0,K28) -> 0 | ... AH29: =Engine!AH$4*MAX(0,AH28) -> 13690.148
A30: Free cash flow | C30: =SUMPRODUCT(D30:AH30,Engine!D$5:AH$5) -> 260114.9 | D30: =(D28-D21-D29)*D20 -> -191192.8 | E30: =(E28-E21-E29)*E20 -> 74031.509 | F30: =(F28-F21-F29)*F20 -> 73890.909 | G30: =(G28-G21-G29)*G20 -> 73751.012 | H30: =(H28-H21-H29)*H20 -> 73611.814 | I30: =(I28-I21-I29)*I20 -> 43473.312 | J30: =(J28-J21-J29)*J20 -> 73335.503 | K30: =(K28-K21-K29)*K20 -> 53198.383 | ... AH30: =(AH28-AH21-AH29)*AH20 -> 0
A31: Supplier income | C31: =SUMPRODUCT(D31:AH31,Engine!D$5:AH$5) -> 103654.42 | D31: =(Portfolio!$C$5*Engine!D16+Portfolio!$C$6*Engine!D28+Portfolio!$C$7*Engine!D40+Portfolio!$C$8*Engine!D52+Portfolio!$C$9*Engine!D64+Portfolio!$C$10*Engine!D76+Portfolio!$C$11*Engine!D88+Portfolio!$C$12*Engine!D100+Portfolio!$C$13*Engine!D112+Portfolio!$C$14*Engine!D124+Portfolio!$C$15*Engine!D136+Portfolio!$C$16*Engine!D148+Portfolio!$C$17*Engine!D160)*D20 -> 0 | E31: =(Portfolio!$C$5*Engine!E16+Portfolio!$C$6*Engine!E28+Portfolio!$C$7*Engine!E40+Portfolio!$C$8*Engine!E52+Portfolio!$C$9*Engine!E64+Portfolio!$C$10*Engine!E76+Portfolio!$C$11*Engine!E88+Portfolio!$C$12*Engine!E100+Portfolio!$C$13*Engine!E112+Portfolio!$C$14*Engine!E124+Portfolio!$C$15*Engine!E136+Portfolio!$C$16*Engine!E148+Portfolio!$C$17*Engine!E160)*E20 -> 14755.6 | F31: =(Portfolio!$C$5*Engine!F16+Portfolio!$C$6*Engine!F28+Portfolio!$C$7*Engine!F40+Portfolio!$C$8*Engine!F52+Portfolio!$C$9*Engine!F64+Portfolio!$C$10*Engine!F76+Portfolio!$C$11*Engine!F88+Portfolio!$C$12*Engine!F100+Portfolio!$C$13*Engine!F112+Portfolio!$C$14*Engine!F124+Portfolio!$C$15*Engine!F136+Portfolio!$C$16*Engine!F148+Portfolio!$C$17*Engine!F160)*F20 -> 14755.6 | G31: =(Portfolio!$C$5*Engine!G16+Portfolio!$C$6*Engine!G28+Portfolio!$C$7*Engine!G40+Portfolio!$C$8*Engine!G52+Portfolio!$C$9*Engine!G64+Portfolio!$C$10*Engine!G76+Portfolio!$C$11*Engine!G88+Portfolio!$C$12*Engine!G100+Portfolio!$C$13*Engine!G112+Portfolio!$C$14*Engine!G124+Portfolio!$C$15*Engine!G136+Portfolio!$C$16*Engine!G148+Portfolio!$C$17*Engine!G160)*G20 -> 14755.6 | H31: =(Portfolio!$C$5*Engine!H16+Portfolio!$C$6*Engine!H28+Portfolio!$C$7*Engine!H40+Portfolio!$C$8*Engine!H52+Portfolio!$C$9*Engine!H64+Portfolio!$C$10*Engine!H76+Portfolio!$C$11*Engine!H88+Portfolio!$C$12*Engine!H100+Portfolio!$C$13*Engine!H112+Portfolio!$C$14*Engine!H124+Portfolio!$C$15*Engine!H136+Portfolio!$C$16*Engine!H148+Portfolio!$C$17*Engine!H160)*H20 -> 14755.6 | I31: =(Portfolio!$C$5*Engine!I16+Portfolio!$C$6*Engine!I28+Portfolio!$C$7*Engine!I40+Portfolio!$C$8*Engine!I52+Portfolio!$C$9*Engine!I64+Portfolio!$C$10*Engine!I76+Portfolio!$C$11*Engine!I88+Portfolio!$C$12*Engine!I100+Portfolio!$C$13*Engine!I112+Portfolio!$C$14*Engine!I124+Portfolio!$C$15*Engine!I136+Portfolio!$C$16*Engine!I148+Portfolio!$C$17*Engine!I160)*I20 -> 14755.6 | J31: =(Portfolio!$C$5*Engine!J16+Portfolio!$C$6*Engine!J28+Portfolio!$C$7*Engine!J40+Portfolio!$C$8*Engine!J52+Portfolio!$C$9*Engine!J64+Portfolio!$C$10*Engine!J76+Portfolio!$C$11*Engine!J88+Portfolio!$C$12*Engine!J100+Portfolio!$C$13*Engine!J112+Portfolio!$C$14*Engine!J124+Portfolio!$C$15*Engine!J136+Portfolio!$C$16*Engine!J148+Portfolio!$C$17*Engine!J160)*J20 -> 14755.6 | K31: =(Portfolio!$C$5*Engine!K16+Portfolio!$C$6*Engine!K28+Portfolio!$C$7*Engine!K40+Portfolio!$C$8*Engine!K52+Portfolio!$C$9*Engine!K64+Portfolio!$C$10*Engine!K76+Portfolio!$C$11*Engine!K88+Portfolio!$C$12*Engine!K100+Portfolio!$C$13*Engine!K112+Portfolio!$C$14*Engine!K124+Portfolio!$C$15*Engine!K136+Portfolio!$C$16*Engine!K148+Portfolio!$C$17*Engine!K160)*K20 -> 14755.6 | ... AH31: =(Portfolio!$C$5*Engine!AH16+Portfolio!$C$6*Engine!AH28+Portfolio!$C$7*Engine!AH40+Portfolio!$C$8*Engine!AH52+Portfolio!$C$9*Engine!AH64+Portfolio!$C$10*Engine!AH76+Portfolio!$C$11*Engine!AH88+Portfolio!$C$12*Engine!AH100+Portfolio!$C$13*Engine!AH112+Portfolio!$C$14*Engine!AH124+Portfolio!$C$15*Engine!AH136+Portfolio!$C$16*Engine!AH148+Portfolio!$C$17*Engine!AH160)*AH20 -> 0

Sheet Results
A1: Results: factory NPV, supplier income and break-even by option
A2: ="Scenario: "&CHOOSE(in_G09,"Benign","Base","Stress")&" · Discount rate "&TEXT(in_G01,"0.0%")&" real · Margin basis: "&IF(in_C11=1,"bulk benchmark","value chain blend")&" · Carbon "&IF(in_G08=1,"included","excluded") -> Scenario: Base · Discount rate 13.0% real · Margin basis: value chain blend · Carbon excluded
A4: ID | B4: Option | C4: Factory NPV | D4: Capex (PV) | E4: Supplier income PV | F4: Factory + supplier NPV | G4: PV supply benefit | H4: Break-even value of a secured tonne | I4: Rank | J4: Reading
A5: 1 | B5: 1 Solar irrigation (nurseries + gardens) | C5: =Engine!C15 -> -135111.79 | D5: =Engine!C9 -> 125961.4 | E5: =Engine!C16 -> 70247.516 | F5: =C5+E5 -> -64864.275 | G5: =Engine!C17 -> 6416.4597 | H5: =IF(G5>0,IF(C5>=0,"already positive",(G5-C5)/G5),"n/a") -> 22.057062 | I5: =RANK(C5,$C$5:$C$17) -> 13 | J5: =IF(C5>=0,"Adds value on factory cash alone",IF(F5>=0,"Positive only with supplier income","Does not pay at these inputs")) -> Does not pay at these inputs
A6: 2 | B6: 2 Apiaries | C6: =Engine!C27 -> -31252.925 | D6: =Engine!C21 -> 32114.744 | E6: =Engine!C28 -> 60381.955 | F6: =C6+E6 -> 29129.03 | G6: =Engine!C29 -> 895.01088 | H6: =IF(G6>0,IF(C6>=0,"already positive",(G6-C6)/G6),"n/a") -> 35.919044 | I6: =RANK(C6,$C$5:$C$17) -> 7 | J6: =IF(C6>=0,"Adds value on factory cash alone",IF(F6>=0,"Positive only with supplier income","Does not pay at these inputs")) -> Positive only with supplier income
A7: 3 | B7: 3 Regeneration & agroforestry | C7: =Engine!C39 -> -45446.693 | D7: =Engine!C33 -> 49410.085 | E7: =Engine!C40 -> 0 | F7: =C7+E7 -> -45446.693 | G7: =Engine!C41 -> 4746.5774 | H7: =IF(G7>0,IF(C7>=0,"already positive",(G7-C7)/G7),"n/a") -> 10.574624 | I7: =RANK(C7,$C$5:$C$17) -> 9 | J7: =IF(C7>=0,"Adds value on factory cash alone",IF(F7>=0,"Positive only with supplier income","Does not pay at these inputs")) -> Does not pay at these inputs
A8: 4 | B8: 4 Biochar at village processing centres | C8: =Engine!C51 -> -126156.42 | D8: =Engine!C45 -> 25000 | E8: =Engine!C52 -> 0 | F8: =C8+E8 -> -126156.42 | G8: =Engine!C53 -> 0 | H8: =IF(G8>0,IF(C8>=0,"already positive",(G8-C8)/G8),"n/a") -> n/a | I8: =RANK(C8,$C$5:$C$17) -> 12 | J8: =IF(C8>=0,"Adds value on factory cash alone",IF(F8>=0,"Positive only with supplier income","Does not pay at these inputs")) -> Does not pay at these inputs
A9: 5 | B9: 5 Processing stoves for butter suppliers | C9: =Engine!C63 -> -43059.931 | D9: =Engine!C57 -> 59917.171 | E9: =Engine!C64 -> 43272.47 | F9: =C9+E9 -> 212.53874 | G9: =Engine!C65 -> 18222.421 | H9: =IF(G9>0,IF(C9>=0,"already positive",(G9-C9)/G9),"n/a") -> 3.3630192 | I9: =RANK(C9,$C$5:$C$17) -> 8 | J9: =IF(C9>=0,"Adds value on factory cash alone",IF(F9>=0,"Positive only with supplier income","Does not pay at these inputs")) -> Positive only with supplier income
A10: 6 | B10: 6 Flood drainage, detention, plinths | C10: =Engine!C75 -> -66504.117 | D10: =Engine!C69 -> 117325 | E10: =Engine!C76 -> 0 | F10: =C10+E10 -> -66504.117 | G10: =Engine!C77 -> 0 | H10: =IF(G10>0,IF(C10>=0,"already positive",(G10-C10)/G10),"n/a") -> n/a | I10: =RANK(C10,$C$5:$C$17) -> 10 | J10: =IF(C10>=0,"Adds value on factory cash alone",IF(F10>=0,"Positive only with supplier income","Does not pay at these inputs")) -> Does not pay at these inputs
A11: 7a | B11: 7a Solar PV, grid-tied | C11: =Engine!C87 -> 72102.621 | D11: =Engine!C81 -> 102768.47 | E11: =Engine!C88 -> 0 | F11: =C11+E11 -> 72102.621 | G11: =Engine!C89 -> 0 | H11: =IF(G11>0,IF(C11>=0,"already positive",(G11-C11)/G11),"n/a") -> n/a | I11: =RANK(C11,$C$5:$C$17) -> 3 | J11: =IF(C11>=0,"Adds value on factory cash alone",IF(F11>=0,"Positive only with supplier income","Does not pay at these inputs")) -> Adds value on factory cash alone
A12: 7b | B12: 7b Battery + islanding (critical loads) | C12: =Engine!C99 -> 22445.393 | D12: =Engine!C93 -> 95804.907 | E12: =Engine!C100 -> 0 | F12: =C12+E12 -> 22445.393 | G12: =Engine!C101 -> 0 | H12: =IF(G12>0,IF(C12>=0,"already positive",(G12-C12)/G12),"n/a") -> n/a | I12: =RANK(C12,$C$5:$C$17) -> 5 | J12: =IF(C12>=0,"Adds value on factory cash alone",IF(F12>=0,"Positive only with supplier income","Does not pay at these inputs")) -> Adds value on factory cash alone
A13: 7c | B13: 7c Solar PPA (no capex) | C13: =Engine!C111 -> 37002.518 | D13: =Engine!C105 -> 0 | E13: =Engine!C112 -> 0 | F13: =C13+E13 -> 37002.518 | G13: =Engine!C113 -> 0 | H13: =IF(G13>0,IF(C13>=0,"already positive",(G13-C13)/G13),"n/a") -> n/a | I13: =RANK(C13,$C$5:$C$17) -> 4 | J13: =IF(C13>=0,"Adds value on factory cash alone",IF(F13>=0,"Positive only with supplier income","Does not pay at these inputs")) -> Adds value on factory cash alone
A14: 7d | B14: 7d Diesel genset (comparator) | C14: =Engine!C123 -> 139263.34 | D14: =Engine!C117 -> 19928.574 | E14: =Engine!C124 -> 0 | F14: =C14+E14 -> 139263.34 | G14: =Engine!C125 -> 0 | H14: =IF(G14>0,IF(C14>=0,"already positive",(G14-C14)/G14),"n/a") -> n/a | I14: =RANK(C14,$C$5:$C$17) -> 1 | J14: =IF(C14>=0,"Adds value on factory cash alone",IF(F14>=0,"Positive only with supplier income","Does not pay at these inputs")) -> Adds value on factory cash alone
A15: 8 | B15: 8 Mango toll pilot (substitution hedge) | C15: =Engine!C135 -> 123164.62 | D15: =Engine!C129 -> 25000 | E15: =Engine!C136 -> 0 | F15: =C15+E15 -> 123164.62 | G15: =Engine!C137 -> 29943.479 | H15: =IF(G15>0,IF(C15>=0,"already positive",(G15-C15)/G15),"n/a") -> already positive | I15: =RANK(C15,$C$5:$C$17) -> 2 | J15: =IF(C15>=0,"Adds value on factory cash alone",IF(F15>=0,"Positive only with supplier income","Does not pay at these inputs")) -> Adds value on factory cash alone
A16: 9 | B16: 9 Community fire management | C16: =Engine!C147 -> -98388.993 | D16: =Engine!C141 -> 15000 | E16: =Engine!C148 -> 0 | F16: =C16+E16 -> -98388.993 | G16: =Engine!C149 -> 11540.082 | H16: =IF(G16>0,IF(C16>=0,"already positive",(G16-C16)/G16),"n/a") -> 9.5258488 | I16: =RANK(C16,$C$5:$C$17) -> 11 | J16: =IF(C16>=0,"Adds value on factory cash alone",IF(F16>=0,"Positive only with supplier income","Does not pay at these inputs")) -> Does not pay at these inputs
A17: 10 | B17: 10 Insurance: property incl. flood + BI | C17: =Engine!C159 -> 1427.051 | D17: =Engine!C153 -> 0 | E17: =Engine!C160 -> 0 | F17: =C17+E17 -> 1427.051 | G17: =Engine!C161 -> 0 | H17: =IF(G17>0,IF(C17>=0,"already positive",(G17-C17)/G17),"n/a") -> n/a | I17: =RANK(C17,$C$5:$C$17) -> 6 | J17: =IF(C17>=0,"Adds value on factory cash alone",IF(F17>=0,"Positive only with supplier income","Does not pay at these inputs")) -> Adds value on factory cash alone
B19: Selected portfolio (Portfolio sheet) | C19: =p_npv -> 260114.9 | F19: =p_npv_cons -> 363769.33
B20: Break-even multiple: how many times more a secured tonne must be worth for the option to break even (approximate; ignores tax after the holiday).
B22: Key quantities
B23: Margin per t crude butter | C23: =c_margin -> 5215.4542
B24: Value of a secured tonne | C24: =c_VST -> 2037.1363
B25: Baseline supply loss, year 1 | C25: =Supply!E7 -> 36668.453
B26: Sourcing area (ha) | C26: =c_catch -> 6756.7568
B27: Baseline outage cost per year | C27: =c_out_cost -> 33910.162
B28: Outage cost as share of sales | C28: =c_out_pct -> 0.0060926854
B29: Loss per flood without measures | C29: =c_floss0 -> 123290.91
B30: Expected flood loss per year | C30: =in_H05*c_floss0 -> 12329.091
B31: Share of jar price staying in Ghana (weighted) | C31: ='Value chain'!D49 -> 0.30993287
B32: Share of total revenue staying in Ghana | C32: ='Value chain'!B61 -> 0.39967343
B33: Retail jars per year | C33: =c_units -> 354940.21
B34: Total revenue per year | C34: =c_sales -> 5565716.9

Sheet Checks
A1: Model checks
A3: Check | B3: Value | C3: Status | D3: What it guards against
A4: Outage cost within 0–10% of sales | B4: =c_out_pct -> 0.0060926854 | C4: =IF(AND(B4>=0,B4<=0.1),"OK","CHECK") -> OK | D4: Outage losses out of line with what Ghanaian firms report (WBES 2023)
A5: Insurance recovery ≤ flood loss | B5: =c_rec0-c_floss0 -> -44887.473 | C5: =IF(B5<=0,"OK","CHECK") -> OK | D5: Recovering more than the loss
A6: All shares between 0 and 1 | B6: =SUMPRODUCT((Inputs!I5:I400<0)*(LEFT(Inputs!D5:D400,1)="%"))+SUMPRODUCT((Inputs!I5:I400>1)*(LEFT(Inputs!D5:D400,1)="%")) -> 0 | C6: =IF(B6=0,"OK","CHECK") -> OK | D6: A percentage input outside 0–100%
A7: Decline rate stays ≥ 0 with options | B7: =MIN(Supply!B31,Supply!B45,Supply!B52) -> 0.0135 | C7: =IF(B7>=0,"OK","CHECK") -> OK | D7: Options cutting tree loss below zero
A8: Brand margin per Amazon jar is positive | B8: ='Value chain'!$B$28 -> 2.6330917 | C8: =IF(B8>0,"OK","CHECK") -> OK | D8: Amazon channel losing money per jar
A9: Value chain sums to retail price | B9: ='Value chain'!B29-in_V01 -> 0 | C9: =IF(ABS(B9)<0.005,"OK","CHECK") -> OK | D9: Missing or double-counted cost lines
A10: PV output ≤ factory electricity use | B10: =in_E09*in_E02-in_C08*1000 -> -102000 | C10: =IF(B10<=0,"OK","CHECK") -> OK | D10: Counting exported solar as savings
A11: Battery and genset not both counted | B11: =Portfolio!C25 -> 0 | C11: =IF(OR(Portfolio!C12*Portfolio!C14=0,B11<0),"OK","CHECK") -> OK | D11: Double-counting outage protection
A12: Portfolio with nothing selected returns zero | B12: =SUM(Portfolio!C5:C17) -> 6 | C12: =IF(B12>0,"n/a (options selected)","OK") -> n/a (options selected) | D12: Engine produces value from nothing
A13: Carbon off in base case | B13: =in_G08 -> 0 | C13: =IF(B13=0,"OK","NOTE: carbon on") -> OK | D13: Counting unsigned carbon revenue

Sheet Gates
A1: Decision gates: evidence each option must show before scaling
A3: Option | B3: Gate before scaling | C3: Inputs it replaces | D3: Status
A4: 6 Flood | B4: Topographic survey and flood-map depth; working outfall | C4: H05, H06, D07 | D4: Open
A5: 7b/7d Backup power | B5: 12-month load and outage log; genset and battery quotes | C5: E06a, E07, E10, H08, H10 | D5: Open
A6: 10 Insurance | B6: Broker quotes for property with flood and business interruption | C6: N01–N04 | D6: Open
A7: 5 Stoves | B7: Fuel tests in suppliers' centres; continued use after 6 months | C7: S01, S02, S07, S09 | D7: Open
A8: 9 Fire | B8: Community agreements; burned-area monitoring | C8: F03, F04, F06 | D8: Open
A9: 2 Apiaries | B9: Occupied colonies; accepted wax batches; wax quote | C9: A04, A09 | D9: Open
A10: 3 Regeneration | B10: Land and collector rights; survival through two dry seasons | C10: R03, R06 | D10: Open
A11: 1 Irrigation | B11: Drought-season water yield; Water Resources Commission authorization | C11: I02, I04 | D11: Open
A12: 4 Biochar | B12: Lab test of cake char; signed credit buyer | C12: B02, B06, B07 | D12: Open
A13: 8 Diversification | B13: Toll yield trial; formulation tests; processor seed volumes | C13: M01b, M04, M05, M06 | D13: Open
A14: Value chain | B14: Amazon Revenue Calculator for your jar; forwarder freight quote; current US tariff on Ghana | C14: V12, V14, V22, V23 | D14: Open

Sheet Source audit
A1: Source audit: errors found in earlier sources, and the independent spot-check
A3: Source | B3: Problem found and how the model handles it | C3: Affects
A4: Fire Ecology 2023 (Dahan, Kasei & Husseini) | B4: Cited as 'Husseini et al.'; '825 km²/yr' is the 2018 value ÷ 24, '19,811 km²' exceeds the study area, '60%' is a share between two zones. None used. | C4: H03
A5: '9.4 million shea trees in Ghana' | B5: Same sentence says they yield 100 t of nuts against 130,000–150,000 t collected. Dropped. | C5: H04
A6: UN-REDD '77% loss' | B6: Forest cover, not shea trees; conflicts with 40% elsewhere. Dropped. | C6: H04
A7: UNDP 70% survival | B7: A project target, not a result. | C7: R03
A8: Darwin Initiative DAR30001 | B8: Eastern Region, mixed species, under one year; no burned-area comparison. | C8: R03, A07
A9: OCL '5 kg kernel per tree' | B9: An assumption used for a regional total; measured parkland mean ~4 kg. | C9: R05
A10: Stout et al. 2018 | B10: Compares open vs bagged flowers, not hives vs none; cannot support an apiary yield gain. | C10: A06
A11: Hive cost GH₵750 | B11: 2017 price converted at 2026 exchange rate; understates cost ~2–2.5×. | C11: A01
A12: Swisscontact biochar | B12: Not about shea; its throughput implies a 52–137% char yield. | C12: B07
A13: Cogent Engineering 2024 | B13: Shea shells, not cake; no char yield in the abstract. | C13: B02
A14: Puro.earth index page | B14: Stale (Nov 2024) and in euros. | C14: B06
... A22: Uganda Investment Authority shea profile | B22: USD 85,000 for 2,000 t/yr is implausible. Not used. | C22: C07
A25: Independent spot-check (24 sources re-opened)
A26: Claim | B26: Exact text found | C26: Verdict | D26: URL
A27: PURC NR 301+ 224.0395; SLT-LV 240.2104; SLT-MV 208.6329 GHp/kWh; eff. 1 Jul 2026 | B27: "301+ - (GHp/kWh) 224.0395"; SLT-LV "Energy Charge - (GHp/kWh) 240.2104"; SLT-MV "208.6329"; "1st July, 2026" | C27: MATCH
A28: Tema PVOUT ~1514 kWh/kWp | B28: PVOUT = 1514.36 kWh/kWp (annual) | C28: MATCH
A29: Diesel floor GH¢17.97/L Oct 2026; could reach GH¢19.60 | B29: "floor for diesel has also increased from GH¢16.77 to GH¢17.97 per litre"; "potentially reaching GH¢19.60 per litre" (1 Oct 2026; 19.60 is a COMAC projection) | C29: MATCH
A30: GCF FP137 Act. 1.4 budget $612,793; 220,000 ha | B30: Activity 1.4 "Original Budget" $612,793.00 (remaining $399,592.63); "an additional 220,000 ha in which communities adopt improved fire management techniques" (target, not achieved) | C30: MATCH
A31: 2,863 of 16,556 seedlings (17.3%) survived | B31: "out of a total sample of 16,556 planted seedlings 2,863 (17.3%) survived" (sample from Greater Accra, Ashanti, Northern sites) | C31: MATCH
A32: Shea kernel ~4 kg/tree parklands, ~1.5 kg natural | B32: "around 4 kg·tree–1" vs "close to 1.5 kg·tree–1" | C32: MATCH
A33: Apiary proximity → immature fruit set, not mature; 500 m | B33: "significantly related to number of immature fruit set but not number of mature fruits"; within 500 m | C33: MATCH
A34: Beeswax 80 cedis/kg, honey 70 cedis/kg, Tamale 2026 | B34: "70 cedis (~$9 CDN) per kilogram of extracted honey"; beeswax "sold at 80 cedis/kg" (Sorigu/Yama centres, 2026 season) | C34: MATCH
A35: Dry-season tomato GM GHS 14,150/ha | B35: "Average gross margin after" GHS 14,150 per hectare (vs 4,555 before; FSRP-supported farmers) | C35: MATCH
A36: CORSIA cookstove ~USD 14.30; broad ~USD 4 | B36: Text: "above USD 14 so far in 2026, compared to a broader clean-cooking average of around USD 4"; 14.30 appears only in chart ("Eligible average $14.30"). Article 6 May 2026; Dec-26 futures USD 13.10 | C36: MATCH (chart)
A37: 2.67 tCO2e/t biochar; 74% after 100 yrs | B37: "(1.00 t* 75% C * (100% - 3% margin) * 44/12 =) 2.67 t CO2e"; "100 years after soil application, 74% of the original carbon..." (assumes 75% C) | C37: MATCH
A38: Coconut oil Aug 2026 USD 1,853/mt | B38: Row: "Coconut oil $/mt ... 1,979 1,924 1,853" under June/July/August 2026 (first fetch misread 1,979 as Aug; re-verified with headers) | C38: MATCH
... A50: 29 Jun 2026 flood rescues VALCO/Sentuo, Tema New Town | B50: Monday June 29, 2026; "Waterland, VALCO/Sentuo, Tema New Town, Afienya and Alajo" | C50: MATCH

Sheet Sources
A1: All sources (opened between 4 and 5 Oct 2026)
A3: Source | B3: URL | C3: Used by inputs
A4: ADB project appraisal guidance | B4: https://development.asia/summary/guidelines-economic-analysis-projects | C4: G02a, G02b
A5: AVSF Burkina | B5: https://www.avsf.org/app/uploads/2023/12/actions-innovantes_equite-_ugf_cnd_avsf_2019.pdf | C5: S02
A6: Adamon 2021 | B6: https://independent.academia.edu/DavidADAMON | C6: B01, B05, S07
A7: Agrilinks/IWMI | B7: https://agrilinks.org/post/cocoa-farmers-ghana-show-strong-interest-solar-based-irrigation-pump-costs-are-often-too-high | C7: I01, I09
A8: Ajala et al. 2019 | B8: https://doaj.org/article/73e0ffab0b6a4dd882aaedcc6ee0e28b | C8: B01, C01, C02, C13
A9: AllAfrica, Feb 2026 | B9: https://allafrica.com/stories/202602110580.html | C9: C07
A10: AllAfrica, Jun 2025 | B10: https://allafrica.com/stories/202506110147.html | C10: H04
A11: Amazon AWD pricing | B11: https://sell.amazon.com/programs/warehousing | C11: V16, V20, V21
A12: Amazon FBA page | B12: https://sell.amazon.com/fulfillment-by-amazon | C12: V22
A13: Amazon selling fees | B13: https://sell.amazon.com/pricing | C13: V24, V31, V32
A14: Amegayie 2022, Tema survey | B14: https://www.etd.ceu.edu/2022/amegayie_amos.pdf | C14: H07
... A143: Yen.com.gh, Aug 2026 | B143: https://yen.com.gh/ghana/309707-what-ghc50000-cover-starting-a-building-project-ghana/ | C143: D01

Sheet Sensitivity
A1: Sensitivity snapshot (static values)
A2: Static snapshot computed on 5 Oct 2026 by recalculating this workbook with each input at Low and High (all else at base). It does not update live.
A4: Factory NPV by option under each hazard scenario
A5: Option | B5: Benign | C5: Base | D5: Stress
A6: 1 Solar irrigation (nurseries + gardens) | B6: -139381.69 | C6: -135111.79 | D6: -124221.51
A7: 2 Apiaries | B7: -31826.57 | C7: -31252.925 | D7: -29779.682
A8: 3 Regeneration & agroforestry | B8: -49410.085 | C8: -45446.693 | D8: -42720.55
A9: 4 Biochar at village processing centres | B9: -126156.42 | C9: -126156.42 | D9: -126156.42
A10: 5 Processing stoves for butter suppliers | B10: -55785.249 | C10: -43059.931 | D10: -16559.653
A11: 6 Flood drainage, detention, plinths | B11: -115107.82 | C11: -66504.117 | D11: 594856.07
A12: 7a Solar PV, grid-tied | B12: 72102.621 | C12: 72102.621 | D12: 72102.621
A13: 7b Battery + islanding (critical loads) | B13: -76639.642 | C13: 22445.393 | D13: 443556.79
A14: 7c Solar PPA (no capex) | B14: 37002.518 | C14: 37002.518 | D14: 37002.518
A15: 7d Diesel genset (comparator) | B15: 7530.6292 | C15: 139263.34 | D15: 699127.36
A16: 8 Mango toll pilot (substitution hedge) | B16: 135716.99 | C16: 123164.62 | D16: 108075.81
A17: 9 Community fire management | B17: -107353.21 | C17: -98388.993 | D17: -81414.673
... A19: Default package (Portfolio sheet) | B19: 91651.663 | C19: 260114.9 | D19: 1265155
A22: What moves the default package NPV most (tornado)
A23: Input | B23: NPV at Low | C23: NPV at High | D23: Swing | E23: Base NPV | G23: Reading
A24: H08 Grid outage hours | B24: 128382.19 | C24: 819978.93 | D24: 691596.73 | E24: 260114.9 | G24: Package stays positive
A25: E07 Spoilage and restart per outage | B25: 182934.56 | C25: 646016.6 | D25: 463082.04 | E25: 260114.9 | G25: Package stays positive
A26: M02 Mango butter price ex-factory | B26: 126585.2 | C26: 447056.49 | D26: 320471.29 | E26: 260114.9 | G26: Package stays positive
A27: G01 Discount rate, real USD | B27: 384923.33 | C27: 176474.74 | D27: 208448.58 | E27: 260114.9 | G27: Package stays positive
A28: M01b Mango butter yield, solvent toll extraction | B28: 195892.88 | C28: 394651.3 | D28: 198758.42 | E28: 260114.9 | G28: Package stays positive
A29: H10 Average outage length | B29: 388748.8 | C29: 195797.95 | D29: 192950.85 | E29: 260114.9 | G29: Package stays positive
A30: H06 Flood depth without measures | B30: 239358.24 | C30: 401570.53 | D30: 162212.29 | E30: 260114.9 | G30: Package stays positive
A31: V01 Amazon US retail price, 8 oz shea body butter | B31: 219624.19 | C31: 327599.43 | D31: 107975.25 | E31: 260114.9 | G31: Package stays positive
A32: H05 Probability the Tema site floods | B32: 233610.63 | C32: 339627.72 | D32: 106017.09 | E32: 260114.9 | G32: Package stays positive
A33: C12 Share of butter sold as finished retail products | B33: 228434.33 | C33: 307635.77 | D33: 79201.439 | E33: 260114.9 | G33: Package stays positive
A34: C05 Unreplaceable share of a shortfall | B34: 245062.8 | C34: 290219.11 | D34: 45156.307 | E34: 260114.9 | G34: Package stays positive
A35: V25 Amazon advertising | B35: 280346.77 | C35: 236992.78 | D35: 43353.989 | E35: 260114.9 | G35: Package stays positive
... A46: E04 Diesel generation fuel cost | B46: 261967.23 | C46: 256641.79 | D46: 5325.4434 | E46: 260114.9 | G46: Package stays positive
